Workbook
Name access_method: glossary!#REF!
Name access_method: nametitle_modappl!#REF!
Name age_class_adult: glossary!$E$18
Name age_class_adult: nametitle_modappl!#REF!
Name age_class_juvenile: glossary!$E$41
Name age_class_juvenile: nametitle_modappl!#REF!
Name age_class_subadult_yearling: glossary!$E$64
Name age_class_subadult_yearling: nametitle_modappl!#REF!
Name age_class_subadult_youngofyear: glossary!$E$65
Name age_class_subadult_youngofyear: nametitle_modappl!#REF!
Name analyst: glossary!$E$20
Name analyst: nametitle_modappl!#REF!
Name animal_id: glossary!#REF!
Name animal_id: nametitle_modappl!#REF!
Name baitlure_audible_lure: glossary!$E$75
Name baitlure_audible_lure: nametitle_modappl!#REF!
Name baitlure_bait_lure_type: glossary!$E$21
Name baitlure_bait_lure_type: nametitle_modappl!#REF!
Name baitlure_lure: glossary!#REF!
Name baitlure_lure: nametitle_modappl!#REF!
Name baitlure_scent_lure: glossary!$E$117
Name baitlure_scent_lure: nametitle_modappl!#REF!
Name baitlure_visual_lure: glossary!$E$148
Name baitlure_visual_lure: nametitle_modappl!#REF!
Name batteries_replaced: glossary!#REF!
Name batteries_replaced: nametitle_modappl!#REF!
Name behaviour: glossary!#REF!
Name behaviour: nametitle_modappl!#REF!
Name camera_active_on_arrival: glossary!#REF!
Name camera_active_on_arrival: nametitle_modappl!#REF!
Name camera_active_on_departure: glossary!#REF!
Name camera_active_on_departure: nametitle_modappl!#REF!
Name camera_angle: glossary!$E$78
Name camera_angle: nametitle_modappl!#REF!
Name camera_attachment: glossary!#REF!
Name camera_attachment: nametitle_modappl!#REF!
Name camera_damaged: glossary!#REF!
Name camera_damaged: nametitle_modappl!#REF!
Name camera_days_per_camera_location: glossary!$E$79
Name camera_days_per_camera_location: nametitle_modappl!#REF!
Name camera_direction: glossary!#REF!
Name camera_direction: nametitle_modappl!#REF!
Name camera_height: glossary!$E$22
Name camera_height: nametitle_modappl!#REF!
Name camera_id: glossary!$E$23
Name camera_id: nametitle_modappl!#REF!
Name camera_location_characteristics: glossary!#REF!
Name camera_location_characteristics: nametitle_modappl!#REF!
Name camera_location_comments: glossary!#REF!
Name camera_location_comments: nametitle_modappl!#REF!
Name camera_location_name: glossary!$E$24
Name camera_location_name: nametitle_modappl!#REF!
Name camera_make: glossary!$E$25
Name camera_make: nametitle_modappl!#REF!
Name camera_model: glossary!$E$26
Name camera_model: nametitle_modappl!#REF!
Name camera_serial_number: glossary!$E$27
Name camera_serial_number: nametitle_modappl!#REF!
Name camera_spacing: glossary!$E$81
Name camera_spacing: nametitle_modappl!#REF!

Sheet FIX
A2: TOC | B2: 01_31_sp_size_multi
A3: TOC | B3: 01_51_num_det_individ
A5: tooltips | B5: [modelling approaches](#mod_approach)

Sheet ADD
A1: from | B1: from2 | C1: key | D1: field_text_upper | E1: definition | F1: tip_id_upper | G1: field_text_lower | H1: tip_id_lower | I1: tooltip | K1: lookup_exact
C2: covariate | D2: Covariate | F2: =C2&"_tu" -> covariate_tu | G2: =LOWER(D2) -> covariate | H2: =C2&"_tl" -> covariate_tl
C3: distribution | D3: Distribution | F3: =C3&"_tu" -> distribution_tu | G3: =LOWER(D3) -> distribution | H3: =C3&"_tl" -> distribution_tl
C4: independence | D4: Independence | F4: =C4&"_tu" -> independence_tu | G4: =LOWER(D4) -> independence | H4: =C4&"_tl" -> independence_tl
C5: home_range | D5: Home ranges | F5: =C5&"_tu" -> home_range_tu | G5: =LOWER(D5) -> home ranges | H5: =C5&"_tl" -> home_range_tl
C6: sp_accum_asymptote | D6: Species-accumulation asymptote | F6: =C6&"_tu" -> sp_accum_asymptote_tu | G6: =LOWER(D6) -> species-accumulation asymptote | H6: =C6&"_tl" -> sp_accum_asymptote_tl
C7: data_distr_para | D7: Parametric distribution | F7: =C7&"_tu" -> data_distr_para_tu | G7: =LOWER(D7) -> parametric distribution | H7: =C7&"_tl" -> data_distr_para_tl
C8: data_distr_poisson | D8: Poisson-distributed | F8: =C8&"_tu" -> data_distr_poisson_tu | G8: =LOWER(D8) -> poisson-distributed | H8: =C8&"_tl" -> data_distr_poisson_tl
C9: closure_demo | D9: Demographic closure | F9: =C9&"_tu" -> closure_demo_tu | G9: =LOWER(D9) -> demographic closure | H9: =C9&"_tl" -> closure_demo_tl
C10: closure_geo | D10: Geographic closure | F10: =C10&"_tu" -> closure_geo_tu | G10: =LOWER(D10) -> geographic closure | H10: =C10&"_tl" -> closure_geo_tl
C11: closure_site | D11: Site closure | E11: the assumption that there is no change in state (e.g. species presence/ absence, immigration/ emigration, births/deaths) during the {{ survey_tl }} period ({{ rtxt_mackenzie_et_al_2004 }}).
C12: activity_centre | D12: Animals’ activity centres
C13: asymptotic | D13: Asymptotic
C14: captures | D14: Captures
C15: recaptures | D15: Recaptures
C16: data_auxiliary | D16: Auxiliary data
C17: adhoc | D17: Ad-hoc
C18: evenness | D18: Evenness
C19: categorical_id | D19: Categorical identifiers
C20: phenotypic | D20: Phenotypic
C21: rate_surivival | D21: Survival rate
C22: spatially_explicit | D22: Spatially explicit
C23: rate_recruitment | D23: Recruitment rate
... C31: colonization | D31: Site colonization
D32: Temporal interactions
D33: Effective area of detection
D34: cryptic
D35: elusive

Sheet ISSUES
A1: id | B1: intext | C1: intext2 | D1: textbib | E1: embed_url
A3: We have no analysis considerations to recommend based on your selections!<br>However, that doesn't mean that there aren't important aspects to consider. Please think through your design carefully to identify potential sources of bias and error.<br><br>Here is an example of what you might see in this section:<br><b>Because you chose...<em><br>State variable:</b> "Relative abundance" or "Unknown"</b></em><br><b>>>></b> Note that when you reach the analysis stage, you will want to select a count model method that most appropriately accounts for "Zero-inflation" and "Overdispersion" (see sections "Overdispersion/Zero-inflation [not yet present] and "Mixed models" [not yet present]).
A4: Based on your selections, none of the modeling approaches were appropriate, please review your selections to consider less restrictive options.<br>You can also refer to [Appendix A - Table A2](https://ab-rcsc.github.io/RCSC-WildCAM_Remote-Camera-Survey-Guidelines-and-Metadata-Standards/1_survey-guidelines/1_10.1_AppendixA-Tables.html) of the Remote Camera Survey Guidelines (RCSC et al., 2024) to determine what might be too restrictive (e.g., if you only have 10 cameras, you will see that few approaches are appropriate).
A8: Distance sampling | B8: In our third edition of the SEEC Stats Toolbox Seminars David Maphisa and Florian Weller explained how to conduct distance sampling. This method relies on either point counts or transect counts in which the distance from the observer to each animal or plant is recorded. These data are then used to estimate density or abundance while reducing observation bias. | D8: https://science.uct.ac.za/seec/stats-toolbox-seminars-spatial-and-species-distribution-toolboxes/distance-sampling
A9: Whitlock, Michael, and Dolph Schluter. The Analysis of Biological Data. Third. Book, Whole. New York;Austin;Plymouth;Boston; Macmillan Learning, 2020.
A10: Estimating survival from CMR data | B10: Altwegg, R. (2020). *SEEC Toolbox on estimating survival from CMR data.* <https://science.uct.ac.za/seec/stats-toolbox-seminars-spatial-and-species-distribution-toolboxes/estimating-survival-cmr-data>
A11: ??? | B11: https://science.uct.ac.za/seec/stats-toolbox-seminars/spatial-and-species-distribution-toolboxes
A14: ~*~*<font size=“4”><span style=“color:#2F5496”>How does this relate to study design?</font></span>~*~* | B14: h_how_relate_study_design | C14: {{ header_ | D14: }}
A15: ~*~*<font size=“4”><span style=“color:#2F5496”>How does that work?</font></span>~*~* | B15: h_how_does_it_work | C15: {{ sub_header_ | D15: }}
A16: ~*~*<font size=“4”><span style=“color:#2F5496”>Why do we care?</font></span>~*~* | B16: h_why_does_it_matter | C16: {{ sub_header_ | D16: }}
C17: {{ sub_header_ | D17: }}
C18: {{ sub_header_ | D18: }}
C19: {{ sub_header_ | D19: }}

Sheet glossary
A1: note | B1: key_order | C1: key_type | D1: mod | E1: field_name_text_format | F1: only_upper | G1: from | H1: from2 | I1: key_ref | J1: key | K1: field_text_upper | L1: in_find_replace | M1: definition | N1: tooltip | O1: substitution | P1: substitution2 | Q1: blank | R1: mandatory | S1: metadata | T1: [survey](/09_glossary.md#survey) | U1: xx | V1: tip_f2 | W1: tip_f3 | X1: tip_f4 | Y1: tip_formula | Z1: access_method_tu: "<a href=\"09_glossary.html#access_method\" target=\"_blank\" data-bs-toggle=\"tooltip\" data-bs-title=\"Access Method: The method used to reach the camera location (e.g., on 'Foot,' 'ATV,' 'Helicopter,' etc.).\">Access Method<button type=\"button\" class=\"btn btn-bd-tip-info-hidden btn-sm position-relative\">.<span class=\"position-absolute top-0 start-100 translate-middle\">{{ icon_info }}</span></button></a>"
B2: 107 | C2: field | D2: - | E2: **\*# Of Images** | F2: upper | G2: surv_guide_meta | H2: cam_visit_equip | I2: number_of_images | J2: =IF(D2<>"-",I2&"_"&D2,I2) -> number_of_images | K2: # Of Images | L2: =IF(VLOOKUP(J2,find_replace!H:H,1,"false")=J2,"TRUE","FALSE") -> TRUE | M2: The number of images on an SD card. | N2: The number of images on an SD card. | O2: =IF(M2=999,"",(" term_"&J2&": """&K2&"""")) -> term_number_of_images: "# Of Images" | P2: =IF(M2="-","-",(" def_"&J2&": """&M2&"""")) -> def_number_of_images: "The number of images on an SD card." | R2: FALSE | S2: TRUE | T2: TRUE | U2: xx | V2: \" target=\"_blank\" data-bs-toggle=\"tooltip\" data-bs-title=\" | W2: \"> | X2: <button type=\"button\" class=\"btn btn-bd-tip-info-hidden btn-sm position-relative\">.<span class=\"position-absolute top-0 start-100 translate-middle\">{{ icon_info }}</span></button></a> | Y2: =IF(M2<>"-",(" "&J2&"_ti"&": "&""""&"<a href=\"&""""&"09_glossary.html#"&J2&V2&K2&": "&M2&W2&""&X2&""""),"-") -> number_of_images_ti: "<a href=\"09_glossary.html#number_of_images\" target=\"_blank\" data-bs-toggle=\"tooltip\" data-bs-title=\"# Of Images: The number of images on an SD card.\"><button type=\"button\" class=\"btn btn-bd-tip-info-hidden btn-sm position-relative\">.<span class=\"position-absolute top-0 start-100 translate-middle\">{{ icon_info }}</span></button></a>"
C3: term | D3: - | E3: Absolute abundance / Population size | G3: surv_guide_meta | H3: objective | I3: obj_abundance | J3: =IF(D3<>"-",I3&"_"&D3,I3) -> obj_abundance | K3: Absolute abundance / Population size | L3: =IF(VLOOKUP(J3,find_replace!H:H,1,"false")=J3,"TRUE","FALSE") -> TRUE | M3: The number of individuals in a population ({{ rtxt_wearn_gloverkapfer_2017 }}). | N3: The number of individuals in a population (Wearn & Glover-Kapfer, 2017). | O3: =IF(M3=999,"",(" term_"&J3&": """&K3&"""")) -> term_obj_abundance: "Absolute abundance / Population size" | P3: =IF(M3="-","-",(" def_"&J3&": """&M3&"""")) -> def_obj_abundance: "The number of individuals in a population ({{ rtxt_wearn_gloverkapfer_2017 }})." | U3: xx | V3: \" target=\"_blank\" data-bs-toggle=\"tooltip\" data-bs-title=\" | W3: \"> | X3: <button type=\"button\" class=\"btn btn-bd-tip-info-hidden btn-sm position-relative\">.<span class=\"position-absolute top-0 start-100 translate-middle\">{{ icon_info }}</span></button></a> | Y3: =IF(M3<>"-",(" "&J3&"_ti"&": "&""""&"<a href=\"&""""&"09_glossary.html#"&J3&V3&K3&": "&M3&W3&""&X3&""""),"-") -> obj_abundance_ti: "<a href=\"09_glossary.html#obj_abundance\" target=\"_blank\" data-bs-toggle=\"tooltip\" data-bs-title=\"Absolute abundance / Population size: The number of individuals in a population ({{ rtxt_wearn_gloverkapfer_2017 }}).\"><button type=\"button\" class=\"btn btn-bd-tip-info-hidden btn-sm position-relative\">.<span class=\"position-absolute top-0 start-100 translate-middle\">{{ icon_info }}</span></button></a>"
B4: 1 | C4: field | D4: - | E4: ***Access Method** | F4: upper | G4: surv_guide_meta | H4: cam_visit | I4: access_method | J4: =IF(D4<>"-",I4&"_"&D4,I4) -> access_method | K4: Access Method | L4: =IF(VLOOKUP(J4,find_replace!H:H,1,"false")=J4,"TRUE","FALSE") -> TRUE | M4: The method used to reach the camera location (e.g., on 'Foot,' 'ATV,' 'Helicopter,' etc.). | N4: The method used to reach the camera location (e.g., on 'Foot,' 'ATV,' 'Helicopter,' etc.). | O4: =IF(M4=999,"",(" term_"&J4&": """&K4&"""")) -> term_access_method: "Access Method" | P4: =IF(M4="-","-",(" def_"&J4&": """&M4&"""")) -> def_access_method: "The method used to reach the camera location (e.g., on 'Foot,' 'ATV,' 'Helicopter,' etc.)." | R4: FALSE | S4: TRUE | T4: TRUE | U4: xx | V4: \" target=\"_blank\" data-bs-toggle=\"tooltip\" data-bs-title=\" | W4: \"> | X4: <button type=\"button\" class=\"btn btn-bd-tip-info-hidden btn-sm position-relative\">.<span class=\"position-absolute top-0 start-100 translate-middle\">{{ icon_info }}</span></button></a> | Y4: =IF(M4<>"-",(" "&J4&"_ti"&": "&""""&"<a href=\"&""""&"09_glossary.html#"&J4&V4&K4&": "&M4&W4&""&X4&""""),"-") -> access_method_ti: "<a href=\"09_glossary.html#access_method\" target=\"_blank\" data-bs-toggle=\"tooltip\" data-bs-title=\"Access Method: The method used to reach the camera location (e.g., on 'Foot,' 'ATV,' 'Helicopter,' etc.).\"><button type=\"button\" class=\"btn btn-bd-tip-info-hidden btn-sm position-relative\">.<span class=\"position-absolute top-0 start-100 translate-middle\">{{ icon_info }}</span></button></a>"
C5: term | D5: - | G5: clarke_et_al_2023 | I5: accuracy | J5: =IF(D5<>"-",I5&"_"&D5,I5) -> accuracy | K5: Accuracy | L5: =IF(VLOOKUP(J5,find_replace!H:H,1,"false")=J5,"TRUE","FALSE") -> TRUE | M5: How close a measured or estimated value is to the true value' ({{ rtxt_clarke_et_al_2023 }}). | N5: How close a measured or estimated value is to the true value' (Clarke et al., 2023). | O5: =IF(M5=999,"",(" term_"&J5&": """&K5&"""")) -> term_accuracy: "Accuracy" | P5: =IF(M5="-","-",(" def_"&J5&": """&M5&"""")) -> def_accuracy: "How close a measured or estimated value is to the true value' ({{ rtxt_clarke_et_al_2023 }})." | U5: xx | V5: \" target=\"_blank\" data-bs-toggle=\"tooltip\" data-bs-title=\" | W5: \"> | X5: <button type=\"button\" class=\"btn btn-bd-tip-info-hidden btn-sm position-relative\">.<span class=\"position-absolute top-0 start-100 translate-middle\">{{ icon_info }}</span></button></a> | Y5: =IF(M5<>"-",(" "&J5&"_ti"&": "&""""&"<a href=\"&""""&"09_glossary.html#"&J5&V5&K5&": "&M5&W5&""&X5&""""),"-") -> accuracy_ti: "<a href=\"09_glossary.html#accuracy\" target=\"_blank\" data-bs-toggle=\"tooltip\" data-bs-title=\"Accuracy: How close a measured or estimated value is to the true value' ({{ rtxt_clarke_et_al_2023 }}).\"><button type=\"button\" class=\"btn btn-bd-tip-info-hidden btn-sm position-relative\">.<span class=\"position-absolute top-0 start-100 translate-middle\">{{ icon_info }}</span></button></a>"
B6: 2 | C6: field_option | D6: - | E6: **Adult** | F6: upper | G6: surv_guide_meta | H6: img_processing | I6: age_class_adult | J6: =IF(D6<>"-",I6&"_"&D6,I6) -> age_class_adult | K6: Adult | L6: =IF(VLOOKUP(J6,find_replace!H:H,1,"false")=J6,"TRUE","FALSE") -> TRUE | M6: Animals that are old enough to breed; reproductively mature. | N6: Animals that are old enough to breed; reproductively mature. | O6: =IF(M6=999,"",(" term_"&J6&": """&K6&"""")) -> term_age_class_adult: "Adult" | P6: =IF(M6="-","-",(" def_"&J6&": """&M6&"""")) -> def_age_class_adult: "Animals that are old enough to breed; reproductively mature." | R6: NULL | S6: TRUE | T6: FALSE | U6: xx | V6: \" target=\"_blank\" data-bs-toggle=\"tooltip\" data-bs-title=\" | W6: \"> | X6: <button type=\"button\" class=\"btn btn-bd-tip-info-hidden btn-sm position-relative\">.<span class=\"position-absolute top-0 start-100 translate-middle\">{{ icon_info }}</span></button></a> | Y6: =IF(M6<>"-",(" "&J6&"_ti"&": "&""""&"<a href=\"&""""&"09_glossary.html#"&J6&V6&K6&": "&M6&W6&""&X6&""""),"-") -> age_class_adult_ti: "<a href=\"09_glossary.html#age_class_adult\" target=\"_blank\" data-bs-toggle=\"tooltip\" data-bs-title=\"Adult: Animals that are old enough to breed; reproductively mature.\"><button type=\"button\" class=\"btn btn-bd-tip-info-hidden btn-sm position-relative\">.<span class=\"position-absolute top-0 start-100 translate-middle\">{{ icon_info }}</span></button></a>"
B7: 3 | C7: field | D7: - | E7: **Age Class** | F7: upper | G7: surv_guide_meta | H7: img_processing | I7: age_class | J7: =IF(D7<>"-",I7&"_"&D7,I7) -> age_class | K7: Age Class | L7: =IF(VLOOKUP(J7,find_replace!H:H,1,"false")=J7,"TRUE","FALSE") -> TRUE | M7: The age classification of individual(s) being categorized (e.g., 'Adult,' 'Juvenile,' 'Subadult,' 'Subadult - Young of Year,' 'Subadult - Yearling,' or 'Unknown'). | N7: The age classification of individual(s) being categorized (e.g., 'Adult,' 'Juvenile,' 'Subadult,' 'Subadult - Young of Year,' 'Subadult - Yearling,' or 'Unknown'). | O7: =IF(M7=999,"",(" term_"&J7&": """&K7&"""")) -> term_age_class: "Age Class" | P7: =IF(M7="-","-",(" def_"&J7&": """&M7&"""")) -> def_age_class: "The age classification of individual(s) being categorized (e.g., 'Adult,' 'Juvenile,' 'Subadult,' 'Subadult - Young of Year,' 'Subadult - Yearling,' or 'Unknown'). " | R7: TRUE | S7: TRUE | T7: TRUE | U7: xx | V7: \" target=\"_blank\" data-bs-toggle=\"tooltip\" data-bs-title=\" | W7: \"> | X7: <button type=\"button\" class=\"btn btn-bd-tip-info-hidden btn-sm position-relative\">.<span class=\"position-absolute top-0 start-100 translate-middle\">{{ icon_info }}</span></button></a> | Y7: =IF(M7<>"-",(" "&J7&"_ti"&": "&""""&"<a href=\"&""""&"09_glossary.html#"&J7&V7&K7&": "&M7&W7&""&X7&""""),"-") -> age_class_ti: "<a href=\"09_glossary.html#age_class\" target=\"_blank\" data-bs-toggle=\"tooltip\" data-bs-title=\"Age Class: The age classification of individual(s) being categorized (e.g., 'Adult,' 'Juvenile,' 'Subadult,' 'Subadult - Young of Year,' 'Subadult - Yearling,' or 'Unknown'). \"><button type=\"button\" class=\"btn btn-bd-tip-info-hidden btn-sm position-relative\">.<span class=\"position-absolute top-0 start-100 translate-middle\">{{ icon_info }}</span></button></a>"
A8: NEW | C8: term | D8: - | E8: Alpha richness (α) | G8: surv_guide_meta | H8: objective_approach | I8: mod_divers_rich_alpha | J8: =IF(D8<>"-",I8&"_"&D8,I8) -> mod_divers_rich_alpha | K8: Alpha richness (α) | L8: =IF(VLOOKUP(J8,find_replace!H:H,1,"false")=J8,"TRUE","FALSE") -> TRUE | M8: The number of species at the level of an individual camera location ({{ rtxt_wearn_gloverkapfer_2017 }}). | N8: The number of species at the level of an individual camera location (Wearn & Glover-Kapfer, 2017). | O8: =IF(M8=999,"",(" term_"&J8&": """&K8&"""")) -> term_mod_divers_rich_alpha: "Alpha richness (α)" | P8: =IF(M8="-","-",(" def_"&J8&": """&M8&"""")) -> def_mod_divers_rich_alpha: "The number of species at the level of an individual camera location ({{ rtxt_wearn_gloverkapfer_2017 }})." | U8: xx | V8: \" target=\"_blank\" data-bs-toggle=\"tooltip\" data-bs-title=\" | W8: \"> | X8: <button type=\"button\" class=\"btn btn-bd-tip-info-hidden btn-sm position-relative\">.<span class=\"position-absolute top-0 start-100 translate-middle\">{{ icon_info }}</span></button></a> | Y8: =IF(M8<>"-",(" "&J8&"_ti"&": "&""""&"<a href=\"&""""&"09_glossary.html#"&J8&V8&K8&": "&M8&W8&""&X8&""""),"-") -> mod_divers_rich_alpha_ti: "<a href=\"09_glossary.html#mod_divers_rich_alpha\" target=\"_blank\" data-bs-toggle=\"tooltip\" data-bs-title=\"Alpha richness (α): The number of species at the level of an individual camera location ({{ rtxt_wearn_gloverkapfer_2017 }}).\"><button type=\"button\" class=\"btn btn-bd-tip-info-hidden btn-sm position-relative\">.<span class=\"position-absolute top-0 start-100 translate-middle\">{{ icon_info }}</span></button></a>"
B9: 4 | C9: field | D9: - | E9: **Analyst** | F9: upper | G9: surv_guide_meta | H9: img_processing | I9: analyst | J9: =IF(D9<>"-",I9&"_"&D9,I9) -> analyst | K9: Analyst | L9: =IF(VLOOKUP(J9,find_replace!H:H,1,"false")=J9,"TRUE","FALSE") -> TRUE | M9: The first and last names of the individual who provided the observation data point (species identification and associated information). If there are multiple analysts for an observation, enter the primary analyst. | N9: The first and last names of the individual who provided the observation data point (species identification and associated information). If there are multiple analysts for an observation, enter the primary analyst. | O9: =IF(M9=999,"",(" term_"&J9&": """&K9&"""")) -> term_analyst: "Analyst" | P9: =IF(M9="-","-",(" def_"&J9&": """&M9&"""")) -> def_analyst: "The first and last names of the individual who provided the observation data point (species identification and associated information). If there are multiple analysts for an observation, enter the primary analyst." | R9: TRUE | S9: TRUE | T9: TRUE | U9: xx | V9: \" target=\"_blank\" data-bs-toggle=\"tooltip\" data-bs-title=\" | W9: \"> | X9: <button type=\"button\" class=\"btn btn-bd-tip-info-hidden btn-sm position-relative\">.<span class=\"position-absolute top-0 start-100 translate-middle\">{{ icon_info }}</span></button></a> | Y9: =IF(M9<>"-",(" "&J9&"_ti"&": "&""""&"<a href=\"&""""&"09_glossary.html#"&J9&V9&K9&": "&M9&W9&""&X9&""""),"-") -> analyst_ti: "<a href=\"09_glossary.html#analyst\" target=\"_blank\" data-bs-toggle=\"tooltip\" data-bs-title=\"Analyst: The first and last names of the individual who provided the observation data point (species identification and associated information). If there are multiple analysts for an observation, enter the primary analyst.\"><button type=\"button\" class=\"btn btn-bd-tip-info-hidden btn-sm position-relative\">.<span class=\"position-absolute top-0 start-100 translate-middle\">{{ icon_info }}</span></button></a>"
B10: 5 | C10: field | D10: - | E10: ***Animal ID** | F10: upper | G10: surv_guide_meta | H10: img_processing | I10: animal_id | J10: =IF(D10<>"-",I10&"_"&D10,I10) -> animal_id | K10: Animal ID | L10: =IF(VLOOKUP(J10,find_replace!H:H,1,"false")=J10,"TRUE","FALSE") -> TRUE | M10: A unique ID for an animal that can be uniquely identified (e.g., marked in some way). If multiple unique individuals are identified, enter an Animal ID for each as a unique row. Leave blank if not applicable. | N10: A unique ID for an animal that can be uniquely identified (e.g., marked in some way). If multiple unique individuals are identified, enter an Animal ID for each as a unique row. Leave blank if not applicable. | O10: =IF(M10=999,"",(" term_"&J10&": """&K10&"""")) -> term_animal_id: "Animal ID" | P10: =IF(M10="-","-",(" def_"&J10&": """&M10&"""")) -> def_animal_id: "A unique ID for an animal that can be uniquely identified (e.g., marked in some way). If multiple unique individuals are identified, enter an Animal ID for each as a unique row. Leave blank if not applicable." | Q10: TRUE | R10: FALSE | S10: TRUE | T10: FALSE | U10: xx | V10: \" target=\"_blank\" data-bs-toggle=\"tooltip\" data-bs-title=\" | W10: \"> | X10: <button type=\"button\" class=\"btn btn-bd-tip-info-hidden btn-sm position-relative\">.<span class=\"position-absolute top-0 start-100 translate-middle\">{{ icon_info }}</span></button></a> | Y10: =IF(M10<>"-",(" "&J10&"_ti"&": "&""""&"<a href=\"&""""&"09_glossary.html#"&J10&V10&K10&": "&M10&W10&""&X10&""""),"-") -> animal_id_ti: "<a href=\"09_glossary.html#animal_id\" target=\"_blank\" data-bs-toggle=\"tooltip\" data-bs-title=\"Animal ID: A unique ID for an animal that can be uniquely identified (e.g., marked in some way). If multiple unique individuals are identified, enter an Animal ID for each as a unique row. Leave blank if not applicable.\"><button type=\"button\" class=\"btn btn-bd-tip-info-hidden btn-sm position-relative\">.<span class=\"position-absolute top-0 start-100 translate-middle\">{{ icon_info }}</span></button></a>"
B11: 6 | C11: term | D11: - | E11: Audible lure | G11: surv_guide_meta | H11: baitlure | I11: baitlure_audible_lure | J11: =IF(D11<>"-",I11&"_"&D11,I11) -> baitlure_audible_lure | K11: Audible lure | L11: =IF(VLOOKUP(J11,find_replace!H:H,1,"false")=J11,"TRUE","FALSE") -> TRUE | M11: Sounds imitating noises of prey or conspecifics that draw animals closer by eliciting curiosity ({{ rtxt_schlexer_2008 }}). | N11: Sounds imitating noises of prey or conspecifics that draw animals closer by eliciting curiosity (Schlexer, 2008). | O11: =IF(M11=999,"",(" term_"&J11&": """&K11&"""")) -> term_baitlure_audible_lure: "Audible lure" | P11: =IF(M11="-","-",(" def_"&J11&": """&M11&"""")) -> def_baitlure_audible_lure: "Sounds imitating noises of prey or conspecifics that draw animals closer by eliciting curiosity ({{ rtxt_schlexer_2008 }})." | R11: NULL | S11: FALSE | T11: TRUE | U11: xx | V11: \" target=\"_blank\" data-bs-toggle=\"tooltip\" data-bs-title=\" | W11: \"> | X11: <button type=\"button\" class=\"btn btn-bd-tip-info-hidden btn-sm position-relative\">.<span class=\"position-absolute top-0 start-100 translate-middle\">{{ icon_info }}</span></button></a> | Y11: =IF(M11<>"-",(" "&J11&"_ti"&": "&""""&"<a href=\"&""""&"09_glossary.html#"&J11&V11&K11&": "&M11&W11&""&X11&""""),"-") -> baitlure_audible_lure_ti: "<a href=\"09_glossary.html#baitlure_audible_lure\" target=\"_blank\" data-bs-toggle=\"tooltip\" data-bs-title=\"Audible lure: Sounds imitating noises of prey or conspecifics that draw animals closer by eliciting curiosity ({{ rtxt_schlexer_2008 }}).\"><button type=\"button\" class=\"btn btn-bd-tip-info-hidden btn-sm position-relative\">.<span class=\"position-absolute top-0 start-100 translate-middle\">{{ icon_info }}</span></button></a>"
B12: 7 | C12: term | D12: - | E12: Bait | G12: surv_guide_meta | H12: baitlure | I12: baitlure_bait | J12: =IF(D12<>"-",I12&"_"&D12,I12) -> baitlure_bait | K12: Bait | L12: =IF(VLOOKUP(J12,find_replace!H:H,1,"false")=J12,"TRUE","FALSE") -> TRUE | M12: A food item (or other substance) that is placed to attract animals via the sense of taste and olfactory cues ({{ rtxt_schlexer_2008 }}). | N12: A food item (or other substance) that is placed to attract animals via the sense of taste and olfactory cues (Schlexer, 2008). | O12: =IF(M12=999,"",(" term_"&J12&": """&K12&"""")) -> term_baitlure_bait: "Bait" | P12: =IF(M12="-","-",(" def_"&J12&": """&M12&"""")) -> def_baitlure_bait: "A food item (or other substance) that is placed to attract animals via the sense of taste and olfactory cues ({{ rtxt_schlexer_2008 }})." | R12: NULL | S12: TRUE | T12: TRUE | U12: xx | V12: \" target=\"_blank\" data-bs-toggle=\"tooltip\" data-bs-title=\" | W12: \"> | X12: <button type=\"button\" class=\"btn btn-bd-tip-info-hidden btn-sm position-relative\">.<span class=\"position-absolute top-0 start-100 translate-middle\">{{ icon_info }}</span></button></a> | Y12: =IF(M12<>"-",(" "&J12&"_ti"&": "&""""&"<a href=\"&""""&"09_glossary.html#"&J12&V12&K12&": "&M12&W12&""&X12&""""),"-") -> baitlure_bait_ti: "<a href=\"09_glossary.html#baitlure_bait\" target=\"_blank\" data-bs-toggle=\"tooltip\" data-bs-title=\"Bait: A food item (or other substance) that is placed to attract animals via the sense of taste and olfactory cues ({{ rtxt_schlexer_2008 }}).\"><button type=\"button\" class=\"btn btn-bd-tip-info-hidden btn-sm position-relative\">.<span class=\"position-absolute top-0 start-100 translate-middle\">{{ icon_info }}</span></button></a>"
B13: 8 | C13: field | D13: - | E13: **Bait*/Lure Type** | F13: upper | G13: surv_guide_meta | H13: baitlure | I13: baitlure_bait_lure_type | J13: =IF(D13<>"-",I13&"_"&D13,I13) -> baitlure_bait_lure_type | K13: Bait/Lure Type | L13: =IF(VLOOKUP(J13,find_replace!H:H,1,"false")=J13,"TRUE","FALSE") -> TRUE | M13: The type of bait or lure used at a camera location. Record 'None' if a Bait*/Lure Type was not used and 'Unknown' if not known. If 'Other,' describe in the Deployment Comments. | N13: The type of bait or lure used at a camera location. Record 'None' if a Bait*/Lure Type was not used and 'Unknown' if not known. If 'Other,' describe in the Deployment Comments. | O13: =IF(M13=999,"",(" term_"&J13&": """&K13&"""")) -> term_baitlure_bait_lure_type: "Bait/Lure Type" | P13: =IF(M13="-","-",(" def_"&J13&": """&M13&"""")) -> def_baitlure_bait_lure_type: "The type of bait or lure used at a camera location. Record 'None' if a Bait*/Lure Type was not used and 'Unknown' if not known. If 'Other,' describe in the Deployment Comments." | Q13: TRUE | R13: TRUE | S13: TRUE | T13: TRUE | U13: xx | V13: \" target=\"_blank\" data-bs-toggle=\"tooltip\" data-bs-title=\" | W13: \"> | X13: <button type=\"button\" class=\"btn btn-bd-tip-info-hidden btn-sm position-relative\">.<span class=\"position-absolute top-0 start-100 translate-middle\">{{ icon_info }}</span></button></a> | Y13: =IF(M13<>"-",(" "&J13&"_ti"&": "&""""&"<a href=\"&""""&"09_glossary.html#"&J13&V13&K13&": "&M13&W13&""&X13&""""),"-") -> baitlure_bait_lure_type_ti: "<a href=\"09_glossary.html#baitlure_bait_lure_type\" target=\"_blank\" data-bs-toggle=\"tooltip\" data-bs-title=\"Bait/Lure Type: The type of bait or lure used at a camera location. Record 'None' if a Bait*/Lure Type was not used and 'Unknown' if not known. If 'Other,' describe in the Deployment Comments.\"><button type=\"button\" class=\"btn btn-bd-tip-info-hidden btn-sm position-relative\">.<span class=\"position-absolute top-0 start-100 translate-middle\">{{ icon_info }}</span></button></a>"
B14: 9 | C14: field | D14: - | E14: ***Batteries Replaced** | F14: upper | G14: surv_guide_meta | H14: cam_visit_equip | I14: batteries_replaced | J14: =IF(D14<>"-",I14&"_"&D14,I14) -> batteries_replaced | K14: Batteries Replaced | L14: =IF(VLOOKUP(J14,find_replace!H:H,1,"false")=J14,"TRUE","FALSE") -> TRUE | M14: Whether the camera's batteries were replaced. | N14: Whether the camera's batteries were replaced. | O14: =IF(M14=999,"",(" term_"&J14&": """&K14&"""")) -> term_batteries_replaced: "Batteries Replaced" | P14: =IF(M14="-","-",(" def_"&J14&": """&M14&"""")) -> def_batteries_replaced: "Whether the camera's batteries were replaced." | R14: FALSE | S14: TRUE | T14: TRUE | U14: xx | V14: \" target=\"_blank\" data-bs-toggle=\"tooltip\" data-bs-title=\" | W14: \"> | X14: <button type=\"button\" class=\"btn btn-bd-tip-info-hidden btn-sm position-relative\">.<span class=\"position-absolute top-0 start-100 translate-middle\">{{ icon_info }}</span></button></a> | Y14: =IF(M14<>"-",(" "&J14&"_ti"&": "&""""&"<a href=\"&""""&"09_glossary.html#"&J14&V14&K14&": "&M14&W14&""&X14&""""),"-") -> batteries_replaced_ti: "<a href=\"09_glossary.html#batteries_replaced\" target=\"_blank\" data-bs-toggle=\"tooltip\" data-bs-title=\"Batteries Replaced: Whether the camera's batteries were replaced.\"><button type=\"button\" class=\"btn btn-bd-tip-info-hidden btn-sm position-relative\">.<span class=\"position-absolute top-0 start-100 translate-middle\">{{ icon_info }}</span></button></a>"
C15: term | D15: - | E15: Behaviour | G15: surv_guide_meta | H15: objective | I15: obj_behaviour | J15: =IF(D15<>"-",I15&"_"&D15,I15) -> obj_behaviour | K15: Behaviour | L15: =IF(VLOOKUP(J15,find_replace!H:H,1,"false")=J15,"TRUE","FALSE") -> TRUE | M15: Behaviour focused objectives vary greatly; they may be qualitative or quantitative (e.g., diel activity patterns, mating, boldness, predation, foraging, activity patterns, vigilance, parental care ({{ rtxt_caravaggi_et_al_2020 }}; {{ rtxt_wearn_gloverkapfer_2017 }}). | N15: Behaviour focused objectives vary greatly; they may be qualitative or quantitative (e.g., diel activity patterns, mating, boldness, predation, foraging, activity patterns, vigilance, parental care (Caravaggi et al., 2020; Wearn & Glover-Kapfer, 2017). | O15: =IF(M15=999,"",(" term_"&J15&": """&K15&"""")) -> term_obj_behaviour: "Behaviour" | P15: =IF(M15="-","-",(" def_"&J15&": """&M15&"""")) -> def_obj_behaviour: "Behaviour focused objectives vary greatly; they may be qualitative or quantitative (e.g., diel activity patterns, mating, boldness, predation, foraging, activity patterns, vigilance, parental care ({{ rtxt_caravaggi_et_al_2020 }}; {{ rtxt_wearn_gloverkapfer_2017 }})." | U15: xx | V15: \" target=\"_blank\" data-bs-toggle=\"tooltip\" data-bs-title=\" | W15: \"> | X15: <button type=\"button\" class=\"btn btn-bd-tip-info-hidden btn-sm position-relative\">.<span class=\"position-absolute top-0 start-100 translate-middle\">{{ icon_info }}</span></button></a> | Y15: =IF(M15<>"-",(" "&J15&"_ti"&": "&""""&"<a href=\"&""""&"09_glossary.html#"&J15&V15&K15&": "&M15&W15&""&X15&""""),"-") -> obj_behaviour_ti: "<a href=\"09_glossary.html#obj_behaviour\" target=\"_blank\" data-bs-toggle=\"tooltip\" data-bs-title=\"Behaviour: Behaviour focused objectives vary greatly; they may be qualitative or quantitative (e.g., diel activity patterns, mating, boldness, predation, foraging, activity patterns, vigilance, parental care ({{ rtxt_caravaggi_et_al_2020 }}; {{ rtxt_wearn_gloverkapfer_2017 }}).\"><button type=\"button\" class=\"btn btn-bd-tip-info-hidden btn-sm position-relative\">.<span class=\"position-absolute top-0 start-100 translate-middle\">{{ icon_info }}</span></button></a>"
B16: 10 | C16: field | D16: tag | E16: **\*Behaviour** | F16: upper | G16: surv_guide_meta | H16: cam_visit_equip | I16: behaviour | J16: =IF(D16<>"-",I16&"_"&D16,I16) -> behaviour_tag | K16: Behaviour (tag) | L16: =IF(VLOOKUP(J16,find_replace!H:H,1,"false")=J16,"TRUE","FALSE") -> #N/A | M16: The behaviour of the individual(s) being categorized (e.g., 'Standing,' 'Drinking,' 'Vigilant,' etc.). | N16: The behaviour of the individual(s) being categorized (e.g., 'Standing,' 'Drinking,' 'Vigilant,' etc.). | O16: =IF(M16=999,"",(" term_"&J16&": """&K16&"""")) -> term_behaviour_tag: "Behaviour (tag)" | P16: =IF(M16="-","-",(" def_"&J16&": """&M16&"""")) -> def_behaviour_tag: "The behaviour of the individual(s) being categorized (e.g., 'Standing,' 'Drinking,' 'Vigilant,' etc.)." | R16: FALSE | S16: TRUE | T16: TRUE | U16: xx | V16: \" target=\"_blank\" data-bs-toggle=\"tooltip\" data-bs-title=\" | W16: \"> | X16: <button type=\"button\" class=\"btn btn-bd-tip-info-hidden btn-sm position-relative\">.<span class=\"position-absolute top-0 start-100 translate-middle\">{{ icon_info }}</span></button></a> | Y16: =IF(M16<>"-",(" "&J16&"_ti"&": "&""""&"<a href=\"&""""&"09_glossary.html#"&J16&V16&K16&": "&M16&W16&""&X16&""""),"-") -> behaviour_tag_ti: "<a href=\"09_glossary.html#behaviour_tag\" target=\"_blank\" data-bs-toggle=\"tooltip\" data-bs-title=\"Behaviour (tag): The behaviour of the individual(s) being categorized (e.g., 'Standing,' 'Drinking,' 'Vigilant,' etc.).\"><button type=\"button\" class=\"btn btn-bd-tip-info-hidden btn-sm position-relative\">.<span class=\"position-absolute top-0 start-100 translate-middle\">{{ icon_info }}</span></button></a>"
A17: NEW | C17: term | D17: - | E17: Beta-diversity (β) | G17: surv_guide_meta | H17: objective_approach | I17: mod_divers_rich_beta | J17: =IF(D17<>"-",I17&"_"&D17,I17) -> mod_divers_rich_beta | K17: Beta-diversity (β) | L17: =IF(VLOOKUP(J17,find_replace!H:H,1,"false")=J17,"TRUE","FALSE") -> TRUE | M17: The differences between the communities or, more formally, the variance among the communities ({{ rtxt_wearn_gloverkapfer_2017 }}). | N17: The differences between the communities or, more formally, the variance among the communities (Wearn & Glover-Kapfer, 2017). | O17: =IF(M17=999,"",(" term_"&J17&": """&K17&"""")) -> term_mod_divers_rich_beta: "Beta-diversity (β)" | P17: =IF(M17="-","-",(" def_"&J17&": """&M17&"""")) -> def_mod_divers_rich_beta: "The differences between the communities or, more formally, the variance among the communities ({{ rtxt_wearn_gloverkapfer_2017 }})." | U17: xx | V17: \" target=\"_blank\" data-bs-toggle=\"tooltip\" data-bs-title=\" | W17: \"> | X17: <button type=\"button\" class=\"btn btn-bd-tip-info-hidden btn-sm position-relative\">.<span class=\"position-absolute top-0 start-100 translate-middle\">{{ icon_info }}</span></button></a> | Y17: =IF(M17<>"-",(" "&J17&"_ti"&": "&""""&"<a href=\"&""""&"09_glossary.html#"&J17&V17&K17&": "&M17&W17&""&X17&""""),"-") -> mod_divers_rich_beta_ti: "<a href=\"09_glossary.html#mod_divers_rich_beta\" target=\"_blank\" data-bs-toggle=\"tooltip\" data-bs-title=\"Beta-diversity (β): The differences between the communities or, more formally, the variance among the communities ({{ rtxt_wearn_gloverkapfer_2017 }}).\"><button type=\"button\" class=\"btn btn-bd-tip-info-hidden btn-sm position-relative\">.<span class=\"position-absolute top-0 start-100 translate-middle\">{{ icon_info }}</span></button></a>"
C18: term | D18: - | G18: kemp_et_al_2022 | I18: bias | J18: =IF(D18<>"-",I18&"_"&D18,I18) -> bias | K18: Bias | L18: =IF(VLOOKUP(J18,find_replace!H:H,1,"false")=J18,"TRUE","FALSE") -> TRUE | M18: A skewed or altered perspective. Biased data refers to data that may be inaccurate or unevenly portrayed (usually in favour of specific variables) and is therefore not as robust.' ({{ rtxt_kemp_et_al_2022 }}). | N18: A skewed or altered perspective. Biased data refers to data that may be inaccurate or unevenly portrayed (usually in favour of specific variables) and is therefore not as robust.' (Kemp et al., 2022). | O18: =IF(M18=999,"",(" term_"&J18&": """&K18&"""")) -> term_bias: "Bias" | P18: =IF(M18="-","-",(" def_"&J18&": """&M18&"""")) -> def_bias: "A skewed or altered perspective. Biased data refers to data that may be inaccurate or unevenly portrayed (usually in favour of specific variables) and is therefore not as robust.' ({{ rtxt_kemp_et_al_2022 }})." | U18: xx | V18: \" target=\"_blank\" data-bs-toggle=\"tooltip\" data-bs-title=\" | W18: \"> | X18: <button type=\"button\" class=\"btn btn-bd-tip-info-hidden btn-sm position-relative\">.<span class=\"position-absolute top-0 start-100 translate-middle\">{{ icon_info }}</span></button></a> | Y18: =IF(M18<>"-",(" "&J18&"_ti"&": "&""""&"<a href=\"&""""&"09_glossary.html#"&J18&V18&K18&": "&M18&W18&""&X18&""""),"-") -> bias_ti: "<a href=\"09_glossary.html#bias\" target=\"_blank\" data-bs-toggle=\"tooltip\" data-bs-title=\"Bias: A skewed or altered perspective. Biased data refers to data that may be inaccurate or unevenly portrayed (usually in favour of specific variables) and is therefore not as robust.' ({{ rtxt_kemp_et_al_2022 }}).\"><button type=\"button\" class=\"btn btn-bd-tip-info-hidden btn-sm position-relative\">.<span class=\"position-absolute top-0 start-100 translate-middle\">{{ icon_info }}</span></button></a>"
C19: term | D19: - | G19: kemp_et_al_2022 | I19: biodiversity | J19: =IF(D19<>"-",I19&"_"&D19,I19) -> biodiversity | K19: Biodiversity | L19: =IF(VLOOKUP(J19,find_replace!H:H,1,"false")=J19,"TRUE","FALSE") -> TRUE | M19: The variation of life in the natural world. In the context of this guide, biodiversity refers to the variety of different wildlife species found in an area.' ({{ rtxt_kemp_et_al_2022 }}). | N19: The variation of life in the natural world. In the context of this guide, biodiversity refers to the variety of different wildlife species found in an area.' (Kemp et al., 2022). | O19: =IF(M19=999,"",(" term_"&J19&": """&K19&"""")) -> term_biodiversity: "Biodiversity" | P19: =IF(M19="-","-",(" def_"&J19&": """&M19&"""")) -> def_biodiversity: "The variation of life in the natural world. In the context of this guide, biodiversity refers to the variety of different wildlife species found in an area.' ({{ rtxt_kemp_et_al_2022 }})." | U19: xx | V19: \" target=\"_blank\" data-bs-toggle=\"tooltip\" data-bs-title=\" | W19: \"> | X19: <button type=\"button\" class=\"btn btn-bd-tip-info-hidden btn-sm position-relative\">.<span class=\"position-absolute top-0 start-100 translate-middle\">{{ icon_info }}</span></button></a> | Y19: =IF(M19<>"-",(" "&J19&"_ti"&": "&""""&"<a href=\"&""""&"09_glossary.html#"&J19&V19&K19&": "&M19&W19&""&X19&""""),"-") -> biodiversity_ti: "<a href=\"09_glossary.html#biodiversity\" target=\"_blank\" data-bs-toggle=\"tooltip\" data-bs-title=\"Biodiversity: The variation of life in the natural world. In the context of this guide, biodiversity refers to the variety of different wildlife species found in an area.' ({{ rtxt_kemp_et_al_2022 }}).\"><button type=\"button\" class=\"btn btn-bd-tip-info-hidden btn-sm position-relative\">.<span class=\"position-absolute top-0 start-100 translate-middle\">{{ icon_info }}</span></button></a>"
C20: term | D20: - | G20: kemp_et_al_2022 | I20: obj_vital_rate_birth | J20: =IF(D20<>"-",I20&"_"&D20,I20) -> obj_vital_rate_birth | K20: Birth rate | L20: =IF(VLOOKUP(J20,find_replace!H:H,1,"false")=J20,"TRUE","FALSE") -> #N/A | M20: The average number of offspring produced per individual per unit time.' ({{ rtxt_nbckc_2024a }}) | N20: The average number of offspring produced per individual per unit time.' (NBCKC, 2024a) | O20: =IF(M20=999,"",(" term_"&J20&": """&K20&"""")) -> term_obj_vital_rate_birth: "Birth rate" | P20: =IF(M20="-","-",(" def_"&J20&": """&M20&"""")) -> def_obj_vital_rate_birth: "The average number of offspring produced per individual per unit time.' ({{ rtxt_nbckc_2024a }})" | U20: xx | V20: \" target=\"_blank\" data-bs-toggle=\"tooltip\" data-bs-title=\" | W20: \"> | X20: <button type=\"button\" class=\"btn btn-bd-tip-info-hidden btn-sm position-relative\">.<span class=\"position-absolute top-0 start-100 translate-middle\">{{ icon_info }}</span></button></a> | Y20: =IF(M20<>"-",(" "&J20&"_ti"&": "&""""&"<a href=\"&""""&"09_glossary.html#"&J20&V20&K20&": "&M20&W20&""&X20&""""),"-") -> obj_vital_rate_birth_ti: "<a href=\"09_glossary.html#obj_vital_rate_birth\" target=\"_blank\" data-bs-toggle=\"tooltip\" data-bs-title=\"Birth rate: The average number of offspring produced per individual per unit time.' ({{ rtxt_nbckc_2024a }})\"><button type=\"button\" class=\"btn btn-bd-tip-info-hidden btn-sm position-relative\">.<span class=\"position-absolute top-0 start-100 translate-middle\">{{ icon_info }}</span></button></a>"
B21: 11 | C21: field | D21: - | E21: **\*Camera Active On Arrival** | F21: upper | G21: surv_guide_meta | H21: cam_visit_equip | I21: cam_active_on_arrival | J21: =IF(D21<>"-",I21&"_"&D21,I21) -> cam_active_on_arrival | K21: Camera Active On Arrival | L21: =IF(VLOOKUP(J21,find_replace!H:H,1,"false")=J21,"TRUE","FALSE") -> TRUE | M21: Whether a camera was functional upon arrival. | N21: Whether a camera was functional upon arrival. | O21: =IF(M21=999,"",(" term_"&J21&": """&K21&"""")) -> term_cam_active_on_arrival: "Camera Active On Arrival" | P21: =IF(M21="-","-",(" def_"&J21&": """&M21&"""")) -> def_cam_active_on_arrival: "Whether a camera was functional upon arrival." | R21: FALSE | S21: TRUE | T21: TRUE | U21: xx | V21: \" target=\"_blank\" data-bs-toggle=\"tooltip\" data-bs-title=\" | W21: \"> | X21: <button type=\"button\" class=\"btn btn-bd-tip-info-hidden btn-sm position-relative\">.<span class=\"position-absolute top-0 start-100 translate-middle\">{{ icon_info }}</span></button></a> | Y21: =IF(M21<>"-",(" "&J21&"_ti"&": "&""""&"<a href=\"&""""&"09_glossary.html#"&J21&V21&K21&": "&M21&W21&""&X21&""""),"-") -> cam_active_on_arrival_ti: "<a href=\"09_glossary.html#cam_active_on_arrival\" target=\"_blank\" data-bs-toggle=\"tooltip\" data-bs-title=\"Camera Active On Arrival: Whether a camera was functional upon arrival.\"><button type=\"button\" class=\"btn btn-bd-tip-info-hidden btn-sm position-relative\">.<span class=\"position-absolute top-0 start-100 translate-middle\">{{ icon_info }}</span></button></a>"
B22: 12 | C22: field | D22: - | E22: **\*Camera Active On Departure** | F22: upper | G22: surv_guide_meta | H22: cam_visit_equip | I22: cam_active_on_departure | J22: =IF(D22<>"-",I22&"_"&D22,I22) -> cam_active_on_departure | K22: Camera Active On Departure | L22: =IF(VLOOKUP(J22,find_replace!H:H,1,"false")=J22,"TRUE","FALSE") -> TRUE | M22: Whether a camera was functional upon departure. | N22: Whether a camera was functional upon departure. | O22: =IF(M22=999,"",(" term_"&J22&": """&K22&"""")) -> term_cam_active_on_departure: "Camera Active On Departure" | P22: =IF(M22="-","-",(" def_"&J22&": """&M22&"""")) -> def_cam_active_on_departure: "Whether a camera was functional upon departure." | R22: FALSE | S22: TRUE | T22: TRUE | U22: xx | V22: \" target=\"_blank\" data-bs-toggle=\"tooltip\" data-bs-title=\" | W22: \"> | X22: <button type=\"button\" class=\"btn btn-bd-tip-info-hidden btn-sm position-relative\">.<span class=\"position-absolute top-0 start-100 translate-middle\">{{ icon_info }}</span></button></a> | Y22: =IF(M22<>"-",(" "&J22&"_ti"&": "&""""&"<a href=\"&""""&"09_glossary.html#"&J22&V22&K22&": "&M22&W22&""&X22&""""),"-") -> cam_active_on_departure_ti: "<a href=\"09_glossary.html#cam_active_on_departure\" target=\"_blank\" data-bs-toggle=\"tooltip\" data-bs-title=\"Camera Active On Departure: Whether a camera was functional upon departure.\"><button type=\"button\" class=\"btn btn-bd-tip-info-hidden btn-sm position-relative\">.<span class=\"position-absolute top-0 start-100 translate-middle\">{{ icon_info }}</span></button></a>"
B23: 13 | C23: term | D23: - | E23: Camera angle | G23: surv_guide_meta | H23: cam_visit_placement | I23: cam_angle | J23: =IF(D23<>"-",I23&"_"&D23,I23) -> cam_angle | K23: Camera angle | L23: =IF(VLOOKUP(J23,find_replace!H:H,1,"false")=J23,"TRUE","FALSE") -> TRUE | M23: The degree at which the camera is pointed toward the FOV Target Feature relative to the horizontal ground surface (with respect to slope, if applicable). | N23: The degree at which the camera is pointed toward the FOV Target Feature relative to the horizontal ground surface (with respect to slope, if applicable). | O23: =IF(M23=999,"",(" term_"&J23&": """&K23&"""")) -> term_cam_angle: "Camera angle" | P23: =IF(M23="-","-",(" def_"&J23&": """&M23&"""")) -> def_cam_angle: "The degree at which the camera is pointed toward the FOV Target Feature relative to the horizontal ground surface (with respect to slope, if applicable)." | R23: NULL | S23: FALSE | T23: TRUE | U23: xx | V23: \" target=\"_blank\" data-bs-toggle=\"tooltip\" data-bs-title=\" | W23: \"> | X23: <button type=\"button\" class=\"btn btn-bd-tip-info-hidden btn-sm position-relative\">.<span class=\"position-absolute top-0 start-100 translate-middle\">{{ icon_info }}</span></button></a> | Y23: =IF(M23<>"-",(" "&J23&"_ti"&": "&""""&"<a href=\"&""""&"09_glossary.html#"&J23&V23&K23&": "&M23&W23&""&X23&""""),"-") -> cam_angle_ti: "<a href=\"09_glossary.html#cam_angle\" target=\"_blank\" data-bs-toggle=\"tooltip\" data-bs-title=\"Camera angle: The degree at which the camera is pointed toward the FOV Target Feature relative to the horizontal ground surface (with respect to slope, if applicable).\"><button type=\"button\" class=\"btn btn-bd-tip-info-hidden btn-sm position-relative\">.<span class=\"position-absolute top-0 start-100 translate-middle\">{{ icon_info }}</span></button></a>"
B24: 14 | C24: field | D24: - | E24: **\*Camera Attachment** | F24: upper | G24: surv_guide_meta | H24: cam_visit_placement | I24: cam_attachment | J24: =IF(D24<>"-",I24&"_"&D24,I24) -> cam_attachment | K24: Camera Attachment | L24: =IF(VLOOKUP(J24,find_replace!H:H,1,"false")=J24,"TRUE","FALSE") -> TRUE | M24: The method*/tools used to attach the camera (e.g., attached to a tree with a bungee cord; reported as codes such as 'Tree + Bungee*/Strap'). If 'Other,' describe in the Camera Location Comments. | N24: The method*/tools used to attach the camera (e.g., attached to a tree with a bungee cord; reported as codes such as 'Tree + Bungee*/Strap'). If 'Other,' describe in the Camera Location Comments. | O24: =IF(M24=999,"",(" term_"&J24&": """&K24&"""")) -> term_cam_attachment: "Camera Attachment" | P24: =IF(M24="-","-",(" def_"&J24&": """&M24&"""")) -> def_cam_attachment: "The method*/tools used to attach the camera (e.g., attached to a tree with a bungee cord; reported as codes such as 'Tree + Bungee*/Strap'). If 'Other,' describe in the Camera Location Comments." | Q24: TRUE | R24: FALSE | S24: TRUE | T24: TRUE | U24: xx | V24: \" target=\"_blank\" data-bs-toggle=\"tooltip\" data-bs-title=\" | W24: \"> | X24: <button type=\"button\" class=\"btn btn-bd-tip-info-hidden btn-sm position-relative\">.<span class=\"position-absolute top-0 start-100 translate-middle\">{{ icon_info }}</span></button></a> | Y24: =IF(M24<>"-",(" "&J24&"_ti"&": "&""""&"<a href=\"&""""&"09_glossary.html#"&J24&V24&K24&": "&M24&W24&""&X24&""""),"-") -> cam_attachment_ti: "<a href=\"09_glossary.html#cam_attachment\" target=\"_blank\" data-bs-toggle=\"tooltip\" data-bs-title=\"Camera Attachment: The method*/tools used to attach the camera (e.g., attached to a tree with a bungee cord; reported as codes such as 'Tree + Bungee*/Strap'). If 'Other,' describe in the Camera Location Comments.\"><button type=\"button\" class=\"btn btn-bd-tip-info-hidden btn-sm position-relative\">.<span class=\"position-absolute top-0 start-100 translate-middle\">{{ icon_info }}</span></button></a>"
B25: 15 | C25: field | D25: - | E25: **\*Camera Damaged** | F25: upper | G25: surv_guide_meta | H25: cam_visit_equip | I25: cam_damaged | J25: =IF(D25<>"-",I25&"_"&D25,I25) -> cam_damaged | K25: Camera Damaged | L25: =IF(VLOOKUP(J25,find_replace!H:H,1,"false")=J25,"TRUE","FALSE") -> TRUE | M25: Whether the camera was damaged or malfunctioning; if there is any damage to the device (physical or mechanical), the crew should describe the damage in the Service*/Retrieval Comments. | N25: Whether the camera was damaged or malfunctioning; if there is any damage to the device (physical or mechanical), the crew should describe the damage in the Service*/Retrieval Comments. | O25: =IF(M25=999,"",(" term_"&J25&": """&K25&"""")) -> term_cam_damaged: "Camera Damaged" | P25: =IF(M25="-","-",(" def_"&J25&": """&M25&"""")) -> def_cam_damaged: "Whether the camera was damaged or malfunctioning; if there is any damage to the device (physical or mechanical), the crew should describe the damage in the Service*/Retrieval Comments." | R25: FALSE | S25: TRUE | T25: TRUE | U25: xx | V25: \" target=\"_blank\" data-bs-toggle=\"tooltip\" data-bs-title=\" | W25: \"> | X25: <button type=\"button\" class=\"btn btn-bd-tip-info-hidden btn-sm position-relative\">.<span class=\"position-absolute top-0 start-100 translate-middle\">{{ icon_info }}</span></button></a> | Y25: =IF(M25<>"-",(" "&J25&"_ti"&": "&""""&"<a href=\"&""""&"09_glossary.html#"&J25&V25&K25&": "&M25&W25&""&X25&""""),"-") -> cam_damaged_ti: "<a href=\"09_glossary.html#cam_damaged\" target=\"_blank\" data-bs-toggle=\"tooltip\" data-bs-title=\"Camera Damaged: Whether the camera was damaged or malfunctioning; if there is any damage to the device (physical or mechanical), the crew should describe the damage in the Service*/Retrieval Comments.\"><button type=\"button\" class=\"btn btn-bd-tip-info-hidden btn-sm position-relative\">.<span class=\"position-absolute top-0 start-100 translate-middle\">{{ icon_info }}</span></button></a>"
B26: 16 | C26: term | D26: - | E26: Camera days per camera location | G26: surv_guide_meta | H26: sampledesign | I26: cam_days_per_cam_location | J26: =IF(D26<>"-",I26&"_"&D26,I26) -> cam_days_per_cam_location | K26: Camera days per camera location | L26: =IF(VLOOKUP(J26,find_replace!H:H,1,"false")=J26,"TRUE","FALSE") -> TRUE | M26: The number of days each camera was active and functioning during the period it was deployed (e.g., 24-hour periods or the difference in days between the Deployment Start Date Time and the Deployment End Date Time if there were no interruptions). | N26: The number of days each camera was active and functioning during the period it was deployed (e.g., 24-hour periods or the difference in days between the Deployment Start Date Time and the Deployment End Date Time if there were no interruptions). | O26: =IF(M26=999,"",(" term_"&J26&": """&K26&"""")) -> term_cam_days_per_cam_location: "Camera days per camera location" | P26: =IF(M26="-","-",(" def_"&J26&": """&M26&"""")) -> def_cam_days_per_cam_location: "The number of days each camera was active and functioning during the period it was deployed (e.g., 24-hour periods or the difference in days between the Deployment Start Date Time and the Deployment End Date Time if there were no interruptions)." | R26: NULL | S26: FALSE | T26: TRUE | U26: xx | V26: \" target=\"_blank\" data-bs-toggle=\"tooltip\" data-bs-title=\" | W26: \"> | X26: <button type=\"button\" class=\"btn btn-bd-tip-info-hidden btn-sm position-relative\">.<span class=\"position-absolute top-0 start-100 translate-middle\">{{ icon_info }}</span></button></a> | Y26: =IF(M26<>"-",(" "&J26&"_ti"&": "&""""&"<a href=\"&""""&"09_glossary.html#"&J26&V26&K26&": "&M26&W26&""&X26&""""),"-") -> cam_days_per_cam_location_ti: "<a href=\"09_glossary.html#cam_days_per_cam_location\" target=\"_blank\" data-bs-toggle=\"tooltip\" data-bs-title=\"Camera days per camera location: The number of days each camera was active and functioning during the period it was deployed (e.g., 24-hour periods or the difference in days between the Deployment Start Date Time and the Deployment End Date Time if there were no interruptions).\"><button type=\"button\" class=\"btn btn-bd-tip-info-hidden btn-sm position-relative\">.<span class=\"position-absolute top-0 start-100 translate-middle\">{{ icon_info }}</span></button></a>"
B27: 17 | C27: field | D27: - | E27: **\*Camera Direction (degrees)** | F27: upper | G27: surv_guide_meta | H27: cam_visit_placement | I27: cam_direction | J27: =IF(D27<>"-",I27&"_"&D27,I27) -> cam_direction | K27: Camera Direction (degrees) | L27: =IF(VLOOKUP(J27,find_replace!H:H,1,"false")=J27,"TRUE","FALSE") -> TRUE | M27: The cardinal direction that a camera faces. Ideally, cameras should face north (N; i.e. '0' degrees), or south (S; i.e. '180' degrees) if north is not possible. The Camera Direction should be chosen to ensure the field of view (FOV) is of the original FOV target feature. | N27: The cardinal direction that a camera faces. Ideally, cameras should face north (N; i.e. '0' degrees), or south (S; i.e. '180' degrees) if north is not possible. The Camera Direction should be chosen to ensure the field of view (FOV) is of the original FOV target feature. | O27: =IF(M27=999,"",(" term_"&J27&": """&K27&"""")) -> term_cam_direction: "Camera Direction (degrees)" | P27: =IF(M27="-","-",(" def_"&J27&": """&M27&"""")) -> def_cam_direction: "The cardinal direction that a camera faces. Ideally, cameras should face north (N; i.e. '0' degrees), or south (S; i.e. '180' degrees) if north is not possible. The Camera Direction should be chosen to ensure the field of view (FOV) is of the original FOV target feature." | R27: FALSE | S27: TRUE | T27: TRUE | U27: xx | V27: \" target=\"_blank\" data-bs-toggle=\"tooltip\" data-bs-title=\" | W27: \"> | X27: <button type=\"button\" class=\"btn btn-bd-tip-info-hidden btn-sm position-relative\">.<span class=\"position-absolute top-0 start-100 translate-middle\">{{ icon_info }}</span></button></a> | Y27: =IF(M27<>"-",(" "&J27&"_ti"&": "&""""&"<a href=\"&""""&"09_glossary.html#"&J27&V27&K27&": "&M27&W27&""&X27&""""),"-") -> cam_direction_ti: "<a href=\"09_glossary.html#cam_direction\" target=\"_blank\" data-bs-toggle=\"tooltip\" data-bs-title=\"Camera Direction (degrees): The cardinal direction that a camera faces. Ideally, cameras should face north (N; i.e. '0' degrees), or south (S; i.e. '180' degrees) if north is not possible. The Camera Direction should be chosen to ensure the field of view (FOV) is of the original FOV target feature.\"><button type=\"button\" class=\"btn btn-bd-tip-info-hidden btn-sm position-relative\">.<span class=\"position-absolute top-0 start-100 translate-middle\">{{ icon_info }}</span></button></a>"
B28: 18 | C28: field | D28: - | E28: **Camera Height (m) ** | F28: upper | G28: surv_guide_meta | H28: cam_visit_placement | I28: cam_height | J28: =IF(D28<>"-",I28&"_"&D28,I28) -> cam_height | K28: Camera Height (m) | L28: =IF(VLOOKUP(J28,find_replace!H:H,1,"false")=J28,"TRUE","FALSE") -> TRUE | M28: The height from the ground (below snow) to the bottom of the lens (metres; to the nearest 0.05 m). | N28: The height from the ground (below snow) to the bottom of the lens (metres; to the nearest 0.05 m). | O28: =IF(M28=999,"",(" term_"&J28&": """&K28&"""")) -> term_cam_height: "Camera Height (m)" | P28: =IF(M28="-","-",(" def_"&J28&": """&M28&"""")) -> def_cam_height: "The height from the ground (below snow) to the bottom of the lens (metres; to the nearest 0.05 m)." | R28: TRUE | S28: TRUE | T28: TRUE | U28: xx | V28: \" target=\"_blank\" data-bs-toggle=\"tooltip\" data-bs-title=\" | W28: \"> | X28: <button type=\"button\" class=\"btn btn-bd-tip-info-hidden btn-sm position-relative\">.<span class=\"position-absolute top-0 start-100 translate-middle\">{{ icon_info }}</span></button></a> | Y28: =IF(M28<>"-",(" "&J28&"_ti"&": "&""""&"<a href=\"&""""&"09_glossary.html#"&J28&V28&K28&": "&M28&W28&""&X28&""""),"-") -> cam_height_ti: "<a href=\"09_glossary.html#cam_height\" target=\"_blank\" data-bs-toggle=\"tooltip\" data-bs-title=\"Camera Height (m): The height from the ground (below snow) to the bottom of the lens (metres; to the nearest 0.05 m).\"><button type=\"button\" class=\"btn btn-bd-tip-info-hidden btn-sm position-relative\">.<span class=\"position-absolute top-0 start-100 translate-middle\">{{ icon_info }}</span></button></a>"
B29: 19 | C29: field | D29: - | E29: **Camera ID** | F29: upper | G29: surv_guide_meta | H29: cam_visit_equip | I29: cam_id | J29: =IF(D29<>"-",I29&"_"&D29,I29) -> cam_id | K29: Camera ID | L29: =IF(VLOOKUP(J29,find_replace!H:H,1,"false")=J29,"TRUE","FALSE") -> TRUE | M29: A unique alphanumeric ID for the camera that distinguishes it from other cameras of the same make or model. | N29: A unique alphanumeric ID for the camera that distinguishes it from other cameras of the same make or model. | O29: =IF(M29=999,"",(" term_"&J29&": """&K29&"""")) -> term_cam_id: "Camera ID" | P29: =IF(M29="-","-",(" def_"&J29&": """&M29&"""")) -> def_cam_id: "A unique alphanumeric ID for the camera that distinguishes it from other cameras of the same make or model." | R29: TRUE | S29: TRUE | T29: TRUE | U29: xx | V29: \" target=\"_blank\" data-bs-toggle=\"tooltip\" data-bs-title=\" | W29: \"> | X29: <button type=\"button\" class=\"btn btn-bd-tip-info-hidden btn-sm position-relative\">.<span class=\"position-absolute top-0 start-100 translate-middle\">{{ icon_info }}</span></button></a> | Y29: =IF(M29<>"-",(" "&J29&"_ti"&": "&""""&"<a href=\"&""""&"09_glossary.html#"&J29&V29&K29&": "&M29&W29&""&X29&""""),"-") -> cam_id_ti: "<a href=\"09_glossary.html#cam_id\" target=\"_blank\" data-bs-toggle=\"tooltip\" data-bs-title=\"Camera ID: A unique alphanumeric ID for the camera that distinguishes it from other cameras of the same make or model.\"><button type=\"button\" class=\"btn btn-bd-tip-info-hidden btn-sm position-relative\">.<span class=\"position-absolute top-0 start-100 translate-middle\">{{ icon_info }}</span></button></a>"
B30: 20 | C30: term | D30: - | E30: Camera location | G30: surv_guide_meta | H30: cam_loc_station | I30: cam_location | J30: =IF(D30<>"-",I30&"_"&D30,I30) -> cam_location | K30: Camera location | L30: =IF(VLOOKUP(J30,find_replace!H:H,1,"false")=J30,"TRUE","FALSE") -> TRUE | M30: The location where a single camera was placed (recorded as 'Camera Location Name'). | N30: The location where a single camera was placed (recorded as 'Camera Location Name'). | O30: =IF(M30=999,"",(" term_"&J30&": """&K30&"""")) -> term_cam_location: "Camera location" | P30: =IF(M30="-","-",(" def_"&J30&": """&M30&"""")) -> def_cam_location: "The location where a single camera was placed (recorded as 'Camera Location Name')." | R30: NULL | S30: TRUE | T30: TRUE | U30: xx | V30: \" target=\"_blank\" data-bs-toggle=\"tooltip\" data-bs-title=\" | W30: \"> | X30: <button type=\"button\" class=\"btn btn-bd-tip-info-hidden btn-sm position-relative\">.<span class=\"position-absolute top-0 start-100 translate-middle\">{{ icon_info }}</span></button></a> | Y30: =IF(M30<>"-",(" "&J30&"_ti"&": "&""""&"<a href=\"&""""&"09_glossary.html#"&J30&V30&K30&": "&M30&W30&""&X30&""""),"-") -> cam_location_ti: "<a href=\"09_glossary.html#cam_location\" target=\"_blank\" data-bs-toggle=\"tooltip\" data-bs-title=\"Camera location: The location where a single camera was placed (recorded as 'Camera Location Name').\"><button type=\"button\" class=\"btn btn-bd-tip-info-hidden btn-sm position-relative\">.<span class=\"position-absolute top-0 start-100 translate-middle\">{{ icon_info }}</span></button></a>"
B31: 21 | C31: field | D31: - | E31: **\*Camera Location Characteristic(s)** | F31: upper | G31: surv_guide_meta | H31: cam_loc_station | I31: cam_location_characteristics | J31: =IF(D31<>"-",I31&"_"&D31,I31) -> cam_location_characteristics | K31: Camera Location Characteristic(s) | L31: =IF(VLOOKUP(J31,find_replace!H:H,1,"false")=J31,"TRUE","FALSE") -> TRUE | M31: Any significant features around the camera at the time of the visit. This may include for example, manmade or natural linear features (e.g., trails), habitat types (e.g., wetlands), wildlife structure (e.g., beaver dam). If 'Other,' describe in the Camera Location Comments. <br><br>Camera Location Characteristics differ from FOV Target Features in that Camera Location Characteristics could include those not in the camera's Field of View. If 'Other,' describe in the Camera Location Comments. | N31: Any significant features around the camera at the time of the visit. This may include for example, manmade or natural linear features (e.g., trails), habitat types (e.g., wetlands), wildlife structure (e.g., beaver dam). If 'Other,' describe in the Camera Location Comments. <br><br>Camera Location Characteristics differ from FOV Target Features in that Camera Location Characteristics could include those not in the camera's Field of View. If 'Other,' describe in the Camera Location Comments. | O31: =IF(M31=999,"",(" term_"&J31&": """&K31&"""")) -> term_cam_location_characteristics: "Camera Location Characteristic(s)" | P31: =IF(M31="-","-",(" def_"&J31&": """&M31&"""")) -> def_cam_location_characteristics: "Any significant features around the camera at the time of the visit. This may include for example, manmade or natural linear features (e.g., trails), habitat types (e.g., wetlands), wildlife structure (e.g., beaver dam). If 'Other,' describe in the Camera Location Comments. <br><br>Camera Location Characteristics differ from FOV Target Features in that Camera Location Characteristics could include those not in the camera's Field of View. If 'Other,' describe in the Camera Location Comments." | Q31: TRUE | R31: FALSE | S31: TRUE | T31: TRUE | U31: xx | V31: \" target=\"_blank\" data-bs-toggle=\"tooltip\" data-bs-title=\" | W31: \"> | X31: <button type=\"button\" class=\"btn btn-bd-tip-info-hidden btn-sm position-relative\">.<span class=\"position-absolute top-0 start-100 translate-middle\">{{ icon_info }}</span></button></a> | Y31: =IF(M31<>"-",(" "&J31&"_ti"&": "&""""&"<a href=\"&""""&"09_glossary.html#"&J31&V31&K31&": "&M31&W31&""&X31&""""),"-") -> cam_location_characteristics_ti: "<a href=\"09_glossary.html#cam_location_characteristics\" target=\"_blank\" data-bs-toggle=\"tooltip\" data-bs-title=\"Camera Location Characteristic(s): Any significant features around the camera at the time of the visit. This may include for example, manmade or natural linear features (e.g., trails), habitat types (e.g., wetlands), wildlife structure (e.g., beaver dam). If 'Other,' describe in the Camera Location Comments. <br><br>Camera Location Characteristics differ from FOV Target Features in that Camera Location Characteristics could include those not in the camera's Field of View. If 'Other,' describe in the Camera Location Comments.\"><button type=\"button\" class=\"btn btn-bd-tip-info-hidden btn-sm position-relative\">.<span class=\"position-absolute top-0 start-100 translate-middle\">{{ icon_info }}</span></button></a>"
B32: 22 | C32: field | D32: - | E32: **\*Camera Location Comments** | F32: upper | G32: surv_guide_meta | H32: cam_loc_station | I32: cam_location_comments | J32: =IF(D32<>"-",I32&"_"&D32,I32) -> cam_location_comments | K32: Camera Location Comments | L32: =IF(VLOOKUP(J32,find_replace!H:H,1,"false")=J32,"TRUE","FALSE") -> TRUE | M32: Comments describing additional details about a camera location. | N32: Comments describing additional details about a camera location. | O32: =IF(M32=999,"",(" term_"&J32&": """&K32&"""")) -> term_cam_location_comments: "Camera Location Comments" | P32: =IF(M32="-","-",(" def_"&J32&": """&M32&"""")) -> def_cam_location_comments: "Comments describing additional details about a camera location." | R32: FALSE | S32: TRUE | T32: TRUE | U32: xx | V32: \" target=\"_blank\" data-bs-toggle=\"tooltip\" data-bs-title=\" | W32: \"> | X32: <button type=\"button\" class=\"btn btn-bd-tip-info-hidden btn-sm position-relative\">.<span class=\"position-absolute top-0 start-100 translate-middle\">{{ icon_info }}</span></button></a> | Y32: =IF(M32<>"-",(" "&J32&"_ti"&": "&""""&"<a href=\"&""""&"09_glossary.html#"&J32&V32&K32&": "&M32&W32&""&X32&""""),"-") -> cam_location_comments_ti: "<a href=\"09_glossary.html#cam_location_comments\" target=\"_blank\" data-bs-toggle=\"tooltip\" data-bs-title=\"Camera Location Comments: Comments describing additional details about a camera location.\"><button type=\"button\" class=\"btn btn-bd-tip-info-hidden btn-sm position-relative\">.<span class=\"position-absolute top-0 start-100 translate-middle\">{{ icon_info }}</span></button></a>"
B33: 23 | C33: field | D33: - | E33: **Camera Location Name** | F33: upper | G33: surv_guide_meta | H33: cam_loc_station | I33: cam_location_name | J33: =IF(D33<>"-",I33&"_"&D33,I33) -> cam_location_name | K33: Camera Location Name | L33: =IF(VLOOKUP(J33,find_replace!H:H,1,"false")=J33,"TRUE","FALSE") -> TRUE | M33: A unique alphanumeric identifier for the location where a single camera was placed (e.g., 'bh1,' 'bh2'). | N33: A unique alphanumeric identifier for the location where a single camera was placed (e.g., 'bh1,' 'bh2'). | O33: =IF(M33=999,"",(" term_"&J33&": """&K33&"""")) -> term_cam_location_name: "Camera Location Name" | P33: =IF(M33="-","-",(" def_"&J33&": """&M33&"""")) -> def_cam_location_name: "A unique alphanumeric identifier for the location where a single camera was placed (e.g., 'bh1,' 'bh2')." | R33: TRUE | S33: TRUE | T33: TRUE | U33: xx | V33: \" target=\"_blank\" data-bs-toggle=\"tooltip\" data-bs-title=\" | W33: \"> | X33: <button type=\"button\" class=\"btn btn-bd-tip-info-hidden btn-sm position-relative\">.<span class=\"position-absolute top-0 start-100 translate-middle\">{{ icon_info }}</span></button></a> | Y33: =IF(M33<>"-",(" "&J33&"_ti"&": "&""""&"<a href=\"&""""&"09_glossary.html#"&J33&V33&K33&": "&M33&W33&""&X33&""""),"-") -> cam_location_name_ti: "<a href=\"09_glossary.html#cam_location_name\" target=\"_blank\" data-bs-toggle=\"tooltip\" data-bs-title=\"Camera Location Name: A unique alphanumeric identifier for the location where a single camera was placed (e.g., 'bh1,' 'bh2').\"><button type=\"button\" class=\"btn btn-bd-tip-info-hidden btn-sm position-relative\">.<span class=\"position-absolute top-0 start-100 translate-middle\">{{ icon_info }}</span></button></a>"
B34: 24 | C34: field | D34: - | E34: **Camera Make** | F34: upper | G34: surv_guide_meta | H34: cam_visit_equip | I34: cam_make | J34: =IF(D34<>"-",I34&"_"&D34,I34) -> cam_make | K34: Camera Make | L34: =IF(VLOOKUP(J34,find_replace!H:H,1,"false")=J34,"TRUE","FALSE") -> TRUE | M34: The make of a particular camera (i.e., the manufacturer, e.g., 'Reconyx' or 'Bushnell'). | N34: The make of a particular camera (i.e., the manufacturer, e.g., 'Reconyx' or 'Bushnell'). | O34: =IF(M34=999,"",(" term_"&J34&": """&K34&"""")) -> term_cam_make: "Camera Make" | P34: =IF(M34="-","-",(" def_"&J34&": """&M34&"""")) -> def_cam_make: "The make of a particular camera (i.e., the manufacturer, e.g., 'Reconyx' or 'Bushnell')." | R34: TRUE | S34: TRUE | T34: TRUE | U34: xx | V34: \" target=\"_blank\" data-bs-toggle=\"tooltip\" data-bs-title=\" | W34: \"> | X34: <button type=\"button\" class=\"btn btn-bd-tip-info-hidden btn-sm position-relative\">.<span class=\"position-absolute top-0 start-100 translate-middle\">{{ icon_info }}</span></button></a> | Y34: =IF(M34<>"-",(" "&J34&"_ti"&": "&""""&"<a href=\"&""""&"09_glossary.html#"&J34&V34&K34&": "&M34&W34&""&X34&""""),"-") -> cam_make_ti: "<a href=\"09_glossary.html#cam_make\" target=\"_blank\" data-bs-toggle=\"tooltip\" data-bs-title=\"Camera Make: The make of a particular camera (i.e., the manufacturer, e.g., 'Reconyx' or 'Bushnell').\"><button type=\"button\" class=\"btn btn-bd-tip-info-hidden btn-sm position-relative\">.<span class=\"position-absolute top-0 start-100 translate-middle\">{{ icon_info }}</span></button></a>"
B35: 25 | C35: field | D35: - | E35: **Camera Model** | F35: upper | G35: surv_guide_meta | H35: cam_visit_equip | I35: cam_model | J35: =IF(D35<>"-",I35&"_"&D35,I35) -> cam_model | K35: Camera Model | L35: =IF(VLOOKUP(J35,find_replace!H:H,1,"false")=J35,"TRUE","FALSE") -> TRUE | M35: The model number or name of a particular camera (e.g., 'PC900' or 'Trophy Cam HD'). | N35: The model number or name of a particular camera (e.g., 'PC900' or 'Trophy Cam HD'). | O35: =IF(M35=999,"",(" term_"&J35&": """&K35&"""")) -> term_cam_model: "Camera Model" | P35: =IF(M35="-","-",(" def_"&J35&": """&M35&"""")) -> def_cam_model: "The model number or name of a particular camera (e.g., 'PC900' or 'Trophy Cam HD')." | R35: TRUE | S35: TRUE | T35: TRUE | U35: xx | V35: \" target=\"_blank\" data-bs-toggle=\"tooltip\" data-bs-title=\" | W35: \"> | X35: <button type=\"button\" class=\"btn btn-bd-tip-info-hidden btn-sm position-relative\">.<span class=\"position-absolute top-0 start-100 translate-middle\">{{ icon_info }}</span></button></a> | Y35: =IF(M35<>"-",(" "&J35&"_ti"&": "&""""&"<a href=\"&""""&"09_glossary.html#"&J35&V35&K35&": "&M35&W35&""&X35&""""),"-") -> cam_model_ti: "<a href=\"09_glossary.html#cam_model\" target=\"_blank\" data-bs-toggle=\"tooltip\" data-bs-title=\"Camera Model: The model number or name of a particular camera (e.g., 'PC900' or 'Trophy Cam HD').\"><button type=\"button\" class=\"btn btn-bd-tip-info-hidden btn-sm position-relative\">.<span class=\"position-absolute top-0 start-100 translate-middle\">{{ icon_info }}</span></button></a>"
B36: 26 | C36: field | D36: - | E36: **Camera Serial Number** | F36: upper | G36: surv_guide_meta | H36: cam_visit_equip | I36: cam_serial_number | J36: =IF(D36<>"-",I36&"_"&D36,I36) -> cam_serial_number | K36: Camera Serial Number | L36: =IF(VLOOKUP(J36,find_replace!H:H,1,"false")=J36,"TRUE","FALSE") -> TRUE | M36: The serial number of a particular camera, which is usually found inside the camera cover (e.g., 'P900FF04152022'). | N36: The serial number of a particular camera, which is usually found inside the camera cover (e.g., 'P900FF04152022'). | O36: =IF(M36=999,"",(" term_"&J36&": """&K36&"""")) -> term_cam_serial_number: "Camera Serial Number" | P36: =IF(M36="-","-",(" def_"&J36&": """&M36&"""")) -> def_cam_serial_number: "The serial number of a particular camera, which is usually found inside the camera cover (e.g., 'P900FF04152022')." | R36: TRUE | S36: TRUE | T36: TRUE | U36: xx | V36: \" target=\"_blank\" data-bs-toggle=\"tooltip\" data-bs-title=\" | W36: \"> | X36: <button type=\"button\" class=\"btn btn-bd-tip-info-hidden btn-sm position-relative\">.<span class=\"position-absolute top-0 start-100 translate-middle\">{{ icon_info }}</span></button></a> | Y36: =IF(M36<>"-",(" "&J36&"_ti"&": "&""""&"<a href=\"&""""&"09_glossary.html#"&J36&V36&K36&": "&M36&W36&""&X36&""""),"-") -> cam_serial_number_ti: "<a href=\"09_glossary.html#cam_serial_number\" target=\"_blank\" data-bs-toggle=\"tooltip\" data-bs-title=\"Camera Serial Number: The serial number of a particular camera, which is usually found inside the camera cover (e.g., 'P900FF04152022').\"><button type=\"button\" class=\"btn btn-bd-tip-info-hidden btn-sm position-relative\">.<span class=\"position-absolute top-0 start-100 translate-middle\">{{ icon_info }}</span></button></a>"
B37: 27 | C37: term | D37: - | E37: Camera spacing | G37: surv_guide_meta | H37: sampledesign | I37: cam_spacing | J37: =IF(D37<>"-",I37&"_"&D37,I37) -> cam_spacing | K37: Camera spacing | L37: =IF(VLOOKUP(J37,find_replace!H:H,1,"false")=J37,"TRUE","FALSE") -> TRUE | M37: The distance between cameras (i.e., also referred to as 'inter-trap distance'). This will be influenced by the chosen sampling design, the [survey](#survey) Objectives, the Target Species and data analysis. | N37: The distance between cameras (i.e., also referred to as 'inter-trap distance'). This will be influenced by the chosen sampling design, the survey Objectives, the Target Species and data analysis. | O37: =IF(M37=999,"",(" term_"&J37&": """&K37&"""")) -> term_cam_spacing: "Camera spacing" | P37: =IF(M37="-","-",(" def_"&J37&": """&M37&"""")) -> def_cam_spacing: "The distance between cameras (i.e., also referred to as 'inter-trap distance'). This will be influenced by the chosen sampling design, the [survey](#survey) Objectives, the Target Species and data analysis." | R37: NULL | S37: FALSE | T37: TRUE | U37: xx | V37: \" target=\"_blank\" data-bs-toggle=\"tooltip\" data-bs-title=\" | W37: \"> | X37: <button type=\"button\" class=\"btn btn-bd-tip-info-hidden btn-sm position-relative\">.<span class=\"position-absolute top-0 start-100 translate-middle\">{{ icon_info }}</span></button></a> | Y37: =IF(M37<>"-",(" "&J37&"_ti"&": "&""""&"<a href=\"&""""&"09_glossary.html#"&J37&V37&K37&": "&M37&W37&""&X37&""""),"-") -> cam_spacing_ti: "<a href=\"09_glossary.html#cam_spacing\" target=\"_blank\" data-bs-toggle=\"tooltip\" data-bs-title=\"Camera spacing: The distance between cameras (i.e., also referred to as 'inter-trap distance'). This will be influenced by the chosen sampling design, the [survey](#survey) Objectives, the Target Species and data analysis.\"><button type=\"button\" class=\"btn btn-bd-tip-info-hidden btn-sm position-relative\">.<span class=\"position-absolute top-0 start-100 translate-middle\">{{ icon_info }}</span></button></a>"
B38: 28 | C38: term | D38: - | E38: Capture-recapture (CR) model */ Capture-mark-recapture (CMR) model (Karanth, 1995; Karanth & Nichols, 1998) | F38: upper | G38: surv_guide_meta | H38: approach | I38: mod_cr_cmr | J38: =IF(D38<>"-",I38&"_"&D38,I38) -> mod_cr_cmr | K38: Capture-recapture (CR) / Capture-mark-recapture (CMR) (Karanth, 1995; Karanth & Nichols, 1998) | L38: =IF(VLOOKUP(J38,find_replace!H:H,1,"false")=J38,"TRUE","FALSE") -> TRUE | M38: A method of estimating the abundance or [density](#density) of marked populations using the number of animals detected and the likelihood animals will be detected (detection probability). CR (Karanth, 1995; Karanth & Nichols, 1998) can be used to estimate vital rates where all newly detected unmarked animals become marked and are distinguishable in future (Efford, 2022). Spatially explicit capture-recapture (SECR; Borchers & Efford, 2008; Efford, 2004; Royle & Young, 2008) models have largely replaced CR and CMR models and provide more accurate [density](#density) estimates (Blanc et al., 2013, Obbard et al., 2010, Sollmann et al., 2011). | N38: A method of estimating the abundance or density of marked populations using the number of animals detected and the likelihood animals will be detected (detection probability). CR (Karanth, 1995; Karanth & Nichols, 1998) can be used to estimate vital rates where all newly detected unmarked animals become marked and are distinguishable in future (Efford, 2022). Spatially explicit capture-recapture (SECR; Borchers & Efford, 2008; Efford, 2004; Royle & Young, 2008) models have largely replaced CR and CMR models and provide more accurate density estimates (Blanc et al., 2013, Obbard et al., 2010, Sollmann et al., 2011). | O38: =IF(M38=999,"",(" term_"&J38&": """&K38&"""")) -> term_mod_cr_cmr: "Capture-recapture (CR) / Capture-mark-recapture (CMR) (Karanth, 1995; Karanth & Nichols, 1998)" | P38: =IF(M38="-","-",(" def_"&J38&": """&M38&"""")) -> def_mod_cr_cmr: "A method of estimating the abundance or [density](#density) of marked populations using the number of animals detected and the likelihood animals will be detected (detection probability). CR (Karanth, 1995; Karanth & Nichols, 1998) can be used to estimate vital rates where all newly detected unmarked animals become marked and are distinguishable in future (Efford, 2022). Spatially explicit capture-recapture (SECR; Borchers & Efford, 2008; Efford, 2004; Royle & Young, 2008) models have largely replaced CR and CMR models and provide more accurate [density](#density) estimates (Blanc et al., 2013, Obbard et al., 2010, Sollmann et al., 2011)." | R38: NULL | S38: FALSE | T38: TRUE | U38: xx | V38: \" target=\"_blank\" data-bs-toggle=\"tooltip\" data-bs-title=\" | W38: \"> | X38: <button type=\"button\" class=\"btn btn-bd-tip-info-hidden btn-sm position-relative\">.<span class=\"position-absolute top-0 start-100 translate-middle\">{{ icon_info }}</span></button></a> | Y38: =IF(M38<>"-",(" "&J38&"_ti"&": "&""""&"<a href=\"&""""&"09_glossary.html#"&J38&V38&K38&": "&M38&W38&""&X38&""""),"-") -> mod_cr_cmr_ti: "<a href=\"09_glossary.html#mod_cr_cmr\" target=\"_blank\" data-bs-toggle=\"tooltip\" data-bs-title=\"Capture-recapture (CR) / Capture-mark-recapture (CMR) (Karanth, 1995; Karanth & Nichols, 1998): A method of estimating the abundance or [density](#density) of marked populations using the number of animals detected and the likelihood animals will be detected (detection probability). CR (Karanth, 1995; Karanth & Nichols, 1998) can be used to estimate vital rates where all newly detected unmarked animals become marked and are distinguishable in future (Efford, 2022). Spatially explicit capture-recapture (SECR; Borchers & Efford, 2008; Efford, 2004; Royle & Young, 2008) models have largely replaced CR and CMR models and provide more accurate [density](#density) estimates (Blanc et al., 2013, Obbard et al., 2010, Sollmann et al., 2011).\"><button type=\"button\" class=\"btn btn-bd-tip-info-hidden btn-sm position-relative\">.<span class=\"position-absolute top-0 start-100 translate-middle\">{{ icon_info }}</span></button></a>"
B39: 29 | C39: term | D39: - | E39: Categorical partial identity model (catSPIM) (Augustine et al., 2019; Sun et al., 2022) | F39: upper | G39: surv_guide_meta | H39: approach | I39: mod_catspim | J39: =IF(D39<>"-",I39&"_"&D39,I39) -> mod_catspim | K39: Categorical partial identity model (Categorical SPIM; catSPIM) (Augustine et al., 2019; Sun et al., 2022) | L39: =IF(VLOOKUP(J39,find_replace!H:H,1,"false")=J39,"TRUE","FALSE") -> TRUE | M39: A method used to estimate the [density](#density) of partially marked populations in which the 'spatial locations of where partial identity samples are captured to probabilistically resolve their complete identities' (Augustine et al., 2018, 2019). catSPIM models use partial identity traits (e.g., sex class, antler points) to help infer individual identities (Augustine et al., 2019; Sun et al., 2022). catSPIM is an extension of the SC model ({{ rtxt_chandler_royle_2013 }}). | N39: A method used to estimate the density of partially marked populations in which the 'spatial locations of where partial identity samples are captured to probabilistically resolve their complete identities' (Augustine et al., 2018, 2019). catSPIM models use partial identity traits (e.g., sex class, antler points) to help infer individual identities (Augustine et al., 2019; Sun et al., 2022). catSPIM is an extension of the SC model (Chandler & Royle, 2013). | O39: =IF(M39=999,"",(" term_"&J39&": """&K39&"""")) -> term_mod_catspim: "Categorical partial identity model (Categorical SPIM; catSPIM) (Augustine et al., 2019; Sun et al., 2022)" | P39: =IF(M39="-","-",(" def_"&J39&": """&M39&"""")) -> def_mod_catspim: "A method used to estimate the [density](#density) of partially marked populations in which the 'spatial locations of where partial identity samples are captured to probabilistically resolve their complete identities' (Augustine et al., 2018, 2019). catSPIM models use partial identity traits (e.g., sex class, antler points) to help infer individual identities (Augustine et al., 2019; Sun et al., 2022). catSPIM is an extension of the SC model ({{ rtxt_chandler_royle_2013 }})." | R39: NULL | S39: FALSE | T39: TRUE | U39: xx | V39: \" target=\"_blank\" data-bs-toggle=\"tooltip\" data-bs-title=\" | W39: \"> | X39: <button type=\"button\" class=\"btn btn-bd-tip-info-hidden btn-sm position-relative\">.<span class=\"position-absolute top-0 start-100 translate-middle\">{{ icon_info }}</span></button></a> | Y39: =IF(M39<>"-",(" "&J39&"_ti"&": "&""""&"<a href=\"&""""&"09_glossary.html#"&J39&V39&K39&": "&M39&W39&""&X39&""""),"-") -> mod_catspim_ti: "<a href=\"09_glossary.html#mod_catspim\" target=\"_blank\" data-bs-toggle=\"tooltip\" data-bs-title=\"Categorical partial identity model (Categorical SPIM; catSPIM) (Augustine et al., 2019; Sun et al., 2022): A method used to estimate the [density](#density) of partially marked populations in which the 'spatial locations of where partial identity samples are captured to probabilistically resolve their complete identities' (Augustine et al., 2018, 2019). catSPIM models use partial identity traits (e.g., sex class, antler points) to help infer individual identities (Augustine et al., 2019; Sun et al., 2022). catSPIM is an extension of the SC model ({{ rtxt_chandler_royle_2013 }}).\"><button type=\"button\" class=\"btn btn-bd-tip-info-hidden btn-sm position-relative\">.<span class=\"position-absolute top-0 start-100 translate-middle\">{{ icon_info }}</span></button></a>"
B40: 30 | C40: term | D40: - | E40: Clustered design | G40: surv_guide_meta | H40: sampledesign | I40: sampledesign_clustered | J40: =IF(D40<>"-",I40&"_"&D40,I40) -> sampledesign_clustered | K40: Clustered design | L40: =IF(VLOOKUP(J40,find_replace!H:H,1,"false")=J40,"TRUE","FALSE") -> TRUE | M40: Multiple cameras are deployed at a sample station (Figure 3d). A clustered design can be used within a systematic or stratified approach (i.e., systematic clustered design or as a clustered random design [{{ rtxt_wearn_gloverkapfer_2017 }}]). | N40: Multiple cameras are deployed at a sample station (Figure 3d). A clustered design can be used within a systematic or stratified approach (i.e., systematic clustered design or as a clustered random design [Wearn & Glover-Kapfer, 2017]). | O40: =IF(M40=999,"",(" term_"&J40&": """&K40&"""")) -> term_sampledesign_clustered: "Clustered design" | P40: =IF(M40="-","-",(" def_"&J40&": """&M40&"""")) -> def_sampledesign_clustered: "Multiple cameras are deployed at a sample station (Figure 3d). A clustered design can be used within a systematic or stratified approach (i.e., systematic clustered design or as a clustered random design [{{ rtxt_wearn_gloverkapfer_2017 }}])." | R40: NULL | S40: TRUE | T40: TRUE | U40: xx | V40: \" target=\"_blank\" data-bs-toggle=\"tooltip\" data-bs-title=\" | W40: \"> | X40: <button type=\"button\" class=\"btn btn-bd-tip-info-hidden btn-sm position-relative\">.<span class=\"position-absolute top-0 start-100 translate-middle\">{{ icon_info }}</span></button></a> | Y40: =IF(M40<>"-",(" "&J40&"_ti"&": "&""""&"<a href=\"&""""&"09_glossary.html#"&J40&V40&K40&": "&M40&W40&""&X40&""""),"-") -> sampledesign_clustered_ti: "<a href=\"09_glossary.html#sampledesign_clustered\" target=\"_blank\" data-bs-toggle=\"tooltip\" data-bs-title=\"Clustered design: Multiple cameras are deployed at a sample station (Figure 3d). A clustered design can be used within a systematic or stratified approach (i.e., systematic clustered design or as a clustered random design [{{ rtxt_wearn_gloverkapfer_2017 }}]).\"><button type=\"button\" class=\"btn btn-bd-tip-info-hidden btn-sm position-relative\">.<span class=\"position-absolute top-0 start-100 translate-middle\">{{ icon_info }}</span></button></a>"
B41: 31 | C41: term | D41: - | E41: Convenience design | G41: surv_guide_meta | H41: sampledesign | I41: sampledesign_convenience | J41: =IF(D41<>"-",I41&"_"&D41,I41) -> sampledesign_convenience | K41: Convenience design | L41: =IF(VLOOKUP(J41,find_replace!H:H,1,"false")=J41,"TRUE","FALSE") -> TRUE | M41: Camera locations or sample stations are chosen based on logistic considerations (e.g., remoteness, access constraints, and*/or costs). | N41: Camera locations or sample stations are chosen based on logistic considerations (e.g., remoteness, access constraints, and*/or costs). | O41: =IF(M41=999,"",(" term_"&J41&": """&K41&"""")) -> term_sampledesign_convenience: "Convenience design" | P41: =IF(M41="-","-",(" def_"&J41&": """&M41&"""")) -> def_sampledesign_convenience: "Camera locations or sample stations are chosen based on logistic considerations (e.g., remoteness, access constraints, and*/or costs)." | R41: NULL | S41: TRUE | T41: TRUE | U41: xx | V41: \" target=\"_blank\" data-bs-toggle=\"tooltip\" data-bs-title=\" | W41: \"> | X41: <button type=\"button\" class=\"btn btn-bd-tip-info-hidden btn-sm position-relative\">.<span class=\"position-absolute top-0 start-100 translate-middle\">{{ icon_info }}</span></button></a> | Y41: =IF(M41<>"-",(" "&J41&"_ti"&": "&""""&"<a href=\"&""""&"09_glossary.html#"&J41&V41&K41&": "&M41&W41&""&X41&""""),"-") -> sampledesign_convenience_ti: "<a href=\"09_glossary.html#sampledesign_convenience\" target=\"_blank\" data-bs-toggle=\"tooltip\" data-bs-title=\"Convenience design: Camera locations or sample stations are chosen based on logistic considerations (e.g., remoteness, access constraints, and*/or costs).\"><button type=\"button\" class=\"btn btn-bd-tip-info-hidden btn-sm position-relative\">.<span class=\"position-absolute top-0 start-100 translate-middle\">{{ icon_info }}</span></button></a>"
B42: 32 | C42: term | D42: - | E42: Crew | G42: surv_guide_meta | H42: cam_visit | I42: crew | J42: =IF(D42<>"-",I42&"_"&D42,I42) -> crew | K42: Crew | L42: =IF(VLOOKUP(J42,find_replace!H:H,1,"false")=J42,"TRUE","FALSE") -> TRUE | M42: The first and last names of all the individuals who collected data during the deployment visit ('Deployment Crew') and Service*/Retrieval visit ('Service*/Retrieval Crew'). | N42: The first and last names of all the individuals who collected data during the deployment visit ('Deployment Crew') and Service*/Retrieval visit ('Service*/Retrieval Crew'). | O42: =IF(M42=999,"",(" term_"&J42&": """&K42&"""")) -> term_crew: "Crew" | P42: =IF(M42="-","-",(" def_"&J42&": """&M42&"""")) -> def_crew: "The first and last names of all the individuals who collected data during the deployment visit ('Deployment Crew') and Service*/Retrieval visit ('Service*/Retrieval Crew')." | R42: NULL | S42: TRUE | T42: TRUE | U42: xx | V42: \" target=\"_blank\" data-bs-toggle=\"tooltip\" data-bs-title=\" | W42: \"> | X42: <button type=\"button\" class=\"btn btn-bd-tip-info-hidden btn-sm position-relative\">.<span class=\"position-absolute top-0 start-100 translate-middle\">{{ icon_info }}</span></button></a> | Y42: =IF(M42<>"-",(" "&J42&"_ti"&": "&""""&"<a href=\"&""""&"09_glossary.html#"&J42&V42&K42&": "&M42&W42&""&X42&""""),"-") -> crew_ti: "<a href=\"09_glossary.html#crew\" target=\"_blank\" data-bs-toggle=\"tooltip\" data-bs-title=\"Crew: The first and last names of all the individuals who collected data during the deployment visit ('Deployment Crew') and Service*/Retrieval visit ('Service*/Retrieval Crew').\"><button type=\"button\" class=\"btn btn-bd-tip-info-hidden btn-sm position-relative\">.<span class=\"position-absolute top-0 start-100 translate-middle\">{{ icon_info }}</span></button></a>"
B43: 33 | C43: term | D43: - | E43: Cumulative detection probability | G43: surv_guide_meta | H43: detection_fov | I43: cumulative_det_probability | J43: =IF(D43<>"-",I43&"_"&D43,I43) -> cumulative_det_probability | K43: Cumulative detection probability | L43: =IF(VLOOKUP(J43,find_replace!H:H,1,"false")=J43,"TRUE","FALSE") -> TRUE | M43: The probability of detecting a species at least once during the entire {{ tl_survey }} (Steenweg et al., 2019). | N43: The probability of detecting a species at least once during the entire survey (Steenweg et al., 2019). | O43: =IF(M43=999,"",(" term_"&J43&": """&K43&"""")) -> term_cumulative_det_probability: "Cumulative detection probability" | P43: =IF(M43="-","-",(" def_"&J43&": """&M43&"""")) -> def_cumulative_det_probability: "The probability of detecting a species at least once during the entire {{ tl_survey }} (Steenweg et al., 2019)." | R43: NULL | S43: FALSE | T43: TRUE | U43: xx | V43: \" target=\"_blank\" data-bs-toggle=\"tooltip\" data-bs-title=\" | W43: \"> | X43: <button type=\"button\" class=\"btn btn-bd-tip-info-hidden btn-sm position-relative\">.<span class=\"position-absolute top-0 start-100 translate-middle\">{{ icon_info }}</span></button></a> | Y43: =IF(M43<>"-",(" "&J43&"_ti"&": "&""""&"<a href=\"&""""&"09_glossary.html#"&J43&V43&K43&": "&M43&W43&""&X43&""""),"-") -> cumulative_det_probability_ti: "<a href=\"09_glossary.html#cumulative_det_probability\" target=\"_blank\" data-bs-toggle=\"tooltip\" data-bs-title=\"Cumulative detection probability: The probability of detecting a species at least once during the entire {{ tl_survey }} (Steenweg et al., 2019).\"><button type=\"button\" class=\"btn btn-bd-tip-info-hidden btn-sm position-relative\">.<span class=\"position-absolute top-0 start-100 translate-middle\">{{ icon_info }}</span></button></a>"
C44: term | D44: - | G44: kemp_et_al_2022 | I44: data | J44: =IF(D44<>"-",I44&"_"&D44,I44) -> data | K44: Data | L44: =IF(VLOOKUP(J44,find_replace!H:H,1,"false")=J44,"TRUE","FALSE") -> TRUE | M44: Information, commonly facts or numbers, that are collected and can be examined and/or measured to help guide decision-making.' ({{ rtxt_kemp_et_al_2022 }}). | N44: Information, commonly facts or numbers, that are collected and can be examined and/or measured to help guide decision-making.' (Kemp et al., 2022). | O44: =IF(M44=999,"",(" term_"&J44&": """&K44&"""")) -> term_data: "Data" | P44: =IF(M44="-","-",(" def_"&J44&": """&M44&"""")) -> def_data: "Information, commonly facts or numbers, that are collected and can be examined and/or measured to help guide decision-making.' ({{ rtxt_kemp_et_al_2022 }})." | U44: xx | V44: \" target=\"_blank\" data-bs-toggle=\"tooltip\" data-bs-title=\" | W44: \"> | X44: <button type=\"button\" class=\"btn btn-bd-tip-info-hidden btn-sm position-relative\">.<span class=\"position-absolute top-0 start-100 translate-middle\">{{ icon_info }}</span></button></a> | Y44: =IF(M44<>"-",(" "&J44&"_ti"&": "&""""&"<a href=\"&""""&"09_glossary.html#"&J44&V44&K44&": "&M44&W44&""&X44&""""),"-") -> data_ti: "<a href=\"09_glossary.html#data\" target=\"_blank\" data-bs-toggle=\"tooltip\" data-bs-title=\"Data: Information, commonly facts or numbers, that are collected and can be examined and/or measured to help guide decision-making.' ({{ rtxt_kemp_et_al_2022 }}).\"><button type=\"button\" class=\"btn btn-bd-tip-info-hidden btn-sm position-relative\">.<span class=\"position-absolute top-0 start-100 translate-middle\">{{ icon_info }}</span></button></a>"
C45: term | D45: - | E45: Density | G45: surv_guide_meta | H45: objective | I45: obj_density | J45: =IF(D45<>"-",I45&"_"&D45,I45) -> obj_density | K45: Density | L45: =IF(VLOOKUP(J45,find_replace!H:H,1,"false")=J45,"TRUE","FALSE") -> TRUE | M45: The number of individuals per unit area ({{ rtxt_wearn_gloverkapfer_2017 }}) | N45: The number of individuals per unit area (Wearn & Glover-Kapfer, 2017) | O45: =IF(M45=999,"",(" term_"&J45&": """&K45&"""")) -> term_obj_density: "Density" | P45: =IF(M45="-","-",(" def_"&J45&": """&M45&"""")) -> def_obj_density: "The number of individuals per unit area ({{ rtxt_wearn_gloverkapfer_2017 }})" | U45: xx | V45: \" target=\"_blank\" data-bs-toggle=\"tooltip\" data-bs-title=\" | W45: \"> | X45: <button type=\"button\" class=\"btn btn-bd-tip-info-hidden btn-sm position-relative\">.<span class=\"position-absolute top-0 start-100 translate-middle\">{{ icon_info }}</span></button></a> | Y45: =IF(M45<>"-",(" "&J45&"_ti"&": "&""""&"<a href=\"&""""&"09_glossary.html#"&J45&V45&K45&": "&M45&W45&""&X45&""""),"-") -> obj_density_ti: "<a href=\"09_glossary.html#obj_density\" target=\"_blank\" data-bs-toggle=\"tooltip\" data-bs-title=\"Density: The number of individuals per unit area ({{ rtxt_wearn_gloverkapfer_2017 }})\"><button type=\"button\" class=\"btn btn-bd-tip-info-hidden btn-sm position-relative\">.<span class=\"position-absolute top-0 start-100 translate-middle\">{{ icon_info }}</span></button></a>"
B46: 35 | C46: term | D46: - | E46: Deployment | G46: surv_guide_meta | H46: cam_visit_deploy | I46: deployment | J46: =IF(D46<>"-",I46&"_"&D46,I46) -> deployment | K46: Deployment | L46: =IF(VLOOKUP(J46,find_replace!H:H,1,"false")=J46,"TRUE","FALSE") -> TRUE | M46: A unique placement of a camera in space and time (recorded as 'Deployment Name'). There may be multiple deployments for one camera location. Deployments are often considered as the time between visits (i.e., deployment to service, service to service, and service to retrieval). Any change to camera location, sampling period, camera equipment (e.g., Trigger Sensitivity setting, becomes non-functioning), and*/or conditions (e.g., not baited then baited later; camera SD card replaced) should be documented as a unique deployment. | N46: A unique placement of a camera in space and time (recorded as 'Deployment Name'). There may be multiple deployments for one camera location. Deployments are often considered as the time between visits (i.e., deployment to service, service to service, and service to retrieval). Any change to camera location, sampling period, camera equipment (e.g., Trigger Sensitivity setting, becomes non-functioning), and*/or conditions (e.g., not baited then baited later; camera SD card replaced) should be documented as a unique deployment. | O46: =IF(M46=999,"",(" term_"&J46&": """&K46&"""")) -> term_deployment: "Deployment" | P46: =IF(M46="-","-",(" def_"&J46&": """&M46&"""")) -> def_deployment: "A unique placement of a camera in space and time (recorded as 'Deployment Name'). There may be multiple deployments for one camera location. Deployments are often considered as the time between visits (i.e., deployment to service, service to service, and service to retrieval). Any change to camera location, sampling period, camera equipment (e.g., Trigger Sensitivity setting, becomes non-functioning), and*/or conditions (e.g., not baited then baited later; camera SD card replaced) should be documented as a unique deployment." | R46: NULL | S46: TRUE | T46: TRUE | U46: xx | V46: \" target=\"_blank\" data-bs-toggle=\"tooltip\" data-bs-title=\" | W46: \"> | X46: <button type=\"button\" class=\"btn btn-bd-tip-info-hidden btn-sm position-relative\">.<span class=\"position-absolute top-0 start-100 translate-middle\">{{ icon_info }}</span></button></a> | Y46: =IF(M46<>"-",(" "&J46&"_ti"&": "&""""&"<a href=\"&""""&"09_glossary.html#"&J46&V46&K46&": "&M46&W46&""&X46&""""),"-") -> deployment_ti: "<a href=\"09_glossary.html#deployment\" target=\"_blank\" data-bs-toggle=\"tooltip\" data-bs-title=\"Deployment: A unique placement of a camera in space and time (recorded as 'Deployment Name'). There may be multiple deployments for one camera location. Deployments are often considered as the time between visits (i.e., deployment to service, service to service, and service to retrieval). Any change to camera location, sampling period, camera equipment (e.g., Trigger Sensitivity setting, becomes non-functioning), and*/or conditions (e.g., not baited then baited later; camera SD card replaced) should be documented as a unique deployment.\"><button type=\"button\" class=\"btn btn-bd-tip-info-hidden btn-sm position-relative\">.<span class=\"position-absolute top-0 start-100 translate-middle\">{{ icon_info }}</span></button></a>"
B47: 36 | C47: field | D47: - | E47: **\*Deployment Area Photo Numbers** | F47: upper | G47: surv_guide_meta | H47: cam_visit_deploy | I47: deployment_area_photo_numbers | J47: =IF(D47<>"-",I47&"_"&D47,I47) -> deployment_area_photo_numbers | K47: Deployment Area Photo Numbers | L47: =IF(VLOOKUP(J47,find_replace!H:H,1,"false")=J47,"TRUE","FALSE") -> TRUE | M47: The image numbers for the deployment area photos (if collected, e.g., 'DSC 100'). These are optionally documented on a Camera Deployment Field Datasheet for each set of camera deployment area photos. Leave blank if not applicable. | N47: The image numbers for the deployment area photos (if collected, e.g., 'DSC 100'). These are optionally documented on a Camera Deployment Field Datasheet for each set of camera deployment area photos. Leave blank if not applicable. | O47: =IF(M47=999,"",(" term_"&J47&": """&K47&"""")) -> term_deployment_area_photo_numbers: "Deployment Area Photo Numbers" | P47: =IF(M47="-","-",(" def_"&J47&": """&M47&"""")) -> def_deployment_area_photo_numbers: "The image numbers for the deployment area photos (if collected, e.g., 'DSC 100'). These are optionally documented on a Camera Deployment Field Datasheet for each set of camera deployment area photos. Leave blank if not applicable." | Q47: TRUE | R47: FALSE | S47: TRUE | T47: TRUE | U47: xx | V47: \" target=\"_blank\" data-bs-toggle=\"tooltip\" data-bs-title=\" | W47: \"> | X47: <button type=\"button\" class=\"btn btn-bd-tip-info-hidden btn-sm position-relative\">.<span class=\"position-absolute top-0 start-100 translate-middle\">{{ icon_info }}</span></button></a> | Y47: =IF(M47<>"-",(" "&J47&"_ti"&": "&""""&"<a href=\"&""""&"09_glossary.html#"&J47&V47&K47&": "&M47&W47&""&X47&""""),"-") -> deployment_area_photo_numbers_ti: "<a href=\"09_glossary.html#deployment_area_photo_numbers\" target=\"_blank\" data-bs-toggle=\"tooltip\" data-bs-title=\"Deployment Area Photo Numbers: The image numbers for the deployment area photos (if collected, e.g., 'DSC 100'). These are optionally documented on a Camera Deployment Field Datasheet for each set of camera deployment area photos. Leave blank if not applicable.\"><button type=\"button\" class=\"btn btn-bd-tip-info-hidden btn-sm position-relative\">.<span class=\"position-absolute top-0 start-100 translate-middle\">{{ icon_info }}</span></button></a>"
B48: 37 | C48: term | D48: - | E48: Deployment area photos | G48: surv_guide_meta | H48: cam_visit_deploy | I48: deployment_area_photos | J48: =IF(D48<>"-",I48&"_"&D48,I48) -> deployment_area_photos | K48: Deployment area photos | L48: =IF(VLOOKUP(J48,find_replace!H:H,1,"false")=J48,"TRUE","FALSE") -> TRUE | M48: Photos of the area around the camera location, collected as a permanent, visual record of the FOV Target Features, Camera Location Characteristics, environmental conditions (e.g., vegetation, ecosite, weather) or other variables of interest. The recommendation includes collecting four photos taken from the centre of the target detection zone (Figure 5), facing each of the four cardinal directions. The documentation of the collection of these photos is recorded as 'Deployment Area Photos Taken' (Y*/N). | N48: Photos of the area around the camera location, collected as a permanent, visual record of the FOV Target Features, Camera Location Characteristics, environmental conditions (e.g., vegetation, ecosite, weather) or other variables of interest. The recommendation includes collecting four photos taken from the centre of the target detection zone (Figure 5), facing each of the four cardinal directions. The documentation of the collection of these photos is recorded as 'Deployment Area Photos Taken' (Y*/N). | O48: =IF(M48=999,"",(" term_"&J48&": """&K48&"""")) -> term_deployment_area_photos: "Deployment area photos" | P48: =IF(M48="-","-",(" def_"&J48&": """&M48&"""")) -> def_deployment_area_photos: "Photos of the area around the camera location, collected as a permanent, visual record of the FOV Target Features, Camera Location Characteristics, environmental conditions (e.g., vegetation, ecosite, weather) or other variables of interest. The recommendation includes collecting four photos taken from the centre of the target detection zone (Figure 5), facing each of the four cardinal directions. The documentation of the collection of these photos is recorded as 'Deployment Area Photos Taken' (Y*/N)." | R48: NULL | S48: TRUE | T48: TRUE | U48: xx | V48: \" target=\"_blank\" data-bs-toggle=\"tooltip\" data-bs-title=\" | W48: \"> | X48: <button type=\"button\" class=\"btn btn-bd-tip-info-hidden btn-sm position-relative\">.<span class=\"position-absolute top-0 start-100 translate-middle\">{{ icon_info }}</span></button></a> | Y48: =IF(M48<>"-",(" "&J48&"_ti"&": "&""""&"<a href=\"&""""&"09_glossary.html#"&J48&V48&K48&": "&M48&W48&""&X48&""""),"-") -> deployment_area_photos_ti: "<a href=\"09_glossary.html#deployment_area_photos\" target=\"_blank\" data-bs-toggle=\"tooltip\" data-bs-title=\"Deployment area photos: Photos of the area around the camera location, collected as a permanent, visual record of the FOV Target Features, Camera Location Characteristics, environmental conditions (e.g., vegetation, ecosite, weather) or other variables of interest. The recommendation includes collecting four photos taken from the centre of the target detection zone (Figure 5), facing each of the four cardinal directions. The documentation of the collection of these photos is recorded as 'Deployment Area Photos Taken' (Y*/N).\"><button type=\"button\" class=\"btn btn-bd-tip-info-hidden btn-sm position-relative\">.<span class=\"position-absolute top-0 start-100 translate-middle\">{{ icon_info }}</span></button></a>"
B49: 38 | C49: field | D49: - | E49: **\*Deployment Area Photos Taken** | F49: upper | G49: surv_guide_meta | H49: cam_visit_deploy | I49: deployment_area_photos_taken | J49: =IF(D49<>"-",I49&"_"&D49,I49) -> deployment_area_photos_taken | K49: Deployment Area Photos Taken | L49: =IF(VLOOKUP(J49,find_replace!H:H,1,"false")=J49,"TRUE","FALSE") -> TRUE | M49: Whether deployment area photos were taken (yes*/no; optional). The recommendation includes collecting four photos taken from the centre of the target detection zone (Figure 5), facing each of the four cardinal directions. | N49: Whether deployment area photos were taken (yes*/no; optional). The recommendation includes collecting four photos taken from the centre of the target detection zone (Figure 5), facing each of the four cardinal directions. | O49: =IF(M49=999,"",(" term_"&J49&": """&K49&"""")) -> term_deployment_area_photos_taken: "Deployment Area Photos Taken" | P49: =IF(M49="-","-",(" def_"&J49&": """&M49&"""")) -> def_deployment_area_photos_taken: "Whether deployment area photos were taken (yes*/no; optional). The recommendation includes collecting four photos taken from the centre of the target detection zone (Figure 5), facing each of the four cardinal directions." | R49: FALSE | S49: TRUE | T49: TRUE | U49: xx | V49: \" target=\"_blank\" data-bs-toggle=\"tooltip\" data-bs-title=\" | W49: \"> | X49: <button type=\"button\" class=\"btn btn-bd-tip-info-hidden btn-sm position-relative\">.<span class=\"position-absolute top-0 start-100 translate-middle\">{{ icon_info }}</span></button></a> | Y49: =IF(M49<>"-",(" "&J49&"_ti"&": "&""""&"<a href=\"&""""&"09_glossary.html#"&J49&V49&K49&": "&M49&W49&""&X49&""""),"-") -> deployment_area_photos_taken_ti: "<a href=\"09_glossary.html#deployment_area_photos_taken\" target=\"_blank\" data-bs-toggle=\"tooltip\" data-bs-title=\"Deployment Area Photos Taken: Whether deployment area photos were taken (yes*/no; optional). The recommendation includes collecting four photos taken from the centre of the target detection zone (Figure 5), facing each of the four cardinal directions.\"><button type=\"button\" class=\"btn btn-bd-tip-info-hidden btn-sm position-relative\">.<span class=\"position-absolute top-0 start-100 translate-middle\">{{ icon_info }}</span></button></a>"
B50: 39 | C50: field | D50: - | E50: **\*Deployment Comments** | F50: upper | G50: surv_guide_meta | H50: cam_visit_deploy | I50: deployment_comments | J50: =IF(D50<>"-",I50&"_"&D50,I50) -> deployment_comments | K50: Deployment Comments | L50: =IF(VLOOKUP(J50,find_replace!H:H,1,"false")=J50,"TRUE","FALSE") -> TRUE | M50: Comments describing additional details about the deployment. | N50: Comments describing additional details about the deployment. | O50: =IF(M50=999,"",(" term_"&J50&": """&K50&"""")) -> term_deployment_comments: "Deployment Comments" | P50: =IF(M50="-","-",(" def_"&J50&": """&M50&"""")) -> def_deployment_comments: "Comments describing additional details about the deployment." | R50: FALSE | S50: TRUE | T50: TRUE | U50: xx | V50: \" target=\"_blank\" data-bs-toggle=\"tooltip\" data-bs-title=\" | W50: \"> | X50: <button type=\"button\" class=\"btn btn-bd-tip-info-hidden btn-sm position-relative\">.<span class=\"position-absolute top-0 start-100 translate-middle\">{{ icon_info }}</span></button></a> | Y50: =IF(M50<>"-",(" "&J50&"_ti"&": "&""""&"<a href=\"&""""&"09_glossary.html#"&J50&V50&K50&": "&M50&W50&""&X50&""""),"-") -> deployment_comments_ti: "<a href=\"09_glossary.html#deployment_comments\" target=\"_blank\" data-bs-toggle=\"tooltip\" data-bs-title=\"Deployment Comments: Comments describing additional details about the deployment.\"><button type=\"button\" class=\"btn btn-bd-tip-info-hidden btn-sm position-relative\">.<span class=\"position-absolute top-0 start-100 translate-middle\">{{ icon_info }}</span></button></a>"
B51: 40 | C51: field | D51: - | E51: **Deployment Crew** | F51: upper | G51: surv_guide_meta | H51: cam_visit_deploy | I51: deployment_crew | J51: =IF(D51<>"-",I51&"_"&D51,I51) -> deployment_crew | K51: Deployment Crew | L51: =IF(VLOOKUP(J51,find_replace!H:H,1,"false")=J51,"TRUE","FALSE") -> TRUE | M51: The first and last names of the individuals who collected data during the deployment visit. | N51: The first and last names of the individuals who collected data during the deployment visit. | O51: =IF(M51=999,"",(" term_"&J51&": """&K51&"""")) -> term_deployment_crew: "Deployment Crew" | P51: =IF(M51="-","-",(" def_"&J51&": """&M51&"""")) -> def_deployment_crew: "The first and last names of the individuals who collected data during the deployment visit." | R51: TRUE | S51: TRUE | T51: TRUE | U51: xx | V51: \" target=\"_blank\" data-bs-toggle=\"tooltip\" data-bs-title=\" | W51: \"> | X51: <button type=\"button\" class=\"btn btn-bd-tip-info-hidden btn-sm position-relative\">.<span class=\"position-absolute top-0 start-100 translate-middle\">{{ icon_info }}</span></button></a> | Y51: =IF(M51<>"-",(" "&J51&"_ti"&": "&""""&"<a href=\"&""""&"09_glossary.html#"&J51&V51&K51&": "&M51&W51&""&X51&""""),"-") -> deployment_crew_ti: "<a href=\"09_glossary.html#deployment_crew\" target=\"_blank\" data-bs-toggle=\"tooltip\" data-bs-title=\"Deployment Crew: The first and last names of the individuals who collected data during the deployment visit.\"><button type=\"button\" class=\"btn btn-bd-tip-info-hidden btn-sm position-relative\">.<span class=\"position-absolute top-0 start-100 translate-middle\">{{ icon_info }}</span></button></a>"
B52: 41 | C52: field | D52: - | E52: **Deployment End Date Time (DD-MMM-YYYY HH:MM:SS)** | F52: upper | G52: surv_guide_meta | H52: cam_visit_deploy | I52: deployment_end_date_time | J52: =IF(D52<>"-",I52&"_"&D52,I52) -> deployment_end_date_time | K52: Deployment End Date Time (DD-MMM-YYYY HH:MM:SS) | L52: =IF(VLOOKUP(J52,find_replace!H:H,1,"false")=J52,"TRUE","FALSE") -> TRUE | M52: The date and time that the data was retrieved for a specific deployment (e.g., 27-Jan-2019 23:00:00). The Deployment End Date Time may not coincide with when the last image or video was collected (i.e., the Image Set End Date Time). Recording this field allows users to account for deployments where no images were captured and to confirm the last date and time that the camera was active. | N52: The date and time that the data was retrieved for a specific deployment (e.g., 27-Jan-2019 23:00:00). The Deployment End Date Time may not coincide with when the last image or video was collected (i.e., the Image Set End Date Time). Recording this field allows users to account for deployments where no images were captured and to confirm the last date and time that the camera was active. | O52: =IF(M52=999,"",(" term_"&J52&": """&K52&"""")) -> term_deployment_end_date_time: "Deployment End Date Time (DD-MMM-YYYY HH:MM:SS)" | P52: =IF(M52="-","-",(" def_"&J52&": """&M52&"""")) -> def_deployment_end_date_time: "The date and time that the data was retrieved for a specific deployment (e.g., 27-Jan-2019 23:00:00). The Deployment End Date Time may not coincide with when the last image or video was collected (i.e., the Image Set End Date Time). Recording this field allows users to account for deployments where no images were captured and to confirm the last date and time that the camera was active." | R52: TRUE | S52: TRUE | T52: TRUE | U52: xx | V52: \" target=\"_blank\" data-bs-toggle=\"tooltip\" data-bs-title=\" | W52: \"> | X52: <button type=\"button\" class=\"btn btn-bd-tip-info-hidden btn-sm position-relative\">.<span class=\"position-absolute top-0 start-100 translate-middle\">{{ icon_info }}</span></button></a> | Y52: =IF(M52<>"-",(" "&J52&"_ti"&": "&""""&"<a href=\"&""""&"09_glossary.html#"&J52&V52&K52&": "&M52&W52&""&X52&""""),"-") -> deployment_end_date_time_ti: "<a href=\"09_glossary.html#deployment_end_date_time\" target=\"_blank\" data-bs-toggle=\"tooltip\" data-bs-title=\"Deployment End Date Time (DD-MMM-YYYY HH:MM:SS): The date and time that the data was retrieved for a specific deployment (e.g., 27-Jan-2019 23:00:00). The Deployment End Date Time may not coincide with when the last image or video was collected (i.e., the Image Set End Date Time). Recording this field allows users to account for deployments where no images were captured and to confirm the last date and time that the camera was active.\"><button type=\"button\" class=\"btn btn-bd-tip-info-hidden btn-sm position-relative\">.<span class=\"position-absolute top-0 start-100 translate-middle\">{{ icon_info }}</span></button></a>"
B53: 42 | C53: field | D53: - | E53: **\*Deployment Image Count** | F53: upper | G53: surv_guide_meta | H53: cam_visit_deploy | I53: deployment_img_count | J53: =IF(D53<>"-",I53&"_"&D53,I53) -> deployment_img_count | K53: Deployment Image Count | L53: =IF(VLOOKUP(J53,find_replace!H:H,1,"false")=J53,"TRUE","FALSE") -> TRUE | M53: The total number of images collected during the deployment, including false triggers (i.e., empty images with no wildlife or human present species) and those triggered by a time-lapse setting (if applicable). | N53: The total number of images collected during the deployment, including false triggers (i.e., empty images with no wildlife or human present species) and those triggered by a time-lapse setting (if applicable). | O53: =IF(M53=999,"",(" term_"&J53&": """&K53&"""")) -> term_deployment_img_count: "Deployment Image Count" | P53: =IF(M53="-","-",(" def_"&J53&": """&M53&"""")) -> def_deployment_img_count: "The total number of images collected during the deployment, including false triggers (i.e., empty images with no wildlife or human present species) and those triggered by a time-lapse setting (if applicable)." | R53: FALSE | S53: TRUE | T53: FALSE | U53: xx | V53: \" target=\"_blank\" data-bs-toggle=\"tooltip\" data-bs-title=\" | W53: \"> | X53: <button type=\"button\" class=\"btn btn-bd-tip-info-hidden btn-sm position-relative\">.<span class=\"position-absolute top-0 start-100 translate-middle\">{{ icon_info }}</span></button></a> | Y53: =IF(M53<>"-",(" "&J53&"_ti"&": "&""""&"<a href=\"&""""&"09_glossary.html#"&J53&V53&K53&": "&M53&W53&""&X53&""""),"-") -> deployment_img_count_ti: "<a href=\"09_glossary.html#deployment_img_count\" target=\"_blank\" data-bs-toggle=\"tooltip\" data-bs-title=\"Deployment Image Count: The total number of images collected during the deployment, including false triggers (i.e., empty images with no wildlife or human present species) and those triggered by a time-lapse setting (if applicable).\"><button type=\"button\" class=\"btn btn-bd-tip-info-hidden btn-sm position-relative\">.<span class=\"position-absolute top-0 start-100 translate-middle\">{{ icon_info }}</span></button></a>"
B54: 43 | C54: term | D54: - | E54: Deployment metadata | G54: surv_guide_meta | H54: cam_visit_deploy | I54: deployment_metadata | J54: =IF(D54<>"-",I54&"_"&D54,I54) -> deployment_metadata | K54: Deployment metadata | L54: =IF(VLOOKUP(J54,find_replace!H:H,1,"false")=J54,"TRUE","FALSE") -> TRUE | M54: Metadata that is collected each time a camera is deployed. Each deployment event should have its own Camera Deployment Field Datasheet. The relevant metadata fields that should be collected differ when a camera is deployed vs. serviced or retrieved.<br><br>Refer to Appendix A - Table A5 and Camera Deployment Field Datasheet. | N54: Metadata that is collected each time a camera is deployed. Each deployment event should have its own Camera Deployment Field Datasheet. The relevant metadata fields that should be collected differ when a camera is deployed vs. serviced or retrieved.<br><br>Refer to Appendix A - Table A5 and Camera Deployment Field Datasheet. | O54: =IF(M54=999,"",(" term_"&J54&": """&K54&"""")) -> term_deployment_metadata: "Deployment metadata" | P54: =IF(M54="-","-",(" def_"&J54&": """&M54&"""")) -> def_deployment_metadata: "Metadata that is collected each time a camera is deployed. Each deployment event should have its own Camera Deployment Field Datasheet. The relevant metadata fields that should be collected differ when a camera is deployed vs. serviced or retrieved.<br><br>Refer to Appendix A - Table A5 and Camera Deployment Field Datasheet." | R54: NULL | S54: TRUE | T54: TRUE | U54: xx | V54: \" target=\"_blank\" data-bs-toggle=\"tooltip\" data-bs-title=\" | W54: \"> | X54: <button type=\"button\" class=\"btn btn-bd-tip-info-hidden btn-sm position-relative\">.<span class=\"position-absolute top-0 start-100 translate-middle\">{{ icon_info }}</span></button></a> | Y54: =IF(M54<>"-",(" "&J54&"_ti"&": "&""""&"<a href=\"&""""&"09_glossary.html#"&J54&V54&K54&": "&M54&W54&""&X54&""""),"-") -> deployment_metadata_ti: "<a href=\"09_glossary.html#deployment_metadata\" target=\"_blank\" data-bs-toggle=\"tooltip\" data-bs-title=\"Deployment metadata: Metadata that is collected each time a camera is deployed. Each deployment event should have its own Camera Deployment Field Datasheet. The relevant metadata fields that should be collected differ when a camera is deployed vs. serviced or retrieved.<br><br>Refer to Appendix A - Table A5 and Camera Deployment Field Datasheet.\"><button type=\"button\" class=\"btn btn-bd-tip-info-hidden btn-sm position-relative\">.<span class=\"position-absolute top-0 start-100 translate-middle\">{{ icon_info }}</span></button></a>"
B55: 44 | C55: field | D55: - | E55: **Deployment Name** | F55: upper | G55: surv_guide_meta | H55: cam_visit_deploy | I55: deployment_name | J55: =IF(D55<>"-",I55&"_"&D55,I55) -> deployment_name | K55: Deployment Name | L55: =IF(VLOOKUP(J55,find_replace!H:H,1,"false")=J55,"TRUE","FALSE") -> TRUE | M55: A unique alphanumeric identifier for a unique camera deployed during a specific [survey](#survey) period (ideally recorded as: 'Camera Location Name'_'Deployment Start Date' (or …_'Deployment End Date') (e.g., 'bh1_17-Jul-2018' or 'bh1_17-Jul-2018_21-Jan-2019'). <br> <br> Alternative naming conventions may be used, but the goal should be to minimize duplicate Image Names. | N55: A unique alphanumeric identifier for a unique camera deployed during a specific survey period (ideally recorded as: 'Camera Location Name'_'Deployment Start Date' (or …_'Deployment End Date') (e.g., 'bh1_17-Jul-2018' or 'bh1_17-Jul-2018_21-Jan-2019'). <br> <br> Alternative naming conventions may be used, but the goal should be to minimize duplicate Image Names. | O55: =IF(M55=999,"",(" term_"&J55&": """&K55&"""")) -> term_deployment_name: "Deployment Name" | P55: =IF(M55="-","-",(" def_"&J55&": """&M55&"""")) -> def_deployment_name: "A unique alphanumeric identifier for a unique camera deployed during a specific [survey](#survey) period (ideally recorded as: 'Camera Location Name'_'Deployment Start Date' (or …_'Deployment End Date') (e.g., 'bh1_17-Jul-2018' or 'bh1_17-Jul-2018_21-Jan-2019'). <br> <br> Alternative naming conventions may be used, but the goal should be to minimize duplicate Image Names." | R55: TRUE | S55: TRUE | T55: TRUE | U55: xx | V55: \" target=\"_blank\" data-bs-toggle=\"tooltip\" data-bs-title=\" | W55: \"> | X55: <button type=\"button\" class=\"btn btn-bd-tip-info-hidden btn-sm position-relative\">.<span class=\"position-absolute top-0 start-100 translate-middle\">{{ icon_info }}</span></button></a> | Y55: =IF(M55<>"-",(" "&J55&"_ti"&": "&""""&"<a href=\"&""""&"09_glossary.html#"&J55&V55&K55&": "&M55&W55&""&X55&""""),"-") -> deployment_name_ti: "<a href=\"09_glossary.html#deployment_name\" target=\"_blank\" data-bs-toggle=\"tooltip\" data-bs-title=\"Deployment Name: A unique alphanumeric identifier for a unique camera deployed during a specific [survey](#survey) period (ideally recorded as: 'Camera Location Name'_'Deployment Start Date' (or …_'Deployment End Date') (e.g., 'bh1_17-Jul-2018' or 'bh1_17-Jul-2018_21-Jan-2019'). <br> <br> Alternative naming conventions may be used, but the goal should be to minimize duplicate Image Names.\"><button type=\"button\" class=\"btn btn-bd-tip-info-hidden btn-sm position-relative\">.<span class=\"position-absolute top-0 start-100 translate-middle\">{{ icon_info }}</span></button></a>"
B56: 45 | C56: field | D56: - | E56: **Deployment Start Date Time (DD-MMM-YYYY HH:MM:SS)** | F56: upper | G56: surv_guide_meta | H56: cam_visit_deploy | I56: deployment_start_date_time | J56: =IF(D56<>"-",I56&"_"&D56,I56) -> deployment_start_date_time | K56: Deployment Start Date Time (DD-MMM-YYYY HH:MM:SS) | L56: =IF(VLOOKUP(J56,find_replace!H:H,1,"false")=J56,"TRUE","FALSE") -> TRUE | M56: The date and time that a camera was placed for a specific deployment (e.g., 17-Jan-2018 10:34:22). <br><br>The Deployment Start Date Time may not coincide with when the first image or video was collected (i.e., the Image Set Start Date Time). Recording this field allows users to account for deployments where no images were captured and to confirm the first date and time a camera was active. | N56: The date and time that a camera was placed for a specific deployment (e.g., 17-Jan-2018 10:34:22). <br><br>The Deployment Start Date Time may not coincide with when the first image or video was collected (i.e., the Image Set Start Date Time). Recording this field allows users to account for deployments where no images were captured and to confirm the first date and time a camera was active. | O56: =IF(M56=999,"",(" term_"&J56&": """&K56&"""")) -> term_deployment_start_date_time: "Deployment Start Date Time (DD-MMM-YYYY HH:MM:SS)" | P56: =IF(M56="-","-",(" def_"&J56&": """&M56&"""")) -> def_deployment_start_date_time: "The date and time that a camera was placed for a specific deployment (e.g., 17-Jan-2018 10:34:22). <br><br>The Deployment Start Date Time may not coincide with when the first image or video was collected (i.e., the Image Set Start Date Time). Recording this field allows users to account for deployments where no images were captured and to confirm the first date and time a camera was active." | R56: TRUE | S56: TRUE | T56: TRUE | U56: xx | V56: \" target=\"_blank\" data-bs-toggle=\"tooltip\" data-bs-title=\" | W56: \"> | X56: <button type=\"button\" class=\"btn btn-bd-tip-info-hidden btn-sm position-relative\">.<span class=\"position-absolute top-0 start-100 translate-middle\">{{ icon_info }}</span></button></a> | Y56: =IF(M56<>"-",(" "&J56&"_ti"&": "&""""&"<a href=\"&""""&"09_glossary.html#"&J56&V56&K56&": "&M56&W56&""&X56&""""),"-") -> deployment_start_date_time_ti: "<a href=\"09_glossary.html#deployment_start_date_time\" target=\"_blank\" data-bs-toggle=\"tooltip\" data-bs-title=\"Deployment Start Date Time (DD-MMM-YYYY HH:MM:SS): The date and time that a camera was placed for a specific deployment (e.g., 17-Jan-2018 10:34:22). <br><br>The Deployment Start Date Time may not coincide with when the first image or video was collected (i.e., the Image Set Start Date Time). Recording this field allows users to account for deployments where no images were captured and to confirm the first date and time a camera was active.\"><button type=\"button\" class=\"btn btn-bd-tip-info-hidden btn-sm position-relative\">.<span class=\"position-absolute top-0 start-100 translate-middle\">{{ icon_info }}</span></button></a>"
B57: 46 | C57: term | D57: - | E57: Deployment visit | G57: surv_guide_meta | H57: cam_visit_deploy | I57: deployment_visit | J57: =IF(D57<>"-",I57&"_"&D57,I57) -> deployment_visit | K57: Deployment visit | L57: =IF(VLOOKUP(J57,find_replace!H:H,1,"false")=J57,"TRUE","FALSE") -> TRUE | M57: When a crew has gone to a location to deploy a remote camera. | N57: When a crew has gone to a location to deploy a remote camera. | O57: =IF(M57=999,"",(" term_"&J57&": """&K57&"""")) -> term_deployment_visit: "Deployment visit" | P57: =IF(M57="-","-",(" def_"&J57&": """&M57&"""")) -> def_deployment_visit: "When a crew has gone to a location to deploy a remote camera." | R57: NULL | S57: TRUE | T57: TRUE | U57: xx | V57: \" target=\"_blank\" data-bs-toggle=\"tooltip\" data-bs-title=\" | W57: \"> | X57: <button type=\"button\" class=\"btn btn-bd-tip-info-hidden btn-sm position-relative\">.<span class=\"position-absolute top-0 start-100 translate-middle\">{{ icon_info }}</span></button></a> | Y57: =IF(M57<>"-",(" "&J57&"_ti"&": "&""""&"<a href=\"&""""&"09_glossary.html#"&J57&V57&K57&": "&M57&W57&""&X57&""""),"-") -> deployment_visit_ti: "<a href=\"09_glossary.html#deployment_visit\" target=\"_blank\" data-bs-toggle=\"tooltip\" data-bs-title=\"Deployment visit: When a crew has gone to a location to deploy a remote camera.\"><button type=\"button\" class=\"btn btn-bd-tip-info-hidden btn-sm position-relative\">.<span class=\"position-absolute top-0 start-100 translate-middle\">{{ icon_info }}</span></button></a>"
B58: 48 | C58: term | D58: - | E58: Detection distance | G58: surv_guide_meta | H58: detection_fov | I58: detection_distance | J58: =IF(D58<>"-",I58&"_"&D58,I58) -> detection_distance | K58: Detection distance | L58: =IF(VLOOKUP(J58,find_replace!H:H,1,"false")=J58,"TRUE","FALSE") -> TRUE | M58: The maximum distance that a sensor can detect a target' (Wearn and Glover-Kapfer, 2017). | N58: The maximum distance that a sensor can detect a target' (Wearn and Glover-Kapfer, 2017). | O58: =IF(M58=999,"",(" term_"&J58&": """&K58&"""")) -> term_detection_distance: "Detection distance" | P58: =IF(M58="-","-",(" def_"&J58&": """&M58&"""")) -> def_detection_distance: "The maximum distance that a sensor can detect a target' (Wearn and Glover-Kapfer, 2017)." | R58: NULL | S58: FALSE | T58: TRUE | U58: xx | V58: \" target=\"_blank\" data-bs-toggle=\"tooltip\" data-bs-title=\" | W58: \"> | X58: <button type=\"button\" class=\"btn btn-bd-tip-info-hidden btn-sm position-relative\">.<span class=\"position-absolute top-0 start-100 translate-middle\">{{ icon_info }}</span></button></a> | Y58: =IF(M58<>"-",(" "&J58&"_ti"&": "&""""&"<a href=\"&""""&"09_glossary.html#"&J58&V58&K58&": "&M58&W58&""&X58&""""),"-") -> detection_distance_ti: "<a href=\"09_glossary.html#detection_distance\" target=\"_blank\" data-bs-toggle=\"tooltip\" data-bs-title=\"Detection distance: The maximum distance that a sensor can detect a target' (Wearn and Glover-Kapfer, 2017).\"><button type=\"button\" class=\"btn btn-bd-tip-info-hidden btn-sm position-relative\">.<span class=\"position-absolute top-0 start-100 translate-middle\">{{ icon_info }}</span></button></a>"
B59: 47 | C59: term | D59: - | E59: Detection 'event' | G59: surv_guide_meta | H59: detection_fov | I59: detection_event | J59: =IF(D59<>"-",I59&"_"&D59,I59) -> detection_event | K59: Detection 'event' | L59: =IF(VLOOKUP(J59,find_replace!H:H,1,"false")=J59,"TRUE","FALSE") -> TRUE | M59: A group of images or video clips that are considered independent from other images or video clips based on a certain time threshold (or 'inter-detection interval'). For example, 30 minutes (O’Brien et al., 2003; Gerber et al., 2010; Kitamura et al., 2010; Samejima et al., 2012) or 1 hour (e.g., Tobler et al., 2008; Rovero & Marshall, 2009). | N59: A group of images or video clips that are considered independent from other images or video clips based on a certain time threshold (or 'inter-detection interval'). For example, 30 minutes (O’Brien et al., 2003; Gerber et al., 2010; Kitamura et al., 2010; Samejima et al., 2012) or 1 hour (e.g., Tobler et al., 2008; Rovero & Marshall, 2009). | O59: =IF(M59=999,"",(" term_"&J59&": """&K59&"""")) -> term_detection_event: "Detection 'event'" | P59: =IF(M59="-","-",(" def_"&J59&": """&M59&"""")) -> def_detection_event: "A group of images or video clips that are considered independent from other images or video clips based on a certain time threshold (or 'inter-detection interval'). For example, 30 minutes (O’Brien et al., 2003; Gerber et al., 2010; Kitamura et al., 2010; Samejima et al., 2012) or 1 hour (e.g., Tobler et al., 2008; Rovero & Marshall, 2009)." | R59: NULL | S59: TRUE | T59: TRUE | U59: xx | V59: \" target=\"_blank\" data-bs-toggle=\"tooltip\" data-bs-title=\" | W59: \"> | X59: <button type=\"button\" class=\"btn btn-bd-tip-info-hidden btn-sm position-relative\">.<span class=\"position-absolute top-0 start-100 translate-middle\">{{ icon_info }}</span></button></a> | Y59: =IF(M59<>"-",(" "&J59&"_ti"&": "&""""&"<a href=\"&""""&"09_glossary.html#"&J59&V59&K59&": "&M59&W59&""&X59&""""),"-") -> detection_event_ti: "<a href=\"09_glossary.html#detection_event\" target=\"_blank\" data-bs-toggle=\"tooltip\" data-bs-title=\"Detection 'event': A group of images or video clips that are considered independent from other images or video clips based on a certain time threshold (or 'inter-detection interval'). For example, 30 minutes (O’Brien et al., 2003; Gerber et al., 2010; Kitamura et al., 2010; Samejima et al., 2012) or 1 hour (e.g., Tobler et al., 2008; Rovero & Marshall, 2009).\"><button type=\"button\" class=\"btn btn-bd-tip-info-hidden btn-sm position-relative\">.<span class=\"position-absolute top-0 start-100 translate-middle\">{{ icon_info }}</span></button></a>"
B60: 49 | C60: term | D60: - | E60: Detection probability (aka detectability) | G60: surv_guide_meta | H60: detection_fov | I60: detection_probability | J60: =IF(D60<>"-",I60&"_"&D60,I60) -> detection_probability | K60: Detection probability (aka detectability) | L60: =IF(VLOOKUP(J60,find_replace!H:H,1,"false")=J60,"TRUE","FALSE") -> TRUE | M60: The probability (likelihood) that an individual of the population of interest is included in the count at time or location *i*. | N60: The probability (likelihood) that an individual of the population of interest is included in the count at time or location *i*. | O60: =IF(M60=999,"",(" term_"&J60&": """&K60&"""")) -> term_detection_probability: "Detection probability (aka detectability)" | P60: =IF(M60="-","-",(" def_"&J60&": """&M60&"""")) -> def_detection_probability: "The probability (likelihood) that an individual of the population of interest is included in the count at time or location *i*." | R60: NULL | S60: FALSE | T60: TRUE | U60: xx | V60: \" target=\"_blank\" data-bs-toggle=\"tooltip\" data-bs-title=\" | W60: \"> | X60: <button type=\"button\" class=\"btn btn-bd-tip-info-hidden btn-sm position-relative\">.<span class=\"position-absolute top-0 start-100 translate-middle\">{{ icon_info }}</span></button></a> | Y60: =IF(M60<>"-",(" "&J60&"_ti"&": "&""""&"<a href=\"&""""&"09_glossary.html#"&J60&V60&K60&": "&M60&W60&""&X60&""""),"-") -> detection_probability_ti: "<a href=\"09_glossary.html#detection_probability\" target=\"_blank\" data-bs-toggle=\"tooltip\" data-bs-title=\"Detection probability (aka detectability): The probability (likelihood) that an individual of the population of interest is included in the count at time or location *i*.\"><button type=\"button\" class=\"btn btn-bd-tip-info-hidden btn-sm position-relative\">.<span class=\"position-absolute top-0 start-100 translate-middle\">{{ icon_info }}</span></button></a>"
B61: 50 | C61: term | D61: - | E61: Detection rate | G61: surv_guide_meta | H61: detection_fov | I61: detection_rate | J61: =IF(D61<>"-",I61&"_"&D61,I61) -> detection_rate | K61: Detection rate | L61: =IF(VLOOKUP(J61,find_replace!H:H,1,"false")=J61,"TRUE","FALSE") -> TRUE | M61: The frequency of independent detections within a specified time period. | N61: The frequency of independent detections within a specified time period. | O61: =IF(M61=999,"",(" term_"&J61&": """&K61&"""")) -> term_detection_rate: "Detection rate" | P61: =IF(M61="-","-",(" def_"&J61&": """&M61&"""")) -> def_detection_rate: "The frequency of independent detections within a specified time period." | R61: NULL | S61: FALSE | T61: TRUE | U61: xx | V61: \" target=\"_blank\" data-bs-toggle=\"tooltip\" data-bs-title=\" | W61: \"> | X61: <button type=\"button\" class=\"btn btn-bd-tip-info-hidden btn-sm position-relative\">.<span class=\"position-absolute top-0 start-100 translate-middle\">{{ icon_info }}</span></button></a> | Y61: =IF(M61<>"-",(" "&J61&"_ti"&": "&""""&"<a href=\"&""""&"09_glossary.html#"&J61&V61&K61&": "&M61&W61&""&X61&""""),"-") -> detection_rate_ti: "<a href=\"09_glossary.html#detection_rate\" target=\"_blank\" data-bs-toggle=\"tooltip\" data-bs-title=\"Detection rate: The frequency of independent detections within a specified time period.\"><button type=\"button\" class=\"btn btn-bd-tip-info-hidden btn-sm position-relative\">.<span class=\"position-absolute top-0 start-100 translate-middle\">{{ icon_info }}</span></button></a>"
B62: 51 | C62: term | D62: - | E62: Detection zone | G62: surv_guide_meta | H62: detection_fov | I62: detection_zone | J62: =IF(D62<>"-",I62&"_"&D62,I62) -> detection_zone | K62: Detection zone | L62: =IF(VLOOKUP(J62,find_replace!H:H,1,"false")=J62,"TRUE","FALSE") -> TRUE | M62: The area (conical in shape) in which a remote camera can detect the heat signature and motion of an object (Rovero & Zimmermann, 2016) (Figure 5). | N62: The area (conical in shape) in which a remote camera can detect the heat signature and motion of an object (Rovero & Zimmermann, 2016) (Figure 5). | O62: =IF(M62=999,"",(" term_"&J62&": """&K62&"""")) -> term_detection_zone: "Detection zone" | P62: =IF(M62="-","-",(" def_"&J62&": """&M62&"""")) -> def_detection_zone: "The area (conical in shape) in which a remote camera can detect the heat signature and motion of an object (Rovero & Zimmermann, 2016) (Figure 5)." | R62: NULL | S62: TRUE | T62: TRUE | U62: xx | V62: \" target=\"_blank\" data-bs-toggle=\"tooltip\" data-bs-title=\" | W62: \"> | X62: <button type=\"button\" class=\"btn btn-bd-tip-info-hidden btn-sm position-relative\">.<span class=\"position-absolute top-0 start-100 translate-middle\">{{ icon_info }}</span></button></a> | Y62: =IF(M62<>"-",(" "&J62&"_ti"&": "&""""&"<a href=\"&""""&"09_glossary.html#"&J62&V62&K62&": "&M62&W62&""&X62&""""),"-") -> detection_zone_ti: "<a href=\"09_glossary.html#detection_zone\" target=\"_blank\" data-bs-toggle=\"tooltip\" data-bs-title=\"Detection zone: The area (conical in shape) in which a remote camera can detect the heat signature and motion of an object (Rovero & Zimmermann, 2016) (Figure 5).\"><button type=\"button\" class=\"btn btn-bd-tip-info-hidden btn-sm position-relative\">.<span class=\"position-absolute top-0 start-100 translate-middle\">{{ icon_info }}</span></button></a>"
B63: 52 | C63: term | D63: - | E63: Distance sampling (DS) model (Howe et al., 2017) | F63: upper | G63: surv_guide_meta | H63: approach | I63: mod_ds | J63: =IF(D63<>"-",I63&"_"&D63,I63) -> mod_ds | K63: Distance sampling (DS) model (Howe et al., 2017) | L63: =IF(VLOOKUP(J63,find_replace!H:H,1,"false")=J63,"TRUE","FALSE") -> TRUE | M63: A method to estimate abundance by using distances at which animals are detected (from [survey](#survey) lines or points) to model abundance as a function of decreasing detection probability with animal distance from the camera (using a decay function) (Cappelle et al., 2021; Howe et al., 2017). | N63: A method to estimate abundance by using distances at which animals are detected (from survey lines or points) to model abundance as a function of decreasing detection probability with animal distance from the camera (using a decay function) (Cappelle et al., 2021; Howe et al., 2017). | O63: =IF(M63=999,"",(" term_"&J63&": """&K63&"""")) -> term_mod_ds: "Distance sampling (DS) model (Howe et al., 2017)" | P63: =IF(M63="-","-",(" def_"&J63&": """&M63&"""")) -> def_mod_ds: "A method to estimate abundance by using distances at which animals are detected (from [survey](#survey) lines or points) to model abundance as a function of decreasing detection probability with animal distance from the camera (using a decay function) (Cappelle et al., 2021; Howe et al., 2017)." | R63: NULL | S63: FALSE | T63: TRUE | U63: xx | V63: \" target=\"_blank\" data-bs-toggle=\"tooltip\" data-bs-title=\" | W63: \"> | X63: <button type=\"button\" class=\"btn btn-bd-tip-info-hidden btn-sm position-relative\">.<span class=\"position-absolute top-0 start-100 translate-middle\">{{ icon_info }}</span></button></a> | Y63: =IF(M63<>"-",(" "&J63&"_ti"&": "&""""&"<a href=\"&""""&"09_glossary.html#"&J63&V63&K63&": "&M63&W63&""&X63&""""),"-") -> mod_ds_ti: "<a href=\"09_glossary.html#mod_ds\" target=\"_blank\" data-bs-toggle=\"tooltip\" data-bs-title=\"Distance sampling (DS) model (Howe et al., 2017): A method to estimate abundance by using distances at which animals are detected (from [survey](#survey) lines or points) to model abundance as a function of decreasing detection probability with animal distance from the camera (using a decay function) (Cappelle et al., 2021; Howe et al., 2017).\"><button type=\"button\" class=\"btn btn-bd-tip-info-hidden btn-sm position-relative\">.<span class=\"position-absolute top-0 start-100 translate-middle\">{{ icon_info }}</span></button></a>"
B64: 53 | C64: field | D64: - | E64: **Easting Camera Location** | F64: upper | G64: surv_guide_meta | H64: cam_loc_station | I64: easting_cam_location | J64: =IF(D64<>"-",I64&"_"&D64,I64) -> easting_cam_location | K64: Easting Camera Location | L64: =IF(VLOOKUP(J64,find_replace!H:H,1,"false")=J64,"TRUE","FALSE") -> TRUE | M64: The easting UTM coordinate of the camera location (e.g., '337875'). Record using the NAD83 datum. Leave blank if recording the Longitude instead. | N64: The easting UTM coordinate of the camera location (e.g., '337875'). Record using the NAD83 datum. Leave blank if recording the Longitude instead. | O64: =IF(M64=999,"",(" term_"&J64&": """&K64&"""")) -> term_easting_cam_location: "Easting Camera Location" | P64: =IF(M64="-","-",(" def_"&J64&": """&M64&"""")) -> def_easting_cam_location: "The easting UTM coordinate of the camera location (e.g., '337875'). Record using the NAD83 datum. Leave blank if recording the Longitude instead." | Q64: TRUE | R64: TRUE | S64: TRUE | T64: TRUE | U64: xx | V64: \" target=\"_blank\" data-bs-toggle=\"tooltip\" data-bs-title=\" | W64: \"> | X64: <button type=\"button\" class=\"btn btn-bd-tip-info-hidden btn-sm position-relative\">.<span class=\"position-absolute top-0 start-100 translate-middle\">{{ icon_info }}</span></button></a> | Y64: =IF(M64<>"-",(" "&J64&"_ti"&": "&""""&"<a href=\"&""""&"09_glossary.html#"&J64&V64&K64&": "&M64&W64&""&X64&""""),"-") -> easting_cam_location_ti: "<a href=\"09_glossary.html#easting_cam_location\" target=\"_blank\" data-bs-toggle=\"tooltip\" data-bs-title=\"Easting Camera Location: The easting UTM coordinate of the camera location (e.g., '337875'). Record using the NAD83 datum. Leave blank if recording the Longitude instead.\"><button type=\"button\" class=\"btn btn-bd-tip-info-hidden btn-sm position-relative\">.<span class=\"position-absolute top-0 start-100 translate-middle\">{{ icon_info }}</span></button></a>"
B65: 54 | C65: term | D65: - | E65: Effective detection distance | G65: surv_guide_meta | H65: detection_fov | I65: effective_detection_distance | J65: =IF(D65<>"-",I65&"_"&D65,I65) -> effective_detection_distance | K65: Effective detection distance | L65: =IF(VLOOKUP(J65,find_replace!H:H,1,"false")=J65,"TRUE","FALSE") -> TRUE | M65: The distance from a camera that would give the same number of detections if all animals up to that distance are perfectly detected, and no animals that are farther away are detected; Buckland, 1987, Becker et al., 2022). | N65: The distance from a camera that would give the same number of detections if all animals up to that distance are perfectly detected, and no animals that are farther away are detected; Buckland, 1987, Becker et al., 2022). | O65: =IF(M65=999,"",(" term_"&J65&": """&K65&"""")) -> term_effective_detection_distance: "Effective detection distance" | P65: =IF(M65="-","-",(" def_"&J65&": """&M65&"""")) -> def_effective_detection_distance: "The distance from a camera that would give the same number of detections if all animals up to that distance are perfectly detected, and no animals that are farther away are detected; Buckland, 1987, Becker et al., 2022)." | R65: NULL | S65: FALSE | T65: TRUE | U65: xx | V65: \" target=\"_blank\" data-bs-toggle=\"tooltip\" data-bs-title=\" | W65: \"> | X65: <button type=\"button\" class=\"btn btn-bd-tip-info-hidden btn-sm position-relative\">.<span class=\"position-absolute top-0 start-100 translate-middle\">{{ icon_info }}</span></button></a> | Y65: =IF(M65<>"-",(" "&J65&"_ti"&": "&""""&"<a href=\"&""""&"09_glossary.html#"&J65&V65&K65&": "&M65&W65&""&X65&""""),"-") -> effective_detection_distance_ti: "<a href=\"09_glossary.html#effective_detection_distance\" target=\"_blank\" data-bs-toggle=\"tooltip\" data-bs-title=\"Effective detection distance: The distance from a camera that would give the same number of detections if all animals up to that distance are perfectly detected, and no animals that are farther away are detected; Buckland, 1987, Becker et al., 2022).\"><button type=\"button\" class=\"btn btn-bd-tip-info-hidden btn-sm position-relative\">.<span class=\"position-absolute top-0 start-100 translate-middle\">{{ icon_info }}</span></button></a>"
C66: term | D66: - | G66: other | I66: mod_divers_rich_rich_est | J66: =IF(D66<>"-",I66&"_"&D66,I66) -> mod_divers_rich_rich_est | K66: Estimated species richness | L66: =IF(VLOOKUP(J66,find_replace!H:H,1,"false")=J66,"TRUE","FALSE") -> TRUE | M66: When the 'sum of the number of species seen' is adjusted based on corrections for '{{ tl_imperfect_detection }}' (i.e. the fact that some species in a given sample may have been missed)' ({{ rtxt_wearn_gloverkapfer_2017 }}) | N66: when the 'sum of the number of species seen' is adjusted based on corrections for 'imperfect detection' (i.e. the fact that some species in a given sample may have been missed)' (Wearn & Glover-Kapfer, 2017) | O66: =IF(M66=999,"",(" term_"&J66&": """&K66&"""")) -> term_mod_divers_rich_rich_est: "Estimated species richness" | P66: =IF(M66="-","-",(" def_"&J66&": """&M66&"""")) -> def_mod_divers_rich_rich_est: "When the 'sum of the number of species seen' is adjusted based on corrections for '{{ tl_imperfect_detection }}' (i.e. the fact that some species in a given sample may have been missed)' ({{ rtxt_wearn_gloverkapfer_2017 }})" | U66: xx | V66: \" target=\"_blank\" data-bs-toggle=\"tooltip\" data-bs-title=\" | W66: \"> | X66: <button type=\"button\" class=\"btn btn-bd-tip-info-hidden btn-sm position-relative\">.<span class=\"position-absolute top-0 start-100 translate-middle\">{{ icon_info }}</span></button></a> | Y66: =IF(M66<>"-",(" "&J66&"_ti"&": "&""""&"<a href=\"&""""&"09_glossary.html#"&J66&V66&K66&": "&M66&W66&""&X66&""""),"-") -> mod_divers_rich_rich_est_ti: "<a href=\"09_glossary.html#mod_divers_rich_rich_est\" target=\"_blank\" data-bs-toggle=\"tooltip\" data-bs-title=\"Estimated species richness: When the 'sum of the number of species seen' is adjusted based on corrections for '{{ tl_imperfect_detection }}' (i.e. the fact that some species in a given sample may have been missed)' ({{ rtxt_wearn_gloverkapfer_2017 }})\"><button type=\"button\" class=\"btn btn-bd-tip-info-hidden btn-sm position-relative\">.<span class=\"position-absolute top-0 start-100 translate-middle\">{{ icon_info }}</span></button></a>"
B67: 55 | C67: field | D67: - | E67: **Event Type** | F67: upper | G67: surv_guide_meta | H67: img_processing | I67: event_type | J67: =IF(D67<>"-",I67&"_"&D67,I67) -> event_type | K67: Event Type | L67: =IF(VLOOKUP(J67,find_replace!H:H,1,"false")=J67,"TRUE","FALSE") -> TRUE | M67: Whether detections were reported as an individual image captured by the camera ('Image'), a 'Sequence,' or 'Tag.' | N67: Whether detections were reported as an individual image captured by the camera ('Image'), a 'Sequence,' or 'Tag.' | O67: =IF(M67=999,"",(" term_"&J67&": """&K67&"""")) -> term_event_type: "Event Type" | P67: =IF(M67="-","-",(" def_"&J67&": """&M67&"""")) -> def_event_type: "Whether detections were reported as an individual image captured by the camera ('Image'), a 'Sequence,' or 'Tag.'" | R67: TRUE | S67: TRUE | T67: FALSE | U67: xx | V67: \" target=\"_blank\" data-bs-toggle=\"tooltip\" data-bs-title=\" | W67: \"> | X67: <button type=\"button\" class=\"btn btn-bd-tip-info-hidden btn-sm position-relative\">.<span class=\"position-absolute top-0 start-100 translate-middle\">{{ icon_info }}</span></button></a> | Y67: =IF(M67<>"-",(" "&J67&"_ti"&": "&""""&"<a href=\"&""""&"09_glossary.html#"&J67&V67&K67&": "&M67&W67&""&X67&""""),"-") -> event_type_ti: "<a href=\"09_glossary.html#event_type\" target=\"_blank\" data-bs-toggle=\"tooltip\" data-bs-title=\"Event Type: Whether detections were reported as an individual image captured by the camera ('Image'), a 'Sequence,' or 'Tag.'\"><button type=\"button\" class=\"btn btn-bd-tip-info-hidden btn-sm position-relative\">.<span class=\"position-absolute top-0 start-100 translate-middle\">{{ icon_info }}</span></button></a>"
B68: 56 | C68: term | D68: - | E68: False trigger | G68: surv_guide_meta | H68: detection_fov | I68: false_trigger | J68: =IF(D68<>"-",I68&"_"&D68,I68) -> false_trigger | K68: False trigger | L68: =IF(VLOOKUP(J68,find_replace!H:H,1,"false")=J68,"TRUE","FALSE") -> TRUE | M68: Blank images (no wildlife or human present). These images commonly occur when a camera is triggered by vegetation blowing in the wind. | N68: Blank images (no wildlife or human present). These images commonly occur when a camera is triggered by vegetation blowing in the wind. | O68: =IF(M68=999,"",(" term_"&J68&": """&K68&"""")) -> term_false_trigger: "False trigger" | P68: =IF(M68="-","-",(" def_"&J68&": """&M68&"""")) -> def_false_trigger: "Blank images (no wildlife or human present). These images commonly occur when a camera is triggered by vegetation blowing in the wind." | R68: NULL | S68: TRUE | T68: TRUE | U68: xx | V68: \" target=\"_blank\" data-bs-toggle=\"tooltip\" data-bs-title=\" | W68: \"> | X68: <button type=\"button\" class=\"btn btn-bd-tip-info-hidden btn-sm position-relative\">.<span class=\"position-absolute top-0 start-100 translate-middle\">{{ icon_info }}</span></button></a> | Y68: =IF(M68<>"-",(" "&J68&"_ti"&": "&""""&"<a href=\"&""""&"09_glossary.html#"&J68&V68&K68&": "&M68&W68&""&X68&""""),"-") -> false_trigger_ti: "<a href=\"09_glossary.html#false_trigger\" target=\"_blank\" data-bs-toggle=\"tooltip\" data-bs-title=\"False trigger: Blank images (no wildlife or human present). These images commonly occur when a camera is triggered by vegetation blowing in the wind.\"><button type=\"button\" class=\"btn btn-bd-tip-info-hidden btn-sm position-relative\">.<span class=\"position-absolute top-0 start-100 translate-middle\">{{ icon_info }}</span></button></a>"
B69: 57 | C69: term | D69: - | E69: Field of View (FOV) | F69: upper | G69: surv_guide_meta | H69: detection_fov | I69: field_of_view | J69: =IF(D69<>"-",I69&"_"&D69,I69) -> field_of_view | K69: Field of View (FOV) | L69: =IF(VLOOKUP(J69,find_replace!H:H,1,"false")=J69,"TRUE","FALSE") -> TRUE | M69: The extent of a scene that is visible in an image; a large FOV is obtained by 'zooming out' from a scene, whilst 'zooming in' will result in a smaller FOV ({{ rtxt_wearn_gloverkapfer_2017 }}). | N69: The extent of a scene that is visible in an image; a large FOV is obtained by 'zooming out' from a scene, whilst 'zooming in' will result in a smaller FOV (Wearn & Glover-Kapfer, 2017). | O69: =IF(M69=999,"",(" term_"&J69&": """&K69&"""")) -> term_field_of_view: "Field of View (FOV)" | P69: =IF(M69="-","-",(" def_"&J69&": """&M69&"""")) -> def_field_of_view: "The extent of a scene that is visible in an image; a large FOV is obtained by 'zooming out' from a scene, whilst 'zooming in' will result in a smaller FOV ({{ rtxt_wearn_gloverkapfer_2017 }})." | R69: NULL | S69: TRUE | T69: TRUE | U69: xx | V69: \" target=\"_blank\" data-bs-toggle=\"tooltip\" data-bs-title=\" | W69: \"> | X69: <button type=\"button\" class=\"btn btn-bd-tip-info-hidden btn-sm position-relative\">.<span class=\"position-absolute top-0 start-100 translate-middle\">{{ icon_info }}</span></button></a> | Y69: =IF(M69<>"-",(" "&J69&"_ti"&": "&""""&"<a href=\"&""""&"09_glossary.html#"&J69&V69&K69&": "&M69&W69&""&X69&""""),"-") -> field_of_view_ti: "<a href=\"09_glossary.html#field_of_view\" target=\"_blank\" data-bs-toggle=\"tooltip\" data-bs-title=\"Field of View (FOV): The extent of a scene that is visible in an image; a large FOV is obtained by 'zooming out' from a scene, whilst 'zooming in' will result in a smaller FOV ({{ rtxt_wearn_gloverkapfer_2017 }}).\"><button type=\"button\" class=\"btn btn-bd-tip-info-hidden btn-sm position-relative\">.<span class=\"position-absolute top-0 start-100 translate-middle\">{{ icon_info }}</span></button></a>"
B70: 58 | C70: term | D70: - | E70: Flash output | G70: surv_guide_meta | H70: cam_visit_settings | I70: settings_flash_output | J70: =IF(D70<>"-",I70&"_"&D70,I70) -> settings_flash_output | K70: Flash output | L70: =IF(VLOOKUP(J70,find_replace!H:H,1,"false")=J70,"TRUE","FALSE") -> TRUE | M70: The camera setting that provides the level of intensity of the flash (if enabled). | N70: The camera setting that provides the level of intensity of the flash (if enabled). | O70: =IF(M70=999,"",(" term_"&J70&": """&K70&"""")) -> term_settings_flash_output: "Flash output" | P70: =IF(M70="-","-",(" def_"&J70&": """&M70&"""")) -> def_settings_flash_output: "The camera setting that provides the level of intensity of the flash (if enabled)." | R70: NULL | S70: TRUE | T70: TRUE | U70: xx | V70: \" target=\"_blank\" data-bs-toggle=\"tooltip\" data-bs-title=\" | W70: \"> | X70: <button type=\"button\" class=\"btn btn-bd-tip-info-hidden btn-sm position-relative\">.<span class=\"position-absolute top-0 start-100 translate-middle\">{{ icon_info }}</span></button></a> | Y70: =IF(M70<>"-",(" "&J70&"_ti"&": "&""""&"<a href=\"&""""&"09_glossary.html#"&J70&V70&K70&": "&M70&W70&""&X70&""""),"-") -> settings_flash_output_ti: "<a href=\"09_glossary.html#settings_flash_output\" target=\"_blank\" data-bs-toggle=\"tooltip\" data-bs-title=\"Flash output: The camera setting that provides the level of intensity of the flash (if enabled).\"><button type=\"button\" class=\"btn btn-bd-tip-info-hidden btn-sm position-relative\">.<span class=\"position-absolute top-0 start-100 translate-middle\">{{ icon_info }}</span></button></a>"
B71: 59 | C71: field | D71: - | E71: **FOV Target Feature** | F71: upper | G71: surv_guide_meta | H71: cam_visit_placement | I71: fov_target | J71: =IF(D71<>"-",I71&"_"&D71,I71) -> fov_target | K71: FOV Target Feature | L71: =IF(VLOOKUP(J71,find_replace!H:H,1,"false")=J71,"TRUE","FALSE") -> TRUE | M71: A specific man-made or natural feature at which the camera is aimed to maximize the detection of wildlife species or to measure the use of that feature. Record 'None' if a FOV Target Feature was not used and 'Unknown' if not known. If 'Other,' describe in the Camera Location Comments. | N71: A specific man-made or natural feature at which the camera is aimed to maximize the detection of wildlife species or to measure the use of that feature. Record 'None' if a FOV Target Feature was not used and 'Unknown' if not known. If 'Other,' describe in the Camera Location Comments. | O71: =IF(M71=999,"",(" term_"&J71&": """&K71&"""")) -> term_fov_target: "FOV Target Feature" | P71: =IF(M71="-","-",(" def_"&J71&": """&M71&"""")) -> def_fov_target: "A specific man-made or natural feature at which the camera is aimed to maximize the detection of wildlife species or to measure the use of that feature. Record 'None' if a FOV Target Feature was not used and 'Unknown' if not known. If 'Other,' describe in the Camera Location Comments." | Q71: TRUE | R71: TRUE | S71: TRUE | T71: TRUE | U71: xx | V71: \" target=\"_blank\" data-bs-toggle=\"tooltip\" data-bs-title=\" | W71: \"> | X71: <button type=\"button\" class=\"btn btn-bd-tip-info-hidden btn-sm position-relative\">.<span class=\"position-absolute top-0 start-100 translate-middle\">{{ icon_info }}</span></button></a> | Y71: =IF(M71<>"-",(" "&J71&"_ti"&": "&""""&"<a href=\"&""""&"09_glossary.html#"&J71&V71&K71&": "&M71&W71&""&X71&""""),"-") -> fov_target_ti: "<a href=\"09_glossary.html#fov_target\" target=\"_blank\" data-bs-toggle=\"tooltip\" data-bs-title=\"FOV Target Feature: A specific man-made or natural feature at which the camera is aimed to maximize the detection of wildlife species or to measure the use of that feature. Record 'None' if a FOV Target Feature was not used and 'Unknown' if not known. If 'Other,' describe in the Camera Location Comments.\"><button type=\"button\" class=\"btn btn-bd-tip-info-hidden btn-sm position-relative\">.<span class=\"position-absolute top-0 start-100 translate-middle\">{{ icon_info }}</span></button></a>"
B72: 60 | C72: field | D72: - | E72: **\*FOV Target Feature Distance (m)** | F72: upper | G72: surv_guide_meta | H72: cam_visit_placement | I72: fov_target_distance | J72: =IF(D72<>"-",I72&"_"&D72,I72) -> fov_target_distance | K72: FOV Target Feature Distance (m) | L72: =IF(VLOOKUP(J72,find_replace!H:H,1,"false")=J72,"TRUE","FALSE") -> TRUE | M72: The distance from the camera to the FOV Target Feature (in metres; to the nearest 0.5 m). Leave blank if not applicable. | N72: The distance from the camera to the FOV Target Feature (in metres; to the nearest 0.5 m). Leave blank if not applicable. | O72: =IF(M72=999,"",(" term_"&J72&": """&K72&"""")) -> term_fov_target_distance: "FOV Target Feature Distance (m)" | P72: =IF(M72="-","-",(" def_"&J72&": """&M72&"""")) -> def_fov_target_distance: "The distance from the camera to the FOV Target Feature (in metres; to the nearest 0.5 m). Leave blank if not applicable." | Q72: TRUE | R72: FALSE | S72: TRUE | T72: TRUE | U72: xx | V72: \" target=\"_blank\" data-bs-toggle=\"tooltip\" data-bs-title=\" | W72: \"> | X72: <button type=\"button\" class=\"btn btn-bd-tip-info-hidden btn-sm position-relative\">.<span class=\"position-absolute top-0 start-100 translate-middle\">{{ icon_info }}</span></button></a> | Y72: =IF(M72<>"-",(" "&J72&"_ti"&": "&""""&"<a href=\"&""""&"09_glossary.html#"&J72&V72&K72&": "&M72&W72&""&X72&""""),"-") -> fov_target_distance_ti: "<a href=\"09_glossary.html#fov_target_distance\" target=\"_blank\" data-bs-toggle=\"tooltip\" data-bs-title=\"FOV Target Feature Distance (m): The distance from the camera to the FOV Target Feature (in metres; to the nearest 0.5 m). Leave blank if not applicable.\"><button type=\"button\" class=\"btn btn-bd-tip-info-hidden btn-sm position-relative\">.<span class=\"position-absolute top-0 start-100 translate-middle\">{{ icon_info }}</span></button></a>"
A73: NEW | C73: term | D73: - | E73: Gamma richness (γ) | G73: surv_guide_meta | H73: objective_approach | I73: mod_divers_rich_gamma | J73: =IF(D73<>"-",I73&"_"&D73,I73) -> mod_divers_rich_gamma | K73: Gamma richness (γ) | L73: =IF(VLOOKUP(J73,find_replace!H:H,1,"false")=J73,"TRUE","FALSE") -> TRUE | M73: The number of species across a whole study area ({{ rtxt_wearn_gloverkapfer_2017 }}). | N73: The number of species across a whole study area (Wearn & Glover-Kapfer, 2017). | O73: =IF(M73=999,"",(" term_"&J73&": """&K73&"""")) -> term_mod_divers_rich_gamma: "Gamma richness (γ)" | P73: =IF(M73="-","-",(" def_"&J73&": """&M73&"""")) -> def_mod_divers_rich_gamma: "The number of species across a whole study area ({{ rtxt_wearn_gloverkapfer_2017 }})." | U73: xx | V73: \" target=\"_blank\" data-bs-toggle=\"tooltip\" data-bs-title=\" | W73: \"> | X73: <button type=\"button\" class=\"btn btn-bd-tip-info-hidden btn-sm position-relative\">.<span class=\"position-absolute top-0 start-100 translate-middle\">{{ icon_info }}</span></button></a> | Y73: =IF(M73<>"-",(" "&J73&"_ti"&": "&""""&"<a href=\"&""""&"09_glossary.html#"&J73&V73&K73&": "&M73&W73&""&X73&""""),"-") -> mod_divers_rich_gamma_ti: "<a href=\"09_glossary.html#mod_divers_rich_gamma\" target=\"_blank\" data-bs-toggle=\"tooltip\" data-bs-title=\"Gamma richness (γ): The number of species across a whole study area ({{ rtxt_wearn_gloverkapfer_2017 }}).\"><button type=\"button\" class=\"btn btn-bd-tip-info-hidden btn-sm position-relative\">.<span class=\"position-absolute top-0 start-100 translate-middle\">{{ icon_info }}</span></button></a>"
B74: 61 | C74: field | D74: - | E74: **GPS Unit Accuracy (m) ** | F74: upper | G74: surv_guide_meta | H74: cam_visit | I74: gps_unit_accuracy | J74: =IF(D74<>"-",I74&"_"&D74,I74) -> gps_unit_accuracy | K74: GPS Unit Accuracy (m) | L74: =IF(VLOOKUP(J74,find_replace!H:H,1,"false")=J74,"TRUE","FALSE") -> TRUE | M74: The margin of error of the GPS unit used to record spatial information (e.g., '5' [m]), such as the coordinates of the camera location. On most GPS units (e.g., 'Garmin') this information is provided on the unit’s satellite information page. | N74: The margin of error of the GPS unit used to record spatial information (e.g., '5' [m]), such as the coordinates of the camera location. On most GPS units (e.g., 'Garmin') this information is provided on the unit’s satellite information page. | O74: =IF(M74=999,"",(" term_"&J74&": """&K74&"""")) -> term_gps_unit_accuracy: "GPS Unit Accuracy (m) " | P74: =IF(M74="-","-",(" def_"&J74&": """&M74&"""")) -> def_gps_unit_accuracy: "The margin of error of the GPS unit used to record spatial information (e.g., '5' [m]), such as the coordinates of the camera location. On most GPS units (e.g., 'Garmin') this information is provided on the unit’s satellite information page. " | R74: TRUE | S74: TRUE | T74: TRUE | U74: xx | V74: \" target=\"_blank\" data-bs-toggle=\"tooltip\" data-bs-title=\" | W74: \"> | X74: <button type=\"button\" class=\"btn btn-bd-tip-info-hidden btn-sm position-relative\">.<span class=\"position-absolute top-0 start-100 translate-middle\">{{ icon_info }}</span></button></a> | Y74: =IF(M74<>"-",(" "&J74&"_ti"&": "&""""&"<a href=\"&""""&"09_glossary.html#"&J74&V74&K74&": "&M74&W74&""&X74&""""),"-") -> gps_unit_accuracy_ti: "<a href=\"09_glossary.html#gps_unit_accuracy\" target=\"_blank\" data-bs-toggle=\"tooltip\" data-bs-title=\"GPS Unit Accuracy (m) : The margin of error of the GPS unit used to record spatial information (e.g., '5' [m]), such as the coordinates of the camera location. On most GPS units (e.g., 'Garmin') this information is provided on the unit’s satellite information page. \"><button type=\"button\" class=\"btn btn-bd-tip-info-hidden btn-sm position-relative\">.<span class=\"position-absolute top-0 start-100 translate-middle\">{{ icon_info }}</span></button></a>"
C75: term | D75: - | G75: rc_tool | H75: term_hr_size | I75: hr | J75: =IF(D75<>"-",I75&"_"&D75,I75) -> hr | K75: Home range | L75: =IF(VLOOKUP(J75,find_replace!H:H,1,"false")=J75,"TRUE","FALSE") -> TRUE | M75: The area within which an animal normally lives and finds what it needs to survive and reproduce. | N75: the area within which an animal normally lives and finds what it needs to survive and reproduce. | O75: =IF(M75=999,"",(" term_"&J75&": """&K75&"""")) -> term_hr: "Home range" | P75: =IF(M75="-","-",(" def_"&J75&": """&M75&"""")) -> def_hr: "The area within which an animal normally lives and finds what it needs to survive and reproduce." | U75: xx | V75: \" target=\"_blank\" data-bs-toggle=\"tooltip\" data-bs-title=\" | W75: \"> | X75: <button type=\"button\" class=\"btn btn-bd-tip-info-hidden btn-sm position-relative\">.<span class=\"position-absolute top-0 start-100 translate-middle\">{{ icon_info }}</span></button></a> | Y75: =IF(M75<>"-",(" "&J75&"_ti"&": "&""""&"<a href=\"&""""&"09_glossary.html#"&J75&V75&K75&": "&M75&W75&""&X75&""""),"-") -> hr_ti: "<a href=\"09_glossary.html#hr\" target=\"_blank\" data-bs-toggle=\"tooltip\" data-bs-title=\"Home range: The area within which an animal normally lives and finds what it needs to survive and reproduce.\"><button type=\"button\" class=\"btn btn-bd-tip-info-hidden btn-sm position-relative\">.<span class=\"position-absolute top-0 start-100 translate-middle\">{{ icon_info }}</span></button></a>"
C76: term | D76: - | G76: rc_tool | I76: hr_size | J76: =IF(D76<>"-",I76&"_"&D76,I76) -> hr_size | K76: Home range size | L76: =IF(VLOOKUP(J76,find_replace!H:H,1,"false")=J76,"TRUE","FALSE") -> #N/A | M76: The size of the area within which an animal normally lives and finds what it needs to survive and reproduce. | N76: the size of the area within which an animal normally lives and finds what it needs to survive and reproduce. | O76: =IF(M76=999,"",(" term_"&J76&": """&K76&"""")) -> term_hr_size: "Home range size" | P76: =IF(M76="-","-",(" def_"&J76&": """&M76&"""")) -> def_hr_size: "The size of the area within which an animal normally lives and finds what it needs to survive and reproduce." | U76: xx | V76: \" target=\"_blank\" data-bs-toggle=\"tooltip\" data-bs-title=\" | W76: \"> | X76: <button type=\"button\" class=\"btn btn-bd-tip-info-hidden btn-sm position-relative\">.<span class=\"position-absolute top-0 start-100 translate-middle\">{{ icon_info }}</span></button></a> | Y76: =IF(M76<>"-",(" "&J76&"_ti"&": "&""""&"<a href=\"&""""&"09_glossary.html#"&J76&V76&K76&": "&M76&W76&""&X76&""""),"-") -> hr_size_ti: "<a href=\"09_glossary.html#hr_size\" target=\"_blank\" data-bs-toggle=\"tooltip\" data-bs-title=\"Home range size: The size of the area within which an animal normally lives and finds what it needs to survive and reproduce.\"><button type=\"button\" class=\"btn btn-bd-tip-info-hidden btn-sm position-relative\">.<span class=\"position-absolute top-0 start-100 translate-middle\">{{ icon_info }}</span></button></a>"
B77: 62 | C77: field | D77: - | E77: **\*Human Transport Mode*/Activity** | F77: upper | G77: surv_guide_meta | H77: img_processing | I77: human_transport_mode_activity | J77: =IF(D77<>"-",I77&"_"&D77,I77) -> human_transport_mode_activity | K77: Human Transport Mode/Activity | L77: =IF(VLOOKUP(J77,find_replace!H:H,1,"false")=J77,"TRUE","FALSE") -> TRUE | M77: The activity performed or mode of transportation used by a human observed (e.g., hiker, skier, off-highway vehicle, etc.). This categorical field should be populated when data on humans (in addition to wildlife) are collected. Leave blank if not applicable and record 'Unknown' if not known. | N77: The activity performed or mode of transportation used by a human observed (e.g., hiker, skier, off-highway vehicle, etc.). This categorical field should be populated when data on humans (in addition to wildlife) are collected. Leave blank if not applicable and record 'Unknown' if not known. | O77: =IF(M77=999,"",(" term_"&J77&": """&K77&"""")) -> term_human_transport_mode_activity: "Human Transport Mode/Activity" | P77: =IF(M77="-","-",(" def_"&J77&": """&M77&"""")) -> def_human_transport_mode_activity: "The activity performed or mode of transportation used by a human observed (e.g., hiker, skier, off-highway vehicle, etc.). This categorical field should be populated when data on humans (in addition to wildlife) are collected. Leave blank if not applicable and record 'Unknown' if not known." | Q77: TRUE | R77: FALSE | S77: TRUE | T77: FALSE | U77: xx | V77: \" target=\"_blank\" data-bs-toggle=\"tooltip\" data-bs-title=\" | W77: \"> | X77: <button type=\"button\" class=\"btn btn-bd-tip-info-hidden btn-sm position-relative\">.<span class=\"position-absolute top-0 start-100 translate-middle\">{{ icon_info }}</span></button></a> | Y77: =IF(M77<>"-",(" "&J77&"_ti"&": "&""""&"<a href=\"&""""&"09_glossary.html#"&J77&V77&K77&": "&M77&W77&""&X77&""""),"-") -> human_transport_mode_activity_ti: "<a href=\"09_glossary.html#human_transport_mode_activity\" target=\"_blank\" data-bs-toggle=\"tooltip\" data-bs-title=\"Human Transport Mode/Activity: The activity performed or mode of transportation used by a human observed (e.g., hiker, skier, off-highway vehicle, etc.). This categorical field should be populated when data on humans (in addition to wildlife) are collected. Leave blank if not applicable and record 'Unknown' if not known.\"><button type=\"button\" class=\"btn btn-bd-tip-info-hidden btn-sm position-relative\">.<span class=\"position-absolute top-0 start-100 translate-middle\">{{ icon_info }}</span></button></a>"
B78: 63 | C78: term | D78: - | E78: Hurdle model (Mullahy, 1986; Heilbron 1994) | F78: upper | G78: surv_guide_meta | H78: approach | I78: mod_rai_hurdle | J78: =IF(D78<>"-",I78&"_"&D78,I78) -> mod_rai_hurdle | K78: Hurdle model (Mullahy, 1986; Heilbron 1994) | L78: =IF(VLOOKUP(J78,find_replace!H:H,1,"false")=J78,"TRUE","FALSE") -> TRUE | M78: A regression model used in the setting of excess zeros (zero-inflation) and overdispersion (Mullahy, 1986). Hurdle models (aka 'zero-altered' models) differ from zero-inflation models in that they are two-part models, and the zero and non-zero counts are modelling separately (thus, they are only adequate when the counting process cannot generate a zero value) (Blasco-Moreno et al., 2019). [relative abundance indices] | N78: A regression model used in the setting of excess zeros (zero-inflation) and overdispersion (Mullahy, 1986). Hurdle models (aka 'zero-altered' models) differ from zero-inflation models in that they are two-part models, and the zero and non-zero counts are modelling separately (thus, they are only adequate when the counting process cannot generate a zero value) (Blasco-Moreno et al., 2019). [relative abundance indices] | O78: =IF(M78=999,"",(" term_"&J78&": """&K78&"""")) -> term_mod_rai_hurdle: "Hurdle model (Mullahy, 1986; Heilbron 1994)" | P78: =IF(M78="-","-",(" def_"&J78&": """&M78&"""")) -> def_mod_rai_hurdle: "A regression model used in the setting of excess zeros (zero-inflation) and overdispersion (Mullahy, 1986). Hurdle models (aka 'zero-altered' models) differ from zero-inflation models in that they are two-part models, and the zero and non-zero counts are modelling separately (thus, they are only adequate when the counting process cannot generate a zero value) (Blasco-Moreno et al., 2019). [relative abundance indices]" | R78: NULL | S78: FALSE | T78: TRUE | U78: xx | V78: \" target=\"_blank\" data-bs-toggle=\"tooltip\" data-bs-title=\" | W78: \"> | X78: <button type=\"button\" class=\"btn btn-bd-tip-info-hidden btn-sm position-relative\">.<span class=\"position-absolute top-0 start-100 translate-middle\">{{ icon_info }}</span></button></a> | Y78: =IF(M78<>"-",(" "&J78&"_ti"&": "&""""&"<a href=\"&""""&"09_glossary.html#"&J78&V78&K78&": "&M78&W78&""&X78&""""),"-") -> mod_rai_hurdle_ti: "<a href=\"09_glossary.html#mod_rai_hurdle\" target=\"_blank\" data-bs-toggle=\"tooltip\" data-bs-title=\"Hurdle model (Mullahy, 1986; Heilbron 1994): A regression model used in the setting of excess zeros (zero-inflation) and overdispersion (Mullahy, 1986). Hurdle models (aka 'zero-altered' models) differ from zero-inflation models in that they are two-part models, and the zero and non-zero counts are modelling separately (thus, they are only adequate when the counting process cannot generate a zero value) (Blasco-Moreno et al., 2019). [relative abundance indices]\"><button type=\"button\" class=\"btn btn-bd-tip-info-hidden btn-sm position-relative\">.<span class=\"position-absolute top-0 start-100 translate-middle\">{{ icon_info }}</span></button></a>"
B79: 64 | C79: term | D79: - | E79: Image | G79: surv_guide_meta | H79: image | I79: image | J79: =IF(D79<>"-",I79&"_"&D79,I79) -> image | K79: Image | L79: =IF(VLOOKUP(J79,find_replace!H:H,1,"false")=J79,"TRUE","FALSE") -> TRUE | M79: An individual image captured by a camera, which may be part of a multi-image sequence (recorded as 'Image Name'). | N79: An individual image captured by a camera, which may be part of a multi-image sequence (recorded as 'Image Name'). | O79: =IF(M79=999,"",(" term_"&J79&": """&K79&"""")) -> term_image: "Image" | P79: =IF(M79="-","-",(" def_"&J79&": """&M79&"""")) -> def_image: "An individual image captured by a camera, which may be part of a multi-image sequence (recorded as 'Image Name')." | R79: NULL | S79: TRUE | T79: TRUE | U79: xx | V79: \" target=\"_blank\" data-bs-toggle=\"tooltip\" data-bs-title=\" | W79: \"> | X79: <button type=\"button\" class=\"btn btn-bd-tip-info-hidden btn-sm position-relative\">.<span class=\"position-absolute top-0 start-100 translate-middle\">{{ icon_info }}</span></button></a> | Y79: =IF(M79<>"-",(" "&J79&"_ti"&": "&""""&"<a href=\"&""""&"09_glossary.html#"&J79&V79&K79&": "&M79&W79&""&X79&""""),"-") -> image_ti: "<a href=\"09_glossary.html#image\" target=\"_blank\" data-bs-toggle=\"tooltip\" data-bs-title=\"Image: An individual image captured by a camera, which may be part of a multi-image sequence (recorded as 'Image Name').\"><button type=\"button\" class=\"btn btn-bd-tip-info-hidden btn-sm position-relative\">.<span class=\"position-absolute top-0 start-100 translate-middle\">{{ icon_info }}</span></button></a>"
B80: 65 | C80: term | D80: - | E80: Image classification | G80: surv_guide_meta | H80: img_processing | I80: img_classification | J80: =IF(D80<>"-",I80&"_"&D80,I80) -> img_classification | K80: Image classification | L80: =IF(VLOOKUP(J80,find_replace!H:H,1,"false")=J80,"TRUE","FALSE") -> TRUE | M80: The process of assigning class labels to an image according to the wildlife species, other entities (e.g., human, vehicle), or conditions within the image. Image classification can be performed manually or automatically by an artificial intelligence (AI) algorithm. Image classification is sometimes used interchangeably with 'image tagging.' | N80: The process of assigning class labels to an image according to the wildlife species, other entities (e.g., human, vehicle), or conditions within the image. Image classification can be performed manually or automatically by an artificial intelligence (AI) algorithm. Image classification is sometimes used interchangeably with 'image tagging.' | O80: =IF(M80=999,"",(" term_"&J80&": """&K80&"""")) -> term_img_classification: "Image classification" | P80: =IF(M80="-","-",(" def_"&J80&": """&M80&"""")) -> def_img_classification: "The process of assigning class labels to an image according to the wildlife species, other entities (e.g., human, vehicle), or conditions within the image. Image classification can be performed manually or automatically by an artificial intelligence (AI) algorithm. Image classification is sometimes used interchangeably with 'image tagging.'" | R80: NULL | S80: FALSE | T80: TRUE | U80: xx | V80: \" target=\"_blank\" data-bs-toggle=\"tooltip\" data-bs-title=\" | W80: \"> | X80: <button type=\"button\" class=\"btn btn-bd-tip-info-hidden btn-sm position-relative\">.<span class=\"position-absolute top-0 start-100 translate-middle\">{{ icon_info }}</span></button></a> | Y80: =IF(M80<>"-",(" "&J80&"_ti"&": "&""""&"<a href=\"&""""&"09_glossary.html#"&J80&V80&K80&": "&M80&W80&""&X80&""""),"-") -> img_classification_ti: "<a href=\"09_glossary.html#img_classification\" target=\"_blank\" data-bs-toggle=\"tooltip\" data-bs-title=\"Image classification: The process of assigning class labels to an image according to the wildlife species, other entities (e.g., human, vehicle), or conditions within the image. Image classification can be performed manually or automatically by an artificial intelligence (AI) algorithm. Image classification is sometimes used interchangeably with 'image tagging.'\"><button type=\"button\" class=\"btn btn-bd-tip-info-hidden btn-sm position-relative\">.<span class=\"position-absolute top-0 start-100 translate-middle\">{{ icon_info }}</span></button></a>"
B81: 66 | C81: term | D81: - | E81: Image classification confidence | G81: surv_guide_meta | H81: img_processing | I81: img_classification_confidence | J81: =IF(D81<>"-",I81&"_"&D81,I81) -> img_classification_confidence | K81: Image classification confidence | L81: =IF(VLOOKUP(J81,find_replace!H:H,1,"false")=J81,"TRUE","FALSE") -> TRUE | M81: The likelihood of an image containing an object of a certain class (Fennell et al., 2022). | N81: The likelihood of an image containing an object of a certain class (Fennell et al., 2022). | O81: =IF(M81=999,"",(" term_"&J81&": """&K81&"""")) -> term_img_classification_confidence: "Image classification confidence " | P81: =IF(M81="-","-",(" def_"&J81&": """&M81&"""")) -> def_img_classification_confidence: "The likelihood of an image containing an object of a certain class (Fennell et al., 2022)." | R81: NULL | S81: FALSE | T81: TRUE | U81: xx | V81: \" target=\"_blank\" data-bs-toggle=\"tooltip\" data-bs-title=\" | W81: \"> | X81: <button type=\"button\" class=\"btn btn-bd-tip-info-hidden btn-sm position-relative\">.<span class=\"position-absolute top-0 start-100 translate-middle\">{{ icon_info }}</span></button></a> | Y81: =IF(M81<>"-",(" "&J81&"_ti"&": "&""""&"<a href=\"&""""&"09_glossary.html#"&J81&V81&K81&": "&M81&W81&""&X81&""""),"-") -> img_classification_confidence_ti: "<a href=\"09_glossary.html#img_classification_confidence\" target=\"_blank\" data-bs-toggle=\"tooltip\" data-bs-title=\"Image classification confidence : The likelihood of an image containing an object of a certain class (Fennell et al., 2022).\"><button type=\"button\" class=\"btn btn-bd-tip-info-hidden btn-sm position-relative\">.<span class=\"position-absolute top-0 start-100 translate-middle\">{{ icon_info }}</span></button></a>"
B82: 67 | C82: field | D82: - | E82: **\*Image Flash Output** | F82: upper | G82: surv_guide_meta | H82: img_exif | I82: img_flash_output | J82: =IF(D82<>"-",I82&"_"&D82,I82) -> img_flash_output | K82: Image Flash Output | L82: =IF(VLOOKUP(J82,find_replace!H:H,1,"false")=J82,"TRUE","FALSE") -> TRUE | M82: The Image Flash Output is an image metadata field indicating the level of intensity of the flash [if enabled*/applicable]). Record as reported in the image Exif data (e.g., 'Flash Did Not Fire,' 'Auto'). This field is in text format; record 'Unknown' if not known; leave blank if not applicable. | N82: The Image Flash Output is an image metadata field indicating the level of intensity of the flash [if enabled*/applicable]). Record as reported in the image Exif data (e.g., 'Flash Did Not Fire,' 'Auto'). This field is in text format; record 'Unknown' if not known; leave blank if not applicable. | O82: =IF(M82=999,"",(" term_"&J82&": """&K82&"""")) -> term_img_flash_output: "Image Flash Output" | P82: =IF(M82="-","-",(" def_"&J82&": """&M82&"""")) -> def_img_flash_output: "The Image Flash Output is an image metadata field indicating the level of intensity of the flash [if enabled*/applicable]). Record as reported in the image Exif data (e.g., 'Flash Did Not Fire,' 'Auto'). This field is in text format; record 'Unknown' if not known; leave blank if not applicable." | Q82: TRUE | R82: FALSE | S82: TRUE | T82: FALSE | U82: xx | V82: \" target=\"_blank\" data-bs-toggle=\"tooltip\" data-bs-title=\" | W82: \"> | X82: <button type=\"button\" class=\"btn btn-bd-tip-info-hidden btn-sm position-relative\">.<span class=\"position-absolute top-0 start-100 translate-middle\">{{ icon_info }}</span></button></a> | Y82: =IF(M82<>"-",(" "&J82&"_ti"&": "&""""&"<a href=\"&""""&"09_glossary.html#"&J82&V82&K82&": "&M82&W82&""&X82&""""),"-") -> img_flash_output_ti: "<a href=\"09_glossary.html#img_flash_output\" target=\"_blank\" data-bs-toggle=\"tooltip\" data-bs-title=\"Image Flash Output: The Image Flash Output is an image metadata field indicating the level of intensity of the flash [if enabled*/applicable]). Record as reported in the image Exif data (e.g., 'Flash Did Not Fire,' 'Auto'). This field is in text format; record 'Unknown' if not known; leave blank if not applicable.\"><button type=\"button\" class=\"btn btn-bd-tip-info-hidden btn-sm position-relative\">.<span class=\"position-absolute top-0 start-100 translate-middle\">{{ icon_info }}</span></button></a>"
B83: 68 | C83: field | D83: - | E83: **\*Image Infrared Illuminator | F83: upper | G83: surv_guide_meta | H83: img_exif | I83: img_infrared_illuminator | J83: =IF(D83<>"-",I83&"_"&D83,I83) -> img_infrared_illuminator | K83: Image Infrared Illuminator | L83: =IF(VLOOKUP(J83,find_replace!H:H,1,"false")=J83,"TRUE","FALSE") -> TRUE | M83: The Image Infrared Illuminator is an image metadata field indicating whether the infrared illuminator setting was enabled (if applicable; to obtain greater visibility at night by producing infrared light). Record as reported in the image Exif data (e.g., 'On' or 'Off'). This field is categorical; leave blank if not applicable and record 'Unknown' if not known. | N83: The Image Infrared Illuminator is an image metadata field indicating whether the infrared illuminator setting was enabled (if applicable; to obtain greater visibility at night by producing infrared light). Record as reported in the image Exif data (e.g., 'On' or 'Off'). This field is categorical; leave blank if not applicable and record 'Unknown' if not known. | O83: =IF(M83=999,"",(" term_"&J83&": """&K83&"""")) -> term_img_infrared_illuminator: "Image Infrared Illuminator" | P83: =IF(M83="-","-",(" def_"&J83&": """&M83&"""")) -> def_img_infrared_illuminator: "The Image Infrared Illuminator is an image metadata field indicating whether the infrared illuminator setting was enabled (if applicable; to obtain greater visibility at night by producing infrared light). Record as reported in the image Exif data (e.g., 'On' or 'Off'). This field is categorical; leave blank if not applicable and record 'Unknown' if not known." | Q83: TRUE | R83: FALSE | S83: TRUE | T83: FALSE | U83: xx | V83: \" target=\"_blank\" data-bs-toggle=\"tooltip\" data-bs-title=\" | W83: \"> | X83: <button type=\"button\" class=\"btn btn-bd-tip-info-hidden btn-sm position-relative\">.<span class=\"position-absolute top-0 start-100 translate-middle\">{{ icon_info }}</span></button></a> | Y83: =IF(M83<>"-",(" "&J83&"_ti"&": "&""""&"<a href=\"&""""&"09_glossary.html#"&J83&V83&K83&": "&M83&W83&""&X83&""""),"-") -> img_infrared_illuminator_ti: "<a href=\"09_glossary.html#img_infrared_illuminator\" target=\"_blank\" data-bs-toggle=\"tooltip\" data-bs-title=\"Image Infrared Illuminator: The Image Infrared Illuminator is an image metadata field indicating whether the infrared illuminator setting was enabled (if applicable; to obtain greater visibility at night by producing infrared light). Record as reported in the image Exif data (e.g., 'On' or 'Off'). This field is categorical; leave blank if not applicable and record 'Unknown' if not known.\"><button type=\"button\" class=\"btn btn-bd-tip-info-hidden btn-sm position-relative\">.<span class=\"position-absolute top-0 start-100 translate-middle\">{{ icon_info }}</span></button></a>"
B84: 69 | C84: field | D84: - | E84: **Image Name** | F84: upper | G84: surv_guide_meta | H84: cam_visit_equip | I84: img_name | J84: =IF(D84<>"-",I84&"_"&D84,I84) -> img_name | K84: Image Name | L84: =IF(VLOOKUP(J84,find_replace!H:H,1,"false")=J84,"TRUE","FALSE") -> TRUE | M84: A unique alphanumeric identifier for the image. It is important to include (at a minimum) the camera location, date, time, and image number when generating an Image Name to avoid duplicate file names (e.g., 'bh1_17-Jul-2018_P900FF04152022_22-Jul-2018 10:34:22_img_100' or 'bh1_17-Jul-2018_22-Jul-2018_10:34:22_img_100'). | N84: A unique alphanumeric identifier for the image. It is important to include (at a minimum) the camera location, date, time, and image number when generating an Image Name to avoid duplicate file names (e.g., 'bh1_17-Jul-2018_P900FF04152022_22-Jul-2018 10:34:22_img_100' or 'bh1_17-Jul-2018_22-Jul-2018_10:34:22_img_100'). | O84: =IF(M84=999,"",(" term_"&J84&": """&K84&"""")) -> term_img_name: "Image Name" | P84: =IF(M84="-","-",(" def_"&J84&": """&M84&"""")) -> def_img_name: "A unique alphanumeric identifier for the image. It is important to include (at a minimum) the camera location, date, time, and image number when generating an Image Name to avoid duplicate file names (e.g., 'bh1_17-Jul-2018_P900FF04152022_22-Jul-2018 10:34:22_img_100' or 'bh1_17-Jul-2018_22-Jul-2018_10:34:22_img_100')." | R84: TRUE | S84: TRUE | T84: TRUE | U84: xx | V84: \" target=\"_blank\" data-bs-toggle=\"tooltip\" data-bs-title=\" | W84: \"> | X84: <button type=\"button\" class=\"btn btn-bd-tip-info-hidden btn-sm position-relative\">.<span class=\"position-absolute top-0 start-100 translate-middle\">{{ icon_info }}</span></button></a> | Y84: =IF(M84<>"-",(" "&J84&"_ti"&": "&""""&"<a href=\"&""""&"09_glossary.html#"&J84&V84&K84&": "&M84&W84&""&X84&""""),"-") -> img_name_ti: "<a href=\"09_glossary.html#img_name\" target=\"_blank\" data-bs-toggle=\"tooltip\" data-bs-title=\"Image Name: A unique alphanumeric identifier for the image. It is important to include (at a minimum) the camera location, date, time, and image number when generating an Image Name to avoid duplicate file names (e.g., 'bh1_17-Jul-2018_P900FF04152022_22-Jul-2018 10:34:22_img_100' or 'bh1_17-Jul-2018_22-Jul-2018_10:34:22_img_100').\"><button type=\"button\" class=\"btn btn-bd-tip-info-hidden btn-sm position-relative\">.<span class=\"position-absolute top-0 start-100 translate-middle\">{{ icon_info }}</span></button></a>"
B85: 70 | C85: term | D85: - | E85: Image processing | G85: surv_guide_meta | H85: img_processing | I85: img_processing | J85: =IF(D85<>"-",I85&"_"&D85,I85) -> img_processing | K85: Image processing | L85: =IF(VLOOKUP(J85,find_replace!H:H,1,"false")=J85,"TRUE","FALSE") -> TRUE | M85: The series of operations that are taken to extract information from images. In the case of remote camera data, it can include loading the images into a processing platform, extracting information from the image metadata (e.g., the date and time the image was taken), running an artificial intelligence (AI) algorithm to identify empty images, classifying animals or other entities within the image. | N85: The series of operations that are taken to extract information from images. In the case of remote camera data, it can include loading the images into a processing platform, extracting information from the image metadata (e.g., the date and time the image was taken), running an artificial intelligence (AI) algorithm to identify empty images, classifying animals or other entities within the image. | O85: =IF(M85=999,"",(" term_"&J85&": """&K85&"""")) -> term_img_processing: "Image processing" | P85: =IF(M85="-","-",(" def_"&J85&": """&M85&"""")) -> def_img_processing: "The series of operations that are taken to extract information from images. In the case of remote camera data, it can include loading the images into a processing platform, extracting information from the image metadata (e.g., the date and time the image was taken), running an artificial intelligence (AI) algorithm to identify empty images, classifying animals or other entities within the image." | R85: NULL | S85: TRUE | T85: TRUE | U85: xx | V85: \" target=\"_blank\" data-bs-toggle=\"tooltip\" data-bs-title=\" | W85: \"> | X85: <button type=\"button\" class=\"btn btn-bd-tip-info-hidden btn-sm position-relative\">.<span class=\"position-absolute top-0 start-100 translate-middle\">{{ icon_info }}</span></button></a> | Y85: =IF(M85<>"-",(" "&J85&"_ti"&": "&""""&"<a href=\"&""""&"09_glossary.html#"&J85&V85&K85&": "&M85&W85&""&X85&""""),"-") -> img_processing_ti: "<a href=\"09_glossary.html#img_processing\" target=\"_blank\" data-bs-toggle=\"tooltip\" data-bs-title=\"Image processing: The series of operations that are taken to extract information from images. In the case of remote camera data, it can include loading the images into a processing platform, extracting information from the image metadata (e.g., the date and time the image was taken), running an artificial intelligence (AI) algorithm to identify empty images, classifying animals or other entities within the image.\"><button type=\"button\" class=\"btn btn-bd-tip-info-hidden btn-sm position-relative\">.<span class=\"position-absolute top-0 start-100 translate-middle\">{{ icon_info }}</span></button></a>"
B86: 71 | C86: term | D86: - | E86: Image Sequence | F86: upper | G86: surv_guide_meta | H86: img_processing | I86: img_sequence | J86: =IF(D86<>"-",I86&"_"&D86,I86) -> img_sequence | K86: Image Sequence | L86: =IF(VLOOKUP(J86,find_replace!H:H,1,"false")=J86,"TRUE","FALSE") -> TRUE | M86: The order of the image in a rapid-fire sequence as reported in the image Exif data (text; e.g., '1 of 1' or '1 of 3'). Leave blank if not applicable. | N86: The order of the image in a rapid-fire sequence as reported in the image Exif data (text; e.g., '1 of 1' or '1 of 3'). Leave blank if not applicable. | O86: =IF(M86=999,"",(" term_"&J86&": """&K86&"""")) -> term_img_sequence: "Image Sequence" | P86: =IF(M86="-","-",(" def_"&J86&": """&M86&"""")) -> def_img_sequence: "The order of the image in a rapid-fire sequence as reported in the image Exif data (text; e.g., '1 of 1' or '1 of 3'). Leave blank if not applicable." | Q86: TRUE | R86: NULL | S86: TRUE | T86: FALSE | U86: xx | V86: \" target=\"_blank\" data-bs-toggle=\"tooltip\" data-bs-title=\" | W86: \"> | X86: <button type=\"button\" class=\"btn btn-bd-tip-info-hidden btn-sm position-relative\">.<span class=\"position-absolute top-0 start-100 translate-middle\">{{ icon_info }}</span></button></a> | Y86: =IF(M86<>"-",(" "&J86&"_ti"&": "&""""&"<a href=\"&""""&"09_glossary.html#"&J86&V86&K86&": "&M86&W86&""&X86&""""),"-") -> img_sequence_ti: "<a href=\"09_glossary.html#img_sequence\" target=\"_blank\" data-bs-toggle=\"tooltip\" data-bs-title=\"Image Sequence: The order of the image in a rapid-fire sequence as reported in the image Exif data (text; e.g., '1 of 1' or '1 of 3'). Leave blank if not applicable.\"><button type=\"button\" class=\"btn btn-bd-tip-info-hidden btn-sm position-relative\">.<span class=\"position-absolute top-0 start-100 translate-middle\">{{ icon_info }}</span></button></a>"
B87: 72 | C87: field | D87: - | E87: **Image Set End Date Time (DD-MMM-YYYY HH:MM:SS)** | F87: upper | G87: surv_guide_meta | H87: img_set | I87: img_set_end_date_time | J87: =IF(D87<>"-",I87&"_"&D87,I87) -> img_set_end_date_time | K87: Image Set End Date Time (DD-MMM-YYYY HH:MM:SS) | L87: =IF(VLOOKUP(J87,find_replace!H:H,1,"false")=J87,"TRUE","FALSE") -> TRUE | M87: The date and time of the last image or video collected during a specific deployment (e.g., '17-Jan-2018 22:10:05'). <br> <br> The Image Set End Date Time may not coincide with the deployment end date time. Recording this field allows users to account for deployments that were conducted but for which no data was found and to confirm the last date and time a camera was active (if functioning) if no images or videos were captured prior to Service*/Retrieval (especially valuable if users did not collect Time-lapse images or if the camera malfunctioned). | N87: The date and time of the last image or video collected during a specific deployment (e.g., '17-Jan-2018 22:10:05'). <br> <br> The Image Set End Date Time may not coincide with the deployment end date time. Recording this field allows users to account for deployments that were conducted but for which no data was found and to confirm the last date and time a camera was active (if functioning) if no images or videos were captured prior to Service*/Retrieval (especially valuable if users did not collect Time-lapse images or if the camera malfunctioned). | O87: =IF(M87=999,"",(" term_"&J87&": """&K87&"""")) -> term_img_set_end_date_time: "Image Set End Date Time (DD-MMM-YYYY HH:MM:SS)" | P87: =IF(M87="-","-",(" def_"&J87&": """&M87&"""")) -> def_img_set_end_date_time: "The date and time of the last image or video collected during a specific deployment (e.g., '17-Jan-2018 22:10:05'). <br> <br> The Image Set End Date Time may not coincide with the deployment end date time. Recording this field allows users to account for deployments that were conducted but for which no data was found and to confirm the last date and time a camera was active (if functioning) if no images or videos were captured prior to Service*/Retrieval (especially valuable if users did not collect Time-lapse images or if the camera malfunctioned)." | R87: TRUE | S87: TRUE | T87: TRUE | U87: xx | V87: \" target=\"_blank\" data-bs-toggle=\"tooltip\" data-bs-title=\" | W87: \"> | X87: <button type=\"button\" class=\"btn btn-bd-tip-info-hidden btn-sm position-relative\">.<span class=\"position-absolute top-0 start-100 translate-middle\">{{ icon_info }}</span></button></a> | Y87: =IF(M87<>"-",(" "&J87&"_ti"&": "&""""&"<a href=\"&""""&"09_glossary.html#"&J87&V87&K87&": "&M87&W87&""&X87&""""),"-") -> img_set_end_date_time_ti: "<a href=\"09_glossary.html#img_set_end_date_time\" target=\"_blank\" data-bs-toggle=\"tooltip\" data-bs-title=\"Image Set End Date Time (DD-MMM-YYYY HH:MM:SS): The date and time of the last image or video collected during a specific deployment (e.g., '17-Jan-2018 22:10:05'). <br> <br> The Image Set End Date Time may not coincide with the deployment end date time. Recording this field allows users to account for deployments that were conducted but for which no data was found and to confirm the last date and time a camera was active (if functioning) if no images or videos were captured prior to Service*/Retrieval (especially valuable if users did not collect Time-lapse images or if the camera malfunctioned).\"><button type=\"button\" class=\"btn btn-bd-tip-info-hidden btn-sm position-relative\">.<span class=\"position-absolute top-0 start-100 translate-middle\">{{ icon_info }}</span></button></a>"
B88: 73 | C88: field | D88: - | E88: **Image Set Start Date Time (DD-MMM-YYYY HH:MM:SS)** | F88: upper | G88: surv_guide_meta | H88: img_set | I88: img_set_start_date_time | J88: =IF(D88<>"-",I88&"_"&D88,I88) -> img_set_start_date_time | K88: Image Set Start Date Time (DD-MMM-YYYY HH:MM:SS) | L88: =IF(VLOOKUP(J88,find_replace!H:H,1,"false")=J88,"TRUE","FALSE") -> TRUE | M88: The date and time of the first image or video collected during a specific deployment (e.g., '17-Jan-2018 12:00:02'). <br><br> The Image Set Start Date Time may not coincide with the Deployment Start Date Time. Recording this field allows users to confirm the first date and time a camera was active (reliable if Time-lapse images were collected; especially valuable if the user scheduled a start delay). | N88: The date and time of the first image or video collected during a specific deployment (e.g., '17-Jan-2018 12:00:02'). <br><br> The Image Set Start Date Time may not coincide with the Deployment Start Date Time. Recording this field allows users to confirm the first date and time a camera was active (reliable if Time-lapse images were collected; especially valuable if the user scheduled a start delay). | O88: =IF(M88=999,"",(" term_"&J88&": """&K88&"""")) -> term_img_set_start_date_time: "Image Set Start Date Time (DD-MMM-YYYY HH:MM:SS)" | P88: =IF(M88="-","-",(" def_"&J88&": """&M88&"""")) -> def_img_set_start_date_time: "The date and time of the first image or video collected during a specific deployment (e.g., '17-Jan-2018 12:00:02'). <br><br> The Image Set Start Date Time may not coincide with the Deployment Start Date Time. Recording this field allows users to confirm the first date and time a camera was active (reliable if Time-lapse images were collected; especially valuable if the user scheduled a start delay)." | R88: TRUE | S88: TRUE | T88: TRUE | U88: xx | V88: \" target=\"_blank\" data-bs-toggle=\"tooltip\" data-bs-title=\" | W88: \"> | X88: <button type=\"button\" class=\"btn btn-bd-tip-info-hidden btn-sm position-relative\">.<span class=\"position-absolute top-0 start-100 translate-middle\">{{ icon_info }}</span></button></a> | Y88: =IF(M88<>"-",(" "&J88&"_ti"&": "&""""&"<a href=\"&""""&"09_glossary.html#"&J88&V88&K88&": "&M88&W88&""&X88&""""),"-") -> img_set_start_date_time_ti: "<a href=\"09_glossary.html#img_set_start_date_time\" target=\"_blank\" data-bs-toggle=\"tooltip\" data-bs-title=\"Image Set Start Date Time (DD-MMM-YYYY HH:MM:SS): The date and time of the first image or video collected during a specific deployment (e.g., '17-Jan-2018 12:00:02'). <br><br> The Image Set Start Date Time may not coincide with the Deployment Start Date Time. Recording this field allows users to confirm the first date and time a camera was active (reliable if Time-lapse images were collected; especially valuable if the user scheduled a start delay).\"><button type=\"button\" class=\"btn btn-bd-tip-info-hidden btn-sm position-relative\">.<span class=\"position-absolute top-0 start-100 translate-middle\">{{ icon_info }}</span></button></a>"
B89: 74 | C89: term | D89: - | E89: Image tagging | G89: surv_guide_meta | H89: img_processing | I89: img_tagging | J89: =IF(D89<>"-",I89&"_"&D89,I89) -> img_tagging | K89: Image tagging | L89: =IF(VLOOKUP(J89,find_replace!H:H,1,"false")=J89,"TRUE","FALSE") -> TRUE | M89: The process of classifying an image according to the wildlife species, other entities (e.g., human, vehicle), or conditions within the image. Image tagging may follow image classification to further classify characteristics of the individuals (e.g., age class, sex class, or behaviour) or entities within the image. | N89: The process of classifying an image according to the wildlife species, other entities (e.g., human, vehicle), or conditions within the image. Image tagging may follow image classification to further classify characteristics of the individuals (e.g., age class, sex class, or behaviour) or entities within the image. | O89: =IF(M89=999,"",(" term_"&J89&": """&K89&"""")) -> term_img_tagging: "Image tagging" | P89: =IF(M89="-","-",(" def_"&J89&": """&M89&"""")) -> def_img_tagging: "The process of classifying an image according to the wildlife species, other entities (e.g., human, vehicle), or conditions within the image. Image tagging may follow image classification to further classify characteristics of the individuals (e.g., age class, sex class, or behaviour) or entities within the image." | R89: NULL | S89: FALSE | T89: TRUE | U89: xx | V89: \" target=\"_blank\" data-bs-toggle=\"tooltip\" data-bs-title=\" | W89: \"> | X89: <button type=\"button\" class=\"btn btn-bd-tip-info-hidden btn-sm position-relative\">.<span class=\"position-absolute top-0 start-100 translate-middle\">{{ icon_info }}</span></button></a> | Y89: =IF(M89<>"-",(" "&J89&"_ti"&": "&""""&"<a href=\"&""""&"09_glossary.html#"&J89&V89&K89&": "&M89&W89&""&X89&""""),"-") -> img_tagging_ti: "<a href=\"09_glossary.html#img_tagging\" target=\"_blank\" data-bs-toggle=\"tooltip\" data-bs-title=\"Image tagging: The process of classifying an image according to the wildlife species, other entities (e.g., human, vehicle), or conditions within the image. Image tagging may follow image classification to further classify characteristics of the individuals (e.g., age class, sex class, or behaviour) or entities within the image.\"><button type=\"button\" class=\"btn btn-bd-tip-info-hidden btn-sm position-relative\">.<span class=\"position-absolute top-0 start-100 translate-middle\">{{ icon_info }}</span></button></a>"
B90: 75 | C90: field | D90: - | E90: **\*Image Trigger Mode | F90: upper | G90: surv_guide_meta | H90: img_exif | I90: img_trigger_mode | J90: =IF(D90<>"-",I90&"_"&D90,I90) -> img_trigger_mode | K90: Image Trigger Mode | L90: =IF(VLOOKUP(J90,find_replace!H:H,1,"false")=J90,"TRUE","FALSE") -> TRUE | M90: The type of trigger mode used to capture the image as reported in the image Exif data (e.g., 'Time Lapse,' 'Motion Detection,' 'CodeLoc Not Entered,' 'External Sensor'). Record 'Unknown' if not known. | N90: The type of trigger mode used to capture the image as reported in the image Exif data (e.g., 'Time Lapse,' 'Motion Detection,' 'CodeLoc Not Entered,' 'External Sensor'). Record 'Unknown' if not known. | O90: =IF(M90=999,"",(" term_"&J90&": """&K90&"""")) -> term_img_trigger_mode: "Image Trigger Mode" | P90: =IF(M90="-","-",(" def_"&J90&": """&M90&"""")) -> def_img_trigger_mode: "The type of trigger mode used to capture the image as reported in the image Exif data (e.g., 'Time Lapse,' 'Motion Detection,' 'CodeLoc Not Entered,' 'External Sensor'). Record 'Unknown' if not known." | Q90: TRUE | R90: FALSE | S90: TRUE | T90: FALSE | U90: xx | V90: \" target=\"_blank\" data-bs-toggle=\"tooltip\" data-bs-title=\" | W90: \"> | X90: <button type=\"button\" class=\"btn btn-bd-tip-info-hidden btn-sm position-relative\">.<span class=\"position-absolute top-0 start-100 translate-middle\">{{ icon_info }}</span></button></a> | Y90: =IF(M90<>"-",(" "&J90&"_ti"&": "&""""&"<a href=\"&""""&"09_glossary.html#"&J90&V90&K90&": "&M90&W90&""&X90&""""),"-") -> img_trigger_mode_ti: "<a href=\"09_glossary.html#img_trigger_mode\" target=\"_blank\" data-bs-toggle=\"tooltip\" data-bs-title=\"Image Trigger Mode: The type of trigger mode used to capture the image as reported in the image Exif data (e.g., 'Time Lapse,' 'Motion Detection,' 'CodeLoc Not Entered,' 'External Sensor'). Record 'Unknown' if not known.\"><button type=\"button\" class=\"btn btn-bd-tip-info-hidden btn-sm position-relative\">.<span class=\"position-absolute top-0 start-100 translate-middle\">{{ icon_info }}</span></button></a>"
B91: 76 | C91: field | D91: - | E91: **\*Image*/Sequence Comments | F91: upper | G91: surv_guide_meta | H91: image | I91: img_sequence_comments | J91: =IF(D91<>"-",I91&"_"&D91,I91) -> img_sequence_comments | K91: Image/Sequence Comments | L91: =IF(VLOOKUP(J91,find_replace!H:H,1,"false")=J91,"TRUE","FALSE") -> TRUE | M91: Comments describing additional details about the image*/sequence. | N91: Comments describing additional details about the image*/sequence. | O91: =IF(M91=999,"",(" term_"&J91&": """&K91&"""")) -> term_img_sequence_comments: "Image/Sequence Comments" | P91: =IF(M91="-","-",(" def_"&J91&": """&M91&"""")) -> def_img_sequence_comments: "Comments describing additional details about the image*/sequence." | R91: FALSE | S91: TRUE | T91: FALSE | U91: xx | V91: \" target=\"_blank\" data-bs-toggle=\"tooltip\" data-bs-title=\" | W91: \"> | X91: <button type=\"button\" class=\"btn btn-bd-tip-info-hidden btn-sm position-relative\">.<span class=\"position-absolute top-0 start-100 translate-middle\">{{ icon_info }}</span></button></a> | Y91: =IF(M91<>"-",(" "&J91&"_ti"&": "&""""&"<a href=\"&""""&"09_glossary.html#"&J91&V91&K91&": "&M91&W91&""&X91&""""),"-") -> img_sequence_comments_ti: "<a href=\"09_glossary.html#img_sequence_comments\" target=\"_blank\" data-bs-toggle=\"tooltip\" data-bs-title=\"Image/Sequence Comments: Comments describing additional details about the image*/sequence.\"><button type=\"button\" class=\"btn btn-bd-tip-info-hidden btn-sm position-relative\">.<span class=\"position-absolute top-0 start-100 translate-middle\">{{ icon_info }}</span></button></a>"
